Workbook

Sheet Sheet1
A1: Order ID | B1: Customer ID | C1: Order Date | D1: Ship Date | E1: City | F1: State | G1: Sales Channel | H1: Payment Method | I1: Product Category | J1: Product Name | K1: Brand | L1: Units Sold | M1: Unit Price | N1: Total Price | O1: Discount % | P1: Discount amount | Q1: Price after discount | R1: Price Category | S1: Unit Category | T1: Discount Category
A2: 10001 | B2: 1102 | C2: 45197 | D2: 45203 | E2: Chennai | F2: Delhi | G2: Mobile App | H2: Credit Card | I2: Home & Kitchen | J2: Mixer Grinder | K2: BrandA | L2: 7 | M2: 2843.87 | N2: =L2*M2 -> 19907.09 | O2: 0 | P2: =N2*O2/100 -> 0 | Q2: =N2-P2 -> 19907.09 | R2: =IF(Q2>=10000,"High","Low") -> High | S2: {=_xlfn.IFS(L2>=8,"High",L2>=5,"Medium",L2<5,"Low")} -> Medium | T2: =IF(P2>=3000,"High",IF(P2>=1500,"Medium","Low")) -> Low | V2: Brand Name | W2: Units Sold | Y2: Average Units Sold
A3: 10002 | B3: 1435 | C3: 45199 | D3: 45203 | E3: Pune | F3: Tamil Nadu | G3: Website | H3: Debit Card | I3: Sports | J3: Football | K3: BrandD | L3: 9 | M3: 2525.23 | N3: =L3*M3 -> 22727.07 | O3: 5 | P3: =N3*O3/100 -> 1136.3535 | Q3: =N3-P3 -> 21590.716 | R3: =IF(Q3>=10000,"High","Low") -> High | S3: {=_xlfn.IFS(L3>=8,"High",L3>=5,"Medium",L3<5,"Low")} -> High | T3: =IF(P3>=3000,"High",IF(P3>=1500,"Medium","Low")) -> Low | V3: BrandB | W3: =SUMIF(K2:K373,V3,L2:L373) -> 354 | Y3: =AVERAGE(L2:L373) -> 4.938172
A4: 10003 | B4: 1860 | C4: 45109 | D4: 45114 | E4: Chennai | F4: West Bengal | G4: Marketplace | H4: Debit Card | I4: Fashion | J4: Sneakers | K4: BrandE | L4: 6 | M4: 3474.34 | N4: =L4*M4 -> 20846.04 | O4: 15 | P4: =N4*O4/100 -> 3126.906 | Q4: =N4-P4 -> 17719.134 | R4: =IF(Q4>=10000,"High","Low") -> High | S4: {=_xlfn.IFS(L4>=8,"High",L4>=5,"Medium",L4<5,"Low")} -> Medium | T4: =IF(P4>=3000,"High",IF(P4>=1500,"Medium","Low")) -> High
A5: 10004 | B5: 1270 | C5: 45079 | D5: 45087 | E5: Bengaluru | F5: West Bengal | G5: Website | H5: Cash on Delivery | I5: Sports | J5: Yoga Mat | K5: BrandA | L5: 1 | M5: 1008.79 | N5: =L5*M5 -> 1008.79 | O5: 15 | P5: =N5*O5/100 -> 151.3185 | Q5: =N5-P5 -> 857.4715 | R5: =IF(Q5>=10000,"High","Low") -> Low | S5: {=_xlfn.IFS(L5>=8,"High",L5>=5,"Medium",L5<5,"Low")} -> Low | T5: =IF(P5>=3000,"High",IF(P5>=1500,"Medium","Low")) -> Low
A6: 10005 | B6: 1106 | C6: 45241 | D6: 45244 | E6: Kolkata | F6: Karnataka | G6: Marketplace | H6: Credit Card | I6: Fashion | J6: Jacket | K6: BrandA | L6: 7 | M6: 3511.47 | N6: =L6*M6 -> 24580.29 | O6: 20 | P6: =N6*O6/100 -> 4916.058 | Q6: =N6-P6 -> 19664.232 | R6: =IF(Q6>=10000,"High","Low") -> High | S6: {=_xlfn.IFS(L6>=8,"High",L6>=5,"Medium",L6<5,"Low")} -> Medium | T6: =IF(P6>=3000,"High",IF(P6>=1500,"Medium","Low")) -> High | V6: Product Category | W6: Brand Name | X6: Units Sold
A7: 10006 | B7: 1071 | C7: 45260 | D7: 45263 | E7: Hyderabad | F7: Telangana | G7: Website | H7: Net Banking | I7: Home & Kitchen | J7: Bedsheet | K7: BrandE | L7: 3 | M7: 3189.55 | N7: =L7*M7 -> 9568.65 | O7: 10 | P7: =N7*O7/100 -> 956.865 | Q7: =N7-P7 -> 8611.785 | R7: =IF(Q7>=10000,"High","Low") -> Low | S7: {=_xlfn.IFS(L7>=8,"High",L7>=5,"Medium",L7<5,"Low")} -> Low | T7: =IF(P7>=3000,"High",IF(P7>=1500,"Medium","Low")) -> Low | V7: Beauty | W7: BrandE | X7: =SUMIFS(L2:L373,I2:I373,V7,K2:K373,W7) -> 89
A8: 10007 | B8: 1700 | C8: 45050 | D8: 45054 | E8: Bengaluru | F8: Telangana | G8: Mobile App | H8: UPI | I8: Fashion | J8: Sneakers | K8: BrandC | L8: 5 | M8: 3030.42 | N8: =L8*M8 -> 15152.1 | O8: 10 | P8: =N8*O8/100 -> 1515.21 | Q8: =N8-P8 -> 13636.89 | R8: =IF(Q8>=10000,"High","Low") -> High | S8: {=_xlfn.IFS(L8>=8,"High",L8>=5,"Medium",L8<5,"Low")} -> Medium | T8: =IF(P8>=3000,"High",IF(P8>=1500,"Medium","Low")) -> Medium
A9: 10008 | B9: 1020 | C9: 45040 | D9: 45041 | E9: Mumbai | F9: Delhi | G9: Website | H9: Credit Card | I9: Fashion | J9: Sneakers | K9: BrandB | L9: 4 | M9: 2310.83 | N9: =L9*M9 -> 9243.32 | O9: 10 | P9: =N9*O9/100 -> 924.332 | Q9: =N9-P9 -> 8318.988 | R9: =IF(Q9>=10000,"High","Low") -> Low | S9: {=_xlfn.IFS(L9>=8,"High",L9>=5,"Medium",L9<5,"Low")} -> Low | T9: =IF(P9>=3000,"High",IF(P9>=1500,"Medium","Low")) -> Low
A10: 10009 | B10: 1614 | C10: 45204 | D10: 45213 | E10: Chennai | F10: West Bengal | G10: Website | H10: Debit Card | I10: Fashion | J10: T-Shirt | K10: BrandD | L10: 5 | M10: 1098.04 | N10: =L10*M10 -> 5490.2 | O10: 15 | P10: =N10*O10/100 -> 823.53 | Q10: =N10-P10 -> 4666.67 | R10: =IF(Q10>=10000,"High","Low") -> Low | S10: {=_xlfn.IFS(L10>=8,"High",L10>=5,"Medium",L10<5,"Low")} -> Medium | T10: =IF(P10>=3000,"High",IF(P10>=1500,"Medium","Low")) -> Low | V10: Brand Name | W10: Average Units Sold
A11: 10010 | B11: 1121 | C11: 45139 | D11: 45147 | E11: Bengaluru | F11: Karnataka | G11: Website | H11: Cash on Delivery | I11: Electronics | J11: Headphones | K11: BrandB | L11: 5 | M11: 1780.66 | N11: =L11*M11 -> 8903.3 | O11: 20 | P11: =N11*O11/100 -> 1780.66 | Q11: =N11-P11 -> 7122.64 | R11: =IF(Q11>=10000,"High","Low") -> Low | S11: {=_xlfn.IFS(L11>=8,"High",L11>=5,"Medium",L11<5,"Low")} -> Medium | T11: =IF(P11>=3000,"High",IF(P11>=1500,"Medium","Low")) -> Medium | V11: BrandB | W11: =AVERAGEIF(K2:K373,V11,L2:L373) -> 4.7837838 | X11: =AVERAGEIF(K2:K373,V11,L2:L373) -> 4.7837838
A12: 10011 | B12: 1466 | C12: 45098 | D12: 45106 | E12: Bengaluru | F12: Karnataka | G12: Mobile App | H12: Cash on Delivery | I12: Electronics | J12: Headphones | K12: BrandE | L12: 6 | M12: 3205.25 | N12: =L12*M12 -> 19231.5 | O12: 0 | P12: =N12*O12/100 -> 0 | Q12: =N12-P12 -> 19231.5 | R12: =IF(Q12>=10000,"High","Low") -> High | S12: {=_xlfn.IFS(L12>=8,"High",L12>=5,"Medium",L12<5,"Low")} -> Medium | T12: =IF(P12>=3000,"High",IF(P12>=1500,"Medium","Low")) -> Low
A13: 10012 | B13: 1214 | C13: 45214 | D13: 45220 | E13: Mumbai | F13: Tamil Nadu | G13: Website | H13: UPI | I13: Electronics | J13: Smartwatch | K13: BrandA | L13: 6 | M13: 272.35 | N13: =L13*M13 -> 1634.1 | O13: 5 | P13: =N13*O13/100 -> 81.705 | Q13: =N13-P13 -> 1552.395 | R13: =IF(Q13>=10000,"High","Low") -> Low | S13: {=_xlfn.IFS(L13>=8,"High",L13>=5,"Medium",L13<5,"Low")} -> Medium | T13: =IF(P13>=3000,"High",IF(P13>=1500,"Medium","Low")) -> Low | V13: Product Category | W13: Brand Name | X13: Average Units Sold
A14: 10013 | B14: 1330 | C14: 45100 | D14: 45107 | E14: Delhi | F14: Tamil Nadu | G14: Mobile App | H14: Cash on Delivery | I14: Home & Kitchen | J14: Bedsheet | K14: BrandA | L14: 8 | M14: 3160.9 | N14: =L14*M14 -> 25287.2 | O14: 0 | P14: =N14*O14/100 -> 0 | Q14: =N14-P14 -> 25287.2 | R14: =IF(Q14>=10000,"High","Low") -> High | S14: {=_xlfn.IFS(L14>=8,"High",L14>=5,"Medium",L14<5,"Low")} -> High | T14: =IF(P14>=3000,"High",IF(P14>=1500,"Medium","Low")) -> Low | V14: Beauty | W14: BrandE | X14: =AVERAGEIFS(L2:L373,I2:I373,V14,K2:K373,W14) -> 5.2352941 | Y14: =AVERAGEIFS(L2:L373,I2:I373,V14,K2:K373,W14) -> 5.2352941
A15: 10014 | B15: 1458 | C15: 45039 | D15: 45045 | E15: Kolkata | F15: Karnataka | G15: Marketplace | H15: Cash on Delivery | I15: Sports | J15: Yoga Mat | K15: BrandD | L15: 8 | M15: 1074.27 | N15: =L15*M15 -> 8594.16 | O15: 15 | P15: =N15*O15/100 -> 1289.124 | Q15: =N15-P15 -> 7305.036 | R15: =IF(Q15>=10000,"High","Low") -> Low | S15: {=_xlfn.IFS(L15>=8,"High",L15>=5,"Medium",L15<5,"Low")} -> High | T15: =IF(P15>=3000,"High",IF(P15>=1500,"Medium","Low")) -> Low
A16: 10015 | B16: 1087 | C16: 45048 | D16: 45057 | E16: Hyderabad | F16: Tamil Nadu | G16: Website | H16: Credit Card | I16: Beauty | J16: Shampoo | K16: BrandA | L16: 9 | M16: 705.59 | N16: =L16*M16 -> 6350.31 | O16: 10 | P16: =N16*O16/100 -> 635.031 | Q16: =N16-P16 -> 5715.279 | R16: =IF(Q16>=10000,"High","Low") -> Low | S16: {=_xlfn.IFS(L16>=8,"High",L16>=5,"Medium",L16<5,"Low")} -> High | T16: =IF(P16>=3000,"High",IF(P16>=1500,"Medium","Low")) -> Low
A17: 10016 | B17: 1372 | C17: 44958 | D17: 44961 | E17: Pune | F17: West Bengal | G17: Mobile App | H17: Net Banking | I17: Fashion | J17: Jacket | K17: BrandA | L17: 8 | M17: 595.45 | N17: =L17*M17 -> 4763.6 | O17: 5 | P17: =N17*O17/100 -> 238.18 | Q17: =N17-P17 -> 4525.42 | R17: =IF(Q17>=10000,"High","Low") -> Low | S17: {=_xlfn.IFS(L17>=8,"High",L17>=5,"Medium",L17<5,"Low")} -> High | T17: =IF(P17>=3000,"High",IF(P17>=1500,"Medium","Low")) -> Low | V17: Tandra
A18: 10017 | B18: 1099 | C18: 45148 | D18: 45151 | E18: Delhi | F18: Maharashtra | G18: Mobile App | H18: UPI | I18: Fashion | J18: Jacket | K18: BrandD | L18: 2 | M18: 254.91 | N18: =L18*M18 -> 509.82 | O18: 15 | P18: =N18*O18/100 -> 76.473 | Q18: =N18-P18 -> 433.347 | R18: =IF(Q18>=10000,"High","Low") -> Low | S18: {=_xlfn.IFS(L18>=8,"High",L18>=5,"Medium",L18<5,"Low")} -> Low | T18: =IF(P18>=3000,"High",IF(P18>=1500,"Medium","Low")) -> Low | V18: 45 | W18: =AVERAGEA(V17:V21) -> 17.2
A19: 10018 | B19: 1871 | C19: 45045 | D19: 45048 | E19: Chennai | F19: West Bengal | G19: Website | H19: Credit Card | I19: Home & Kitchen | J19: Curtains | K19: BrandD | L19: 1 | M19: 2165.81 | N19: =L19*M19 -> 2165.81 | O19: 15 | P19: =N19*O19/100 -> 324.8715 | Q19: =N19-P19 -> 1840.9385 | R19: =IF(Q19>=10000,"High","Low") -> Low | S19: {=_xlfn.IFS(L19>=8,"High",L19>=5,"Medium",L19<5,"Low")} -> Low | T19: =IF(P19>=3000,"High",IF(P19>=1500,"Medium","Low")) -> Low | V19: 40
A20: 10019 | B20: 1663 | C20: 44965 | D20: 44968 | E20: Bengaluru | F20: Karnataka | G20: Marketplace | H20: Net Banking | I20: Fashion | J20: Jacket | K20: BrandE | L20: 2 | M20: 990.3 | N20: =L20*M20 -> 1980.6 | O20: 15 | P20: =N20*O20/100 -> 297.09 | Q20: =N20-P20 -> 1683.51 | R20: =IF(Q20>=10000,"High","Low") -> Low | S20: {=_xlfn.IFS(L20>=8,"High",L20>=5,"Medium",L20<5,"Low")} -> Low | T20: =IF(P20>=3000,"High",IF(P20>=1500,"Medium","Low")) -> Low | V20: TRUE
A21: 10020 | B21: 1130 | C21: 45194 | D21: 45203 | E21: Mumbai | F21: Karnataka | G21: Mobile App | H21: Credit Card | I21: Electronics | J21: Smartwatch | K21: BrandA | L21: 2 | M21: 3959.31 | N21: =L21*M21 -> 7918.62 | O21: 5 | P21: =N21*O21/100 -> 395.931 | Q21: =N21-P21 -> 7522.689 | R21: =IF(Q21>=10000,"High","Low") -> Low | S21: {=_xlfn.IFS(L21>=8,"High",L21>=5,"Medium",L21<5,"Low")} -> Low | T21: =IF(P21>=3000,"High",IF(P21>=1500,"Medium","Low")) -> Low | V21: FALSE
A22: 10021 | B22: 1661 | C22: 45159 | D22: 45163 | E22: Mumbai | F22: West Bengal | G22: Website | H22: Credit Card | I22: Beauty | J22: Lipstick | K22: BrandA | L22: 3 | M22: 2361.58 | N22: =L22*M22 -> 7084.74 | O22: 5 | P22: =N22*O22/100 -> 354.237 | Q22: =N22-P22 -> 6730.503 | R22: =IF(Q22>=10000,"High","Low") -> Low | S22: {=_xlfn.IFS(L22>=8,"High",L22>=5,"Medium",L22<5,"Low")} -> Low | T22: =IF(P22>=3000,"High",IF(P22>=1500,"Medium","Low")) -> Low
A23: 10022 | B23: 1308 | C23: 44944 | D23: 44951 | E23: Kolkata | F23: Tamil Nadu | G23: Marketplace | H23: Cash on Delivery | I23: Books | J23: Fiction Novel | K23: BrandE | L23: 7 | M23: 680.86 | N23: =L23*M23 -> 4766.02 | O23: 20 | P23: =N23*O23/100 -> 953.204 | Q23: =N23-P23 -> 3812.816 | R23: =IF(Q23>=10000,"High","Low") -> Low | S23: {=_xlfn.IFS(L23>=8,"High",L23>=5,"Medium",L23<5,"Low")} -> Medium | T23: =IF(P23>=3000,"High",IF(P23>=1500,"Medium","Low")) -> Low | V23: Total selling amount | W23: =SUM(N2:N373) -> 3664518.5
A24: 10023 | B24: 1769 | C24: 45075 | D24: 45084 | E24: Delhi | F24: Tamil Nadu | G24: Mobile App | H24: Net Banking | I24: Fashion | J24: Sneakers | K24: BrandC | L24: 2 | M24: 2801.74 | N24: =L24*M24 -> 5603.48 | O24: 20 | P24: =N24*O24/100 -> 1120.696 | Q24: =N24-P24 -> 4482.784 | R24: =IF(Q24>=10000,"High","Low") -> Low | S24: {=_xlfn.IFS(L24>=8,"High",L24>=5,"Medium",L24<5,"Low")} -> Low | T24: =IF(P24>=3000,"High",IF(P24>=1500,"Medium","Low")) -> Low
A25: 10024 | B25: 1343 | C25: 45075 | D25: 45082 | E25: Pune | F25: Telangana | G25: Mobile App | H25: UPI | I25: Electronics | J25: Smartwatch | K25: BrandC | L25: 1 | M25: 3606.31 | N25: =L25*M25 -> 3606.31 | O25: 0 | P25: =N25*O25/100 -> 0 | Q25: =N25-P25 -> 3606.31 | R25: =IF(Q25>=10000,"High","Low") -> Low | S25: {=_xlfn.IFS(L25>=8,"High",L25>=5,"Medium",L25<5,"Low")} -> Low | T25: =IF(P25>=3000,"High",IF(P25>=1500,"Medium","Low")) -> Low | V25: Total selling amount | W25: =SUMPRODUCT(L2:L373,M2:M373) -> 3664518.5
A26: 10025 | B26: 1491 | C26: 45052 | D26: 45061 | E26: Kolkata | F26: Karnataka | G26: Marketplace | H26: UPI | I26: Books | J26: Comics | K26: BrandC | L26: 6 | M26: 3018.94 | N26: =L26*M26 -> 18113.64 | O26: 5 | P26: =N26*O26/100 -> 905.682 | Q26: =N26-P26 -> 17207.958 | R26: =IF(Q26>=10000,"High","Low") -> High | S26: {=_xlfn.IFS(L26>=8,"High",L26>=5,"Medium",L26<5,"Low")} -> Medium | T26: =IF(P26>=3000,"High",IF(P26>=1500,"Medium","Low")) -> Low
A27: 10026 | B27: 1413 | C27: 45228 | D27: 45231 | E27: Bengaluru | F27: Delhi | G27: Marketplace | H27: Net Banking | I27: Beauty | J27: Perfume | K27: BrandE | L27: 9 | M27: 444.29 | N27: =L27*M27 -> 3998.61 | O27: 5 | P27: =N27*O27/100 -> 199.9305 | Q27: =N27-P27 -> 3798.6795 | R27: =IF(Q27>=10000,"High","Low") -> Low | S27: {=_xlfn.IFS(L27>=8,"High",L27>=5,"Medium",L27<5,"Low")} -> High | T27: =IF(P27>=3000,"High",IF(P27>=1500,"Medium","Low")) -> Low
A28: 10027 | B28: 1805 | C28: 45286 | D28: 45290 | E28: Kolkata | F28: Telangana | G28: Website | H28: Cash on Delivery | I28: Books | J28: Fiction Novel | K28: BrandA | L28: 3 | M28: 3599.15 | N28: =L28*M28 -> 10797.45 | O28: 5 | P28: =N28*O28/100 -> 539.8725 | Q28: =N28-P28 -> 10257.578 | R28: =IF(Q28>=10000,"High","Low") -> High | S28: {=_xlfn.IFS(L28>=8,"High",L28>=5,"Medium",L28<5,"Low")} -> Low | T28: =IF(P28>=3000,"High",IF(P28>=1500,"Medium","Low")) -> Low | V28: Total selling amount | W28: BrandA | X28: {=SUMPRODUCT(L2:L373,M2:M373,--(K2:K373=W28))} -> 737855.54
A29: 10028 | B29: 1385 | C29: 45164 | D29: 45172 | E29: Hyderabad | F29: Tamil Nadu | G29: Website | H29: Debit Card | I29: Electronics | J29: Smartwatch | K29: BrandE | L29: 6 | M29: 3206.63 | N29: =L29*M29 -> 19239.78 | O29: 20 | P29: =N29*O29/100 -> 3847.956 | Q29: =N29-P29 -> 15391.824 | R29: =IF(Q29>=10000,"High","Low") -> High | S29: {=_xlfn.IFS(L29>=8,"High",L29>=5,"Medium",L29<5,"Low")} -> Medium | T29: =IF(P29>=3000,"High",IF(P29>=1500,"Medium","Low")) -> High
A30: 10029 | B30: 1191 | C30: 45061 | D30: 45067 | E30: Mumbai | F30: West Bengal | G30: Mobile App | H30: Credit Card | I30: Sports | J30: Football | K30: BrandE | L30: 3 | M30: 759.47 | N30: =L30*M30 -> 2278.41 | O30: 15 | P30: =N30*O30/100 -> 341.7615 | Q30: =N30-P30 -> 1936.6485 | R30: =IF(Q30>=10000,"High","Low") -> Low | S30: {=_xlfn.IFS(L30>=8,"High",L30>=5,"Medium",L30<5,"Low")} -> Low | T30: =IF(P30>=3000,"High",IF(P30>=1500,"Medium","Low")) -> Low
A31: 10030 | B31: 1955 | C31: 45077 | D31: 45082 | E31: Mumbai | F31: Tamil Nadu | G31: Marketplace | H31: Cash on Delivery | I31: Sports | J31: Cricket Bat | K31: BrandC | L31: 1 | M31: 349.38 | N31: =L31*M31 -> 349.38 | O31: 10 | P31: =N31*O31/100 -> 34.938 | Q31: =N31-P31 -> 314.442 | R31: =IF(Q31>=10000,"High","Low") -> Low | S31: {=_xlfn.IFS(L31>=8,"High",L31>=5,"Medium",L31<5,"Low")} -> Low | T31: =IF(P31>=3000,"High",IF(P31>=1500,"Medium","Low")) -> Low | V31: Product Name | W31: Brand | X31: Units Sold | Y31: Unit Price
A32: 10031 | B32: 1276 | C32: 45162 | D32: 45166 | E32: Chennai | F32: West Bengal | G32: Marketplace | H32: Net Banking | I32: Books | J32: Textbook | K32: BrandB | L32: 5 | M32: 2295.65 | N32: =L32*M32 -> 11478.25 | O32: 20 | P32: =N32*O32/100 -> 2295.65 | Q32: =N32-P32 -> 9182.6 | R32: =IF(Q32>=10000,"High","Low") -> Low | S32: {=_xlfn.IFS(L32>=8,"High",L32>=5,"Medium",L32<5,"Low")} -> Medium | T32: =IF(P32>=3000,"High",IF(P32>=1500,"Medium","Low")) -> Medium | V32: Mixer Grinder | W32: BrandA | X32: 7 | Y32: 2843.87
A33: 10032 | B33: 1160 | C33: 45150 | D33: 45158 | E33: Chennai | F33: Telangana | G33: Marketplace | H33: Credit Card | I33: Home & Kitchen | J33: Bedsheet | K33: BrandA | L33: 4 | M33: 750.74 | N33: =L33*M33 -> 3002.96 | O33: 5 | P33: =N33*O33/100 -> 150.148 | Q33: =N33-P33 -> 2852.812 | R33: =IF(Q33>=10000,"High","Low") -> Low | S33: {=_xlfn.IFS(L33>=8,"High",L33>=5,"Medium",L33<5,"Low")} -> Low | T33: =IF(P33>=3000,"High",IF(P33>=1500,"Medium","Low")) -> Low | V33: Football | W33: BrandD | X33: 9 | Y33: 2525.23
A34: 10033 | B34: 1459 | C34: 45129 | D34: 45130 | E34: Pune | F34: Karnataka | G34: Mobile App | H34: UPI | I34: Books | J34: Comics | K34: BrandC | L34: 7 | M34: 3363.18 | N34: =L34*M34 -> 23542.26 | O34: 20 | P34: =N34*O34/100 -> 4708.452 | Q34: =N34-P34 -> 18833.808 | R34: =IF(Q34>=10000,"High","Low") -> High | S34: {=_xlfn.IFS(L34>=8,"High",L34>=5,"Medium",L34<5,"Low")} -> Medium | T34: =IF(P34>=3000,"High",IF(P34>=1500,"Medium","Low")) -> High | V34: Sneakers | W34: BrandE | X34: 6 | Y34: 3474.34
A35: 10034 | B35: 1313 | C35: 45182 | D35: 45191 | E35: Bengaluru | F35: Tamil Nadu | G35: Marketplace | H35: Debit Card | I35: Fashion | J35: T-Shirt | K35: BrandB | L35: 6 | M35: 1529.59 | N35: =L35*M35 -> 9177.54 | O35: 0 | P35: =N35*O35/100 -> 0 | Q35: =N35-P35 -> 9177.54 | R35: =IF(Q35>=10000,"High","Low") -> Low | S35: {=_xlfn.IFS(L35>=8,"High",L35>=5,"Medium",L35<5,"Low")} -> Medium | T35: =IF(P35>=3000,"High",IF(P35>=1500,"Medium","Low")) -> Low | V35: Yoga Mat | W35: BrandA | Y35: 1008.79
A36: 10035 | B36: 1021 | C36: 45012 | D36: 45013 | E36: Hyderabad | F36: West Bengal | G36: Marketplace | H36: UPI | I36: Fashion | J36: T-Shirt | K36: BrandB | L36: 7 | M36: 3664.64 | N36: =L36*M36 -> 25652.48 | O36: 5 | P36: =N36*O36/100 -> 1282.624 | Q36: =N36-P36 -> 24369.856 | R36: =IF(Q36>=10000,"High","Low") -> High | S36: {=_xlfn.IFS(L36>=8,"High",L36>=5,"Medium",L36<5,"Low")} -> Medium | T36: =IF(P36>=3000,"High",IF(P36>=1500,"Medium","Low")) -> Low | V36: Jacket | W36: BrandA | X36: 7 | Y36: 3511.47
A37: 10036 | B37: 1252 | C37: 45076 | D37: 45084 | E37: Delhi | F37: Karnataka | G37: Mobile App | H37: Net Banking | I37: Sports | J37: Football | K37: BrandD | L37: 5 | M37: 2327.9 | N37: =L37*M37 -> 11639.5 | O37: 0 | P37: =N37*O37/100 -> 0 | Q37: =N37-P37 -> 11639.5 | R37: =IF(Q37>=10000,"High","Low") -> High | S37: {=_xlfn.IFS(L37>=8,"High",L37>=5,"Medium",L37<5,"Low")} -> Medium | T37: =IF(P37>=3000,"High",IF(P37>=1500,"Medium","Low")) -> Low | V37: Bedsheet | W37: BrandE | Y37: 3189.55
A38: 10037 | B38: 1747 | C38: 45161 | D38: 45165 | E38: Kolkata | F38: Delhi | G38: Website | H38: Credit Card | I38: Home & Kitchen | J38: Curtains | K38: BrandA | L38: 4 | M38: 853.29 | N38: =L38*M38 -> 3413.16 | O38: 5 | P38: =N38*O38/100 -> 170.658 | Q38: =N38-P38 -> 3242.502 | R38: =IF(Q38>=10000,"High","Low") -> Low | S38: {=_xlfn.IFS(L38>=8,"High",L38>=5,"Medium",L38<5,"Low")} -> Low | T38: =IF(P38>=3000,"High",IF(P38>=1500,"Medium","Low")) -> Low | V38: Sneakers | W38: BrandC | X38: 5 | Y38: 3030.42
A39: 10038 | B39: 1856 | C39: 45271 | D39: 45280 | E39: Pune | F39: West Bengal | G39: Website | H39: Net Banking | I39: Electronics | J39: Laptop | K39: BrandB | L39: 7 | M39: 687.46 | N39: =L39*M39 -> 4812.22 | O39: 20 | P39: =N39*O39/100 -> 962.444 | Q39: =N39-P39 -> 3849.776 | R39: =IF(Q39>=10000,"High","Low") -> Low | S39: {=_xlfn.IFS(L39>=8,"High",L39>=5,"Medium",L39<5,"Low")} -> Medium | T39: =IF(P39>=3000,"High",IF(P39>=1500,"Medium","Low")) -> Low | V39: Sneakers | W39: BrandB | X39: 4 | Y39: 2310.83
A40: 10039 | B40: 1560 | C40: 44948 | D40: 44953 | E40: Bengaluru | F40: Telangana | G40: Mobile App | H40: Credit Card | I40: Fashion | J40: T-Shirt | K40: BrandC | L40: 7 | M40: 2369.42 | N40: =L40*M40 -> 16585.94 | O40: 15 | P40: =N40*O40/100 -> 2487.891 | Q40: =N40-P40 -> 14098.049 | R40: =IF(Q40>=10000,"High","Low") -> High | S40: {=_xlfn.IFS(L40>=8,"High",L40>=5,"Medium",L40<5,"Low")} -> Medium | T40: =IF(P40>=3000,"High",IF(P40>=1500,"Medium","Low")) -> Medium
A41: 10040 | B41: 1474 | C41: 45274 | D41: 45277 | E41: Chennai | F41: Delhi | G41: Marketplace | H41: Cash on Delivery | I41: Sports | J41: Football | K41: BrandD | L41: 6 | M41: 3083.25 | N41: =L41*M41 -> 18499.5 | O41: 10 | P41: =N41*O41/100 -> 1849.95 | Q41: =N41-P41 -> 16649.55 | R41: =IF(Q41>=10000,"High","Low") -> High | S41: {=_xlfn.IFS(L41>=8,"High",L41>=5,"Medium",L41<5,"Low")} -> Medium | T41: =IF(P41>=3000,"High",IF(P41>=1500,"Medium","Low")) -> Medium
A42: 10041 | B42: 1058 | C42: 45211 | D42: 45220 | E42: Kolkata | F42: Delhi | G42: Mobile App | H42: Debit Card | I42: Beauty | J42: Face Cream | K42: BrandA | L42: 8 | M42: 3158.8 | N42: =L42*M42 -> 25270.4 | O42: 0 | P42: =N42*O42/100 -> 0 | Q42: =N42-P42 -> 25270.4 | R42: =IF(Q42>=10000,"High","Low") -> High | S42: {=_xlfn.IFS(L42>=8,"High",L42>=5,"Medium",L42<5,"Low")} -> High | T42: =IF(P42>=3000,"High",IF(P42>=1500,"Medium","Low")) -> Low | V42: =COUNT(X32:X39) -> 6 | W42: =COUNTA(W32:W39) -> 8
A43: 10042 | B43: 1510 | C43: 45195 | D43: 45204 | E43: Chennai | F43: Maharashtra | G43: Website | H43: Cash on Delivery | I43: Sports | J43: Football | K43: BrandE | L43: 4 | M43: 1211.67 | N43: =L43*M43 -> 4846.68 | O43: 20 | P43: =N43*O43/100 -> 969.336 | Q43: =N43-P43 -> 3877.344 | R43: =IF(Q43>=10000,"High","Low") -> Low | S43: {=_xlfn.IFS(L43>=8,"High",L43>=5,"Medium",L43<5,"Low")} -> Low | T43: =IF(P43>=3000,"High",IF(P43>=1500,"Medium","Low")) -> Low | V43: =COUNTA(X32:X39) -> 6 | W43: =COUNTBLANK(X32:X39) -> 2
A44: 10043 | B44: 1681 | C44: 45184 | D44: 45188 | E44: Kolkata | F44: Tamil Nadu | G44: Website | H44: Cash on Delivery | I44: Fashion | J44: T-Shirt | K44: BrandC | L44: 5 | M44: 936.35 | N44: =L44*M44 -> 4681.75 | O44: 15 | P44: =N44*O44/100 -> 702.2625 | Q44: =N44-P44 -> 3979.4875 | R44: =IF(Q44>=10000,"High","Low") -> Low | S44: {=_xlfn.IFS(L44>=8,"High",L44>=5,"Medium",L44<5,"Low")} -> Medium | T44: =IF(P44>=3000,"High",IF(P44>=1500,"Medium","Low")) -> Low
A45: 10044 | B45: 1475 | C45: 44955 | D45: 44959 | E45: Delhi | F45: West Bengal | G45: Mobile App | H45: Net Banking | I45: Fashion | J45: T-Shirt | K45: BrandB | L45: 4 | M45: 214.51 | N45: =L45*M45 -> 858.04 | O45: 20 | P45: =N45*O45/100 -> 171.608 | Q45: =N45-P45 -> 686.432 | R45: =IF(Q45>=10000,"High","Low") -> Low | S45: {=_xlfn.IFS(L45>=8,"High",L45>=5,"Medium",L45<5,"Low")} -> Low | T45: =IF(P45>=3000,"High",IF(P45>=1500,"Medium","Low")) -> Low | V45: Brand Name | W45: Count
A46: 10045 | B46: 1699 | C46: 45139 | D46: 45147 | E46: Bengaluru | F46: Delhi | G46: Mobile App | H46: Debit Card | I46: Sports | J46: Cricket Bat | K46: BrandB | L46: 1 | M46: 2764.92 | N46: =L46*M46 -> 2764.92 | O46: 0 | P46: =N46*O46/100 -> 0 | Q46: =N46-P46 -> 2764.92 | R46: =IF(Q46>=10000,"High","Low") -> Low | S46: {=_xlfn.IFS(L46>=8,"High",L46>=5,"Medium",L46<5,"Low")} -> Low | T46: =IF(P46>=3000,"High",IF(P46>=1500,"Medium","Low")) -> Low | V46: BrandC | W46: =COUNTIF(W32:W39,V46) -> 1
A47: 10046 | B47: 1975 | C47: 45209 | D47: 45211 | E47: Kolkata | F47: Maharashtra | G47: Website | H47: Credit Card | I47: Electronics | J47: Smartwatch | K47: BrandC | L47: 8 | M47: 444.79 | N47: =L47*M47 -> 3558.32 | O47: 10 | P47: =N47*O47/100 -> 355.832 | Q47: =N47-P47 -> 3202.488 | R47: =IF(Q47>=10000,"High","Low") -> Low | S47: {=_xlfn.IFS(L47>=8,"High",L47>=5,"Medium",L47<5,"Low")} -> High | T47: =IF(P47>=3000,"High",IF(P47>=1500,"Medium","Low")) -> Low
A48: 10047 | B48: 1782 | C48: 44976 | D48: 44985 | E48: Hyderabad | F48: Telangana | G48: Mobile App | H48: Credit Card | I48: Books | J48: Textbook | K48: BrandB | L48: 1 | M48: 1769.93 | N48: =L48*M48 -> 1769.93 | O48: 20 | P48: =N48*O48/100 -> 353.986 | Q48: =N48-P48 -> 1415.944 | R48: =IF(Q48>=10000,"High","Low") -> Low | S48: {=_xlfn.IFS(L48>=8,"High",L48>=5,"Medium",L48<5,"Low")} -> Low | T48: =IF(P48>=3000,"High",IF(P48>=1500,"Medium","Low")) -> Low | V48: Product Category | W48: Brand Name | X48: Count
A49: 10048 | B49: 1189 | C49: 45021 | D49: 45027 | E49: Pune | F49: Karnataka | G49: Website | H49: UPI | I49: Fashion | J49: Jeans | K49: BrandD | L49: 5 | M49: 2466.48 | N49: =L49*M49 -> 12332.4 | O49: 5 | P49: =N49*O49/100 -> 616.62 | Q49: =N49-P49 -> 11715.78 | R49: =IF(Q49>=10000,"High","Low") -> High | S49: {=_xlfn.IFS(L49>=8,"High",L49>=5,"Medium",L49<5,"Low")} -> Medium | T49: =IF(P49>=3000,"High",IF(P49>=1500,"Medium","Low")) -> Low | V49: Bedsheet | W49: BrandE | X49: =COUNTIFS(V32:V39,V49,W32:W39,W49) -> 1
A50: 10049 | B50: 1957 | C50: 45014 | D50: 45023 | E50: Mumbai | F50: West Bengal | G50: Mobile App | H50: Credit Card | I50: Sports | J50: Football | K50: BrandA | L50: 6 | M50: 3757.87 | N50: =L50*M50 -> 22547.22 | O50: 15 | P50: =N50*O50/100 -> 3382.083 | Q50: =N50-P50 -> 19165.137 | R50: =IF(Q50>=10000,"High","Low") -> High | S50: {=_xlfn.IFS(L50>=8,"High",L50>=5,"Medium",L50<5,"Low")} -> Medium | T50: =IF(P50>=3000,"High",IF(P50>=1500,"Medium","Low")) -> High
A51: 10050 | B51: 1686 | C51: 44970 | D51: 44978 | E51: Hyderabad | F51: Delhi | G51: Mobile App | H51: Net Banking | I51: Sports | J51: Cricket Bat | K51: BrandD | L51: 6 | M51: 1350.44 | N51: =L51*M51 -> 8102.64 | O51: 20 | P51: =N51*O51/100 -> 1620.528 | Q51: =N51-P51 -> 6482.112 | R51: =IF(Q51>=10000,"High","Low") -> Low | S51: {=_xlfn.IFS(L51>=8,"High",L51>=5,"Medium",L51<5,"Low")} -> Medium | T51: =IF(P51>=3000,"High",IF(P51>=1500,"Medium","Low")) -> Medium
A52: 10052 | B52: 1562 | C52: 45097 | D52: 45098 | E52: Pune | F52: Maharashtra | G52: Website | H52: Cash on Delivery | I52: Books | J52: Textbook | K52: BrandE | L52: 3 | M52: 2668.52 | N52: =L52*M52 -> 8005.56 | O52: 5 | P52: =N52*O52/100 -> 400.278 | Q52: =N52-P52 -> 7605.282 | R52: =IF(Q52>=10000,"High","Low") -> Low | S52: {=_xlfn.IFS(L52>=8,"High",L52>=5,"Medium",L52<5,"Low")} -> Low | T52: =IF(P52>=3000,"High",IF(P52>=1500,"Medium","Low")) -> Low
A53: 10053 | B53: 1875 | C53: 45115 | D53: 45118 | E53: Mumbai | F53: Delhi | G53: Mobile App | H53: Cash on Delivery | I53: Beauty | J53: Face Cream | K53: BrandA | L53: 5 | M53: 2534.07 | N53: =L53*M53 -> 12670.35 | O53: 10 | P53: =N53*O53/100 -> 1267.035 | Q53: =N53-P53 -> 11403.315 | R53: =IF(Q53>=10000,"High","Low") -> High | S53: {=_xlfn.IFS(L53>=8,"High",L53>=5,"Medium",L53<5,"Low")} -> Medium | T53: =IF(P53>=3000,"High",IF(P53>=1500,"Medium","Low")) -> Low
A54: 10054 | B54: 1566 | C54: 45279 | D54: 45281 | E54: Hyderabad | F54: Tamil Nadu | G54: Website | H54: Debit Card | I54: Electronics | J54: Headphones | K54: BrandA | L54: 8 | M54: 1428.62 | N54: =L54*M54 -> 11428.96 | O54: 10 | P54: =N54*O54/100 -> 1142.896 | Q54: =N54-P54 -> 10286.064 | R54: =IF(Q54>=10000,"High","Low") -> High | S54: {=_xlfn.IFS(L54>=8,"High",L54>=5,"Medium",L54<5,"Low")} -> High | T54: =IF(P54>=3000,"High",IF(P54>=1500,"Medium","Low")) -> Low
A55: 10055 | B55: 1243 | C55: 45110 | D55: 45115 | E55: Kolkata | F55: Delhi | G55: Website | H55: Credit Card | I55: Beauty | J55: Face Cream | K55: BrandC | L55: 2 | M55: 3723.19 | N55: =L55*M55 -> 7446.38 | O55: 5 | P55: =N55*O55/100 -> 372.319 | Q55: =N55-P55 -> 7074.061 | R55: =IF(Q55>=10000,"High","Low") -> Low | S55: {=_xlfn.IFS(L55>=8,"High",L55>=5,"Medium",L55<5,"Low")} -> Low | T55: =IF(P55>=3000,"High",IF(P55>=1500,"Medium","Low")) -> Low
A56: 10056 | B56: 1831 | C56: 44929 | D56: 44934 | E56: Kolkata | F56: West Bengal | G56: Mobile App | H56: Net Banking | I56: Books | J56: Textbook | K56: BrandC | L56: 6 | M56: 3402.72 | N56: =L56*M56 -> 20416.32 | O56: 15 | P56: =N56*O56/100 -> 3062.448 | Q56: =N56-P56 -> 17353.872 | R56: =IF(Q56>=10000,"High","Low") -> High | S56: {=_xlfn.IFS(L56>=8,"High",L56>=5,"Medium",L56<5,"Low")} -> Medium | T56: =IF(P56>=3000,"High",IF(P56>=1500,"Medium","Low")) -> High
A57: 10057 | B57: 1504 | C57: 45117 | D57: 45122 | E57: Kolkata | F57: West Bengal | G57: Mobile App | H57: Debit Card | I57: Books | J57: Fiction Novel | K57: BrandE | L57: 9 | M57: 1012.33 | N57: =L57*M57 -> 9110.97 | O57: 20 | P57: =N57*O57/100 -> 1822.194 | Q57: =N57-P57 -> 7288.776 | R57: =IF(Q57>=10000,"High","Low") -> Low | S57: {=_xlfn.IFS(L57>=8,"High",L57>=5,"Medium",L57<5,"Low")} -> High | T57: =IF(P57>=3000,"High",IF(P57>=1500,"Medium","Low")) -> Medium
A58: 10059 | B58: 1484 | C58: 44945 | D58: 44950 | E58: Hyderabad | F58: Telangana | G58: Website | H58: Net Banking | I58: Beauty | J58: Face Cream | K58: BrandE | L58: 8 | M58: 2122.36 | N58: =L58*M58 -> 16978.88 | O58: 0 | P58: =N58*O58/100 -> 0 | Q58: =N58-P58 -> 16978.88 | R58: =IF(Q58>=10000,"High","Low") -> High | S58: {=_xlfn.IFS(L58>=8,"High",L58>=5,"Medium",L58<5,"Low")} -> High | T58: =IF(P58>=3000,"High",IF(P58>=1500,"Medium","Low")) -> Low
A59: 10060 | B59: 1818 | C59: 44949 | D59: 44952 | E59: Mumbai | F59: Telangana | G59: Marketplace | H59: Net Banking | I59: Books | J59: Textbook | K59: BrandC | L59: 8 | M59: 3128.25 | N59: =L59*M59 -> 25026 | O59: 15 | P59: =N59*O59/100 -> 3753.9 | Q59: =N59-P59 -> 21272.1 | R59: =IF(Q59>=10000,"High","Low") -> High | S59: {=_xlfn.IFS(L59>=8,"High",L59>=5,"Medium",L59<5,"Low")} -> High | T59: =IF(P59>=3000,"High",IF(P59>=1500,"Medium","Low")) -> High
A60: 10061 | B60: 1646 | C60: 44956 | D60: 44957 | E60: Kolkata | F60: Maharashtra | G60: Website | H60: Net Banking | I60: Sports | J60: Yoga Mat | K60: BrandC | L60: 7 | M60: 319.56 | N60: =L60*M60 -> 2236.92 | O60: 10 | P60: =N60*O60/100 -> 223.692 | Q60: =N60-P60 -> 2013.228 | R60: =IF(Q60>=10000,"High","Low") -> Low | S60: {=_xlfn.IFS(L60>=8,"High",L60>=5,"Medium",L60<5,"Low")} -> Medium | T60: =IF(P60>=3000,"High",IF(P60>=1500,"Medium","Low")) -> Low
A61: 10063 | B61: 1840 | C61: 45034 | D61: 45043 | E61: Hyderabad | F61: Tamil Nadu | G61: Marketplace | H61: Net Banking | I61: Books | J61: Textbook | K61: BrandD | L61: 6 | M61: 2645.71 | N61: =L61*M61 -> 15874.26 | O61: 10 | P61: =N61*O61/100 -> 1587.426 | Q61: =N61-P61 -> 14286.834 | R61: =IF(Q61>=10000,"High","Low") -> High | S61: {=_xlfn.IFS(L61>=8,"High",L61>=5,"Medium",L61<5,"Low")} -> Medium | T61: =IF(P61>=3000,"High",IF(P61>=1500,"Medium","Low")) -> Medium
... A373: 10500 | B373: 1569 | C373: 44972 | D373: 44977 | E373: Chennai | F373: Delhi | G373: Marketplace | H373: Net Banking | I373: Fashion | J373: Jeans | K373: BrandE | L373: 1 | M373: 2432.17 | N373: =L373*M373 -> 2432.17 | O373: 20 | P373: =N373*O373/100 -> 486.434 | Q373: =N373-P373 -> 1945.736 | R373: =IF(Q373>=10000,"High","Low") -> Low | S373: {=_xlfn.IFS(L373>=8,"High",L373>=5,"Medium",L373<5,"Low")} -> Low | T373: =IF(P373>=3000,"High",IF(P373>=1500,"Medium","Low")) -> Low

Sheet Sheet7
A1: Order ID | B1: Customer ID | C1: Order Date | D1: Ship Date | E1: City | F1: State | G1: Sales Channel | H1: Payment Method | I1: Product Category | J1: Product Name | K1: Brand | L1: Units Sold | M1: Unit Price
A2: 10403 | B2: 1152 | C2: 45035 | D2: 45037 | E2: Delhi | F2: Karnataka | G2: Website | H2: UPI | I2: Sports | J2: Yoga Mat | K2: BrandA | L2: 1 | M2: 2743.75 | O2: City | Q2: Sales Channel | S2: Unit Price
A3: 10406 | B3: 1895 | C3: 45195 | D3: 45204 | E3: Delhi | F3: West Bengal | G3: Marketplace | H3: UPI | I3: Electronics | J3: Smartwatch | K3: BrandA | L3: 1 | M3: 2044.41 | O3: Kolkata | Q3: Mobile App | S3: >1000
A4: 10460 | B4: 1515 | C4: 45215 | D4: 45221 | E4: Pune | F4: West Bengal | G4: Website | H4: Debit Card | I4: Electronics | J4: Headphones | K4: BrandA | L4: 1 | M4: 445.38
A5: 10020 | B5: 1130 | C5: 45194 | D5: 45203 | E5: Mumbai | F5: Karnataka | G5: Mobile App | H5: Credit Card | I5: Electronics | J5: Smartwatch | K5: BrandA | L5: 2 | M5: 3959.31
A6: 10102 | B6: 1161 | C6: 44996 | D6: 45002 | E6: Kolkata | F6: Maharashtra | G6: Marketplace | H6: Debit Card | I6: Fashion | J6: Jacket | K6: BrandA | L6: 2 | M6: 1859.03
A7: 10108 | B7: 1815 | C7: 45037 | D7: 45045 | E7: Chennai | F7: West Bengal | G7: Website | H7: Credit Card | I7: Sports | J7: Yoga Mat | K7: BrandA | L7: 2 | M7: 564.31
A8: 10004 | B8: 1270 | C8: 45079 | D8: 45087 | E8: Bengaluru | F8: West Bengal | G8: Website | H8: Cash on Delivery | I8: Sports | J8: Yoga Mat | K8: BrandA | L8: 1 | M8: 1008.79 | O8: Order ID | P8: Customer ID | Q8: Order Date | R8: Ship Date | S8: City | T8: State | U8: Sales Channel | V8: Payment Method | W8: Product Category | X8: Product Name | Y8: Brand | Z8: Units Sold | AA8: Unit Price
A9: 10073 | B9: 1564 | C9: 45055 | D9: 45063 | E9: Hyderabad | F9: Delhi | G9: Mobile App | H9: Debit Card | I9: Electronics | J9: Smartphone | K9: BrandA | L9: 1 | M9: 3037.61 | O9: 10102 | P9: 1161 | Q9: 44996 | R9: 45002 | S9: Kolkata | T9: Maharashtra | U9: Marketplace | V9: Debit Card | W9: Fashion | X9: Jacket | Y9: BrandA | Z9: 2 | AA9: 1859.03
A10: 10138 | B10: 1128 | C10: 45088 | D10: 45093 | E10: Pune | F10: West Bengal | G10: Mobile App | H10: Cash on Delivery | I10: Beauty | J10: Shampoo | K10: BrandA | L10: 1 | M10: 912.67 | O10: 10027 | P10: 1805 | Q10: 45286 | R10: 45290 | S10: Kolkata | T10: Telangana | U10: Website | V10: Cash on Delivery | W10: Books | X10: Fiction Novel | Y10: BrandA | Z10: 3 | AA10: 3599.15
A11: 10232 | B11: 1639 | C11: 44962 | D11: 44969 | E11: Pune | F11: West Bengal | G11: Mobile App | H11: Credit Card | I11: Books | J11: Comics | K11: BrandA | L11: 1 | M11: 2250.49 | O11: 10037 | P11: 1747 | Q11: 45161 | R11: 45165 | S11: Kolkata | T11: Delhi | U11: Website | V11: Credit Card | W11: Home & Kitchen | X11: Curtains | Y11: BrandA | Z11: 4 | AA11: 853.29
A12: 10350 | B12: 1640 | C12: 45180 | D12: 45185 | E12: Chennai | F12: Telangana | G12: Mobile App | H12: UPI | I12: Books | J12: Textbook | K12: BrandA | L12: 1 | M12: 3708.38 | O12: 10112 | P12: 1726 | Q12: 45153 | R12: 45154 | S12: Kolkata | T12: Telangana | U12: Marketplace | V12: Credit Card | W12: Sports | X12: Yoga Mat | Y12: BrandA | Z12: 4 | AA12: 1110.59
A13: 10190 | B13: 1857 | C13: 45185 | D13: 45187 | E13: Bengaluru | F13: Maharashtra | G13: Marketplace | H13: Debit Card | I13: Electronics | J13: Smartwatch | K13: BrandA | L13: 2 | M13: 1372.59 | O13: 10127 | P13: 1379 | Q13: 44930 | R13: 44935 | S13: Kolkata | T13: Maharashtra | U13: Website | V13: Credit Card | W13: Fashion | X13: Jacket | Y13: BrandA | Z13: 6 | AA13: 1846.21
A14: 10192 | B14: 1891 | C14: 45039 | D14: 45042 | E14: Chennai | F14: West Bengal | G14: Marketplace | H14: Cash on Delivery | I14: Beauty | J14: Perfume | K14: BrandA | L14: 2 | M14: 487.23 | O14: 10216 | P14: 1085 | Q14: 45221 | R14: 45227 | S14: Kolkata | T14: Tamil Nadu | U14: Website | V14: Credit Card | W14: Books | X14: Biography | Y14: BrandA | Z14: 6 | AA14: 809.49
A15: 10305 | B15: 1438 | C15: 44991 | D15: 44993 | E15: Mumbai | F15: Telangana | G15: Mobile App | H15: Cash on Delivery | I15: Fashion | J15: T-Shirt | K15: BrandA | L15: 2 | M15: 3256.02 | O15: 10303 | P15: 1246 | Q15: 45124 | R15: 45125 | S15: Kolkata | T15: West Bengal | U15: Mobile App | V15: Debit Card | W15: Books | X15: Biography | Y15: BrandA | Z15: 6 | AA15: 257.2
A16: 10332 | B16: 1954 | C16: 44946 | D16: 44955 | E16: Chennai | F16: Tamil Nadu | G16: Mobile App | H16: Net Banking | I16: Books | J16: Biography | K16: BrandA | L16: 2 | M16: 1335.36 | O16: 10005 | P16: 1106 | Q16: 45241 | R16: 45244 | S16: Kolkata | T16: Karnataka | U16: Marketplace | V16: Credit Card | W16: Fashion | X16: Jacket | Y16: BrandA | Z16: 7 | AA16: 3511.47
A17: 10372 | B17: 1651 | C17: 45164 | D17: 45167 | E17: Delhi | F17: Tamil Nadu | G17: Website | H17: Cash on Delivery | I17: Electronics | J17: Laptop | K17: BrandA | L17: 2 | M17: 3957.02 | O17: 10143 | P17: 1498 | Q17: 44986 | R17: 44993 | S17: Kolkata | T17: Maharashtra | U17: Marketplace | V17: Debit Card | W17: Books | X17: Fiction Novel | Y17: BrandA | Z17: 7 | AA17: 3680.23
A18: 10444 | B18: 1437 | C18: 44960 | D18: 44969 | E18: Hyderabad | F18: Karnataka | G18: Marketplace | H18: Credit Card | I18: Fashion | J18: Sneakers | K18: BrandA | L18: 2 | M18: 3904.44 | O18: 10289 | P18: 1854 | Q18: 45012 | R18: 45014 | S18: Kolkata | T18: Maharashtra | U18: Mobile App | V18: Debit Card | W18: Books | X18: Fiction Novel | Y18: BrandA | Z18: 7 | AA18: 1396.71
A19: 10021 | B19: 1661 | C19: 45159 | D19: 45163 | E19: Mumbai | F19: West Bengal | G19: Website | H19: Credit Card | I19: Beauty | J19: Lipstick | K19: BrandA | L19: 3 | M19: 2361.58 | O19: 10330 | P19: 1659 | Q19: 44958 | R19: 44966 | S19: Kolkata | T19: Maharashtra | U19: Mobile App | V19: UPI | W19: Beauty | X19: Face Cream | Y19: BrandA | Z19: 7 | AA19: 3978.5
A20: 10027 | B20: 1805 | C20: 45286 | D20: 45290 | E20: Kolkata | F20: Telangana | G20: Website | H20: Cash on Delivery | I20: Books | J20: Fiction Novel | K20: BrandA | L20: 3 | M20: 3599.15 | O20: 10041 | P20: 1058 | Q20: 45211 | R20: 45220 | S20: Kolkata | T20: Delhi | U20: Mobile App | V20: Debit Card | W20: Beauty | X20: Face Cream | Y20: BrandA | Z20: 8 | AA20: 3158.8
... A70: 10171 | B70: 1986 | C70: 45227 | D70: 45228 | E70: Chennai | F70: Telangana | G70: Website | H70: Credit Card | I70: Home & Kitchen | J70: Bedsheet | K70: BrandA | L70: 8 | M70: 3795.01 | O70: 10057 | P70: 1504 | Q70: 45117 | R70: 45122 | S70: Kolkata | T70: West Bengal | U70: Mobile App | V70: Debit Card | W70: Books | X70: Fiction Novel | Y70: BrandE | Z70: 9 | AA70: 1012.33
A71: 10196 | B71: 1863 | C71: 45124 | D71: 45133 | E71: Kolkata | F71: West Bengal | G71: Marketplace | H71: UPI | I71: Beauty | J71: Shampoo | K71: BrandA | L71: 8 | M71: 2561.86
A72: 10220 | B72: 1556 | C72: 45026 | D72: 45035 | E72: Kolkata | F72: Delhi | G72: Website | H72: Credit Card | I72: Home & Kitchen | J72: Curtains | K72: BrandA | L72: 8 | M72: 3240.98
A73: 10015 | B73: 1087 | C73: 45048 | D73: 45057 | E73: Hyderabad | F73: Tamil Nadu | G73: Website | H73: Credit Card | I73: Beauty | J73: Shampoo | K73: BrandA | L73: 9 | M73: 705.59
A74: 10179 | B74: 1768 | C74: 44973 | D74: 44976 | E74: Kolkata | F74: Delhi | G74: Marketplace | H74: Debit Card | I74: Fashion | J74: Sneakers | K74: BrandA | L74: 9 | M74: 388.26 | P74: Order ID | Q74: Customer ID | R74: Order Date | S74: Ship Date | T74: City | U74: State | V74: Sales Channel | W74: Payment Method | X74: Product Category | Y74: Product Name | Z74: Brand | AA74: Units Sold | AB74: Unit Price
A75: 10355 | B75: 1945 | C75: 45188 | D75: 45191 | E75: Kolkata | F75: Tamil Nadu | G75: Marketplace | H75: Cash on Delivery | I75: Beauty | J75: Shampoo | K75: BrandA | L75: 9 | M75: 2632.88 | P75: 10020 | Q75: 1130 | R75: 45194 | S75: 45203 | T75: Mumbai | U75: Karnataka | V75: Mobile App | W75: Credit Card | X75: Electronics | Y75: Smartwatch | Z75: BrandA | AA75: 2 | AB75: 3959.31
A76: 10356 | B76: 1150 | C76: 45093 | D76: 45102 | E76: Delhi | F76: Karnataka | G76: Marketplace | H76: Net Banking | I76: Fashion | J76: T-Shirt | K76: BrandA | L76: 9 | M76: 1259.77 | P76: 10073 | Q76: 1564 | R76: 45055 | S76: 45063 | T76: Hyderabad | U76: Delhi | V76: Mobile App | W76: Debit Card | X76: Electronics | Y76: Smartphone | Z76: BrandA | AA76: 1 | AB76: 3037.61
A77: 10045 | B77: 1699 | C77: 45139 | D77: 45147 | E77: Bengaluru | F77: Delhi | G77: Mobile App | H77: Debit Card | I77: Sports | J77: Cricket Bat | K77: BrandB | L77: 1 | M77: 2764.92 | P77: 10138 | Q77: 1128 | R77: 45088 | S77: 45093 | T77: Pune | U77: West Bengal | V77: Mobile App | W77: Cash on Delivery | X77: Beauty | Y77: Shampoo | Z77: BrandA | AA77: 1 | AB77: 912.67
A78: 10047 | B78: 1782 | C78: 44976 | D78: 44985 | E78: Hyderabad | F78: Telangana | G78: Mobile App | H78: Credit Card | I78: Books | J78: Textbook | K78: BrandB | L78: 1 | M78: 1769.93 | P78: 10232 | Q78: 1639 | R78: 44962 | S78: 44969 | T78: Pune | U78: West Bengal | V78: Mobile App | W78: Credit Card | X78: Books | Y78: Comics | Z78: BrandA | AA78: 1 | AB78: 2250.49
A79: 10152 | B79: 1230 | C79: 45043 | D79: 45050 | E79: Kolkata | F79: Delhi | G79: Website | H79: UPI | I79: Beauty | J79: Lipstick | K79: BrandB | L79: 1 | M79: 3249.11 | P79: 10350 | Q79: 1640 | R79: 45180 | S79: 45185 | T79: Chennai | U79: Telangana | V79: Mobile App | W79: UPI | X79: Books | Y79: Textbook | Z79: BrandA | AA79: 1 | AB79: 3708.38
A80: 10186 | B80: 1794 | C80: 45251 | D80: 45254 | E80: Kolkata | F80: Telangana | G80: Marketplace | H80: Debit Card | I80: Beauty | J80: Lipstick | K80: BrandB | L80: 1 | M80: 508.81 | P80: 10305 | Q80: 1438 | R80: 44991 | S80: 44993 | T80: Mumbai | U80: Telangana | V80: Mobile App | W80: Cash on Delivery | X80: Fashion | Y80: T-Shirt | Z80: BrandA | AA80: 2 | AB80: 3256.02
A81: 10233 | B81: 1505 | C81: 45139 | D81: 45143 | E81: Delhi | F81: Telangana | G81: Mobile App | H81: UPI | I81: Home & Kitchen | J81: Curtains | K81: BrandB | L81: 1 | M81: 556.53 | P81: 10332 | Q81: 1954 | R81: 44946 | S81: 44955 | T81: Chennai | U81: Tamil Nadu | V81: Mobile App | W81: Net Banking | X81: Books | Y81: Biography | Z81: BrandA | AA81: 2 | AB81: 1335.36
A82: 10267 | B82: 1691 | C82: 45074 | D82: 45079 | E82: Hyderabad | F82: Karnataka | G82: Marketplace | H82: UPI | I82: Beauty | J82: Shampoo | K82: BrandB | L82: 1 | M82: 900.78 | P82: 10188 | Q82: 1206 | R82: 45064 | S82: 45070 | T82: Hyderabad | U82: Maharashtra | V82: Mobile App | W82: Debit Card | X82: Beauty | Y82: Shampoo | Z82: BrandA | AA82: 3 | AB82: 778.85
A83: 10309 | B83: 1400 | C83: 44928 | D83: 44936 | E83: Bengaluru | F83: West Bengal | G83: Marketplace | H83: UPI | I83: Electronics | J83: Smartwatch | K83: BrandB | L83: 1 | M83: 2740.46 | P83: 10339 | Q83: 1147 | R83: 45005 | S83: 45012 | T83: Chennai | U83: Maharashtra | V83: Mobile App | W83: Debit Card | X83: Fashion | Y83: Sneakers | Z83: BrandA | AA83: 4 | AB83: 3708.51
A84: 10329 | B84: 1770 | C84: 44975 | D84: 44976 | E84: Hyderabad | F84: Karnataka | G84: Mobile App | H84: UPI | I84: Sports | J84: Football | K84: BrandB | L84: 1 | M84: 3171.36 | P84: 10053 | Q84: 1875 | R84: 45115 | S84: 45118 | T84: Mumbai | U84: Delhi | V84: Mobile App | W84: Cash on Delivery | X84: Beauty | Y84: Face Cream | Z84: BrandA | AA84: 5 | AB84: 2534.07
A85: 10359 | B85: 1297 | C85: 45104 | D85: 45105 | E85: Delhi | F85: Telangana | G85: Mobile App | H85: Debit Card | I85: Fashion | J85: T-Shirt | K85: BrandB | L85: 1 | M85: 202.49 | P85: 10184 | Q85: 1397 | R85: 45063 | S85: 45072 | T85: Pune | U85: Maharashtra | V85: Mobile App | W85: UPI | X85: Beauty | Y85: Face Cream | Z85: BrandA | AA85: 5 | AB85: 2125.75
A86: 10390 | B86: 1586 | C86: 45102 | D86: 45103 | E86: Hyderabad | F86: Maharashtra | G86: Website | H86: Cash on Delivery | I86: Fashion | J86: T-Shirt | K86: BrandB | L86: 1 | M86: 2430.36 | P86: 10215 | Q86: 1242 | R86: 45157 | S86: 45162 | T86: Chennai | U86: Delhi | V86: Mobile App | W86: Debit Card | X86: Sports | Y86: Football | Z86: BrandA | AA86: 5 | AB86: 633.43
... A195: 10025 | B195: 1491 | C195: 45052 | D195: 45061 | E195: Kolkata | F195: Karnataka | G195: Marketplace | H195: UPI | I195: Books | J195: Comics | K195: BrandC | L195: 6 | M195: 3018.94 | P195: 10093 | Q195: 1565 | R195: 44980 | S195: 44982 | T195: Hyderabad | U195: West Bengal | V195: Mobile App | W195: Net Banking | X195: Beauty | Y195: Lipstick | Z195: BrandE | AA195: 9 | AB195: 1938.76
A196: 10056 | B196: 1831 | C196: 44929 | D196: 44934 | E196: Kolkata | F196: West Bengal | G196: Mobile App | H196: Net Banking | I196: Books | J196: Textbook | K196: BrandC | L196: 6 | M196: 3402.72
A197: 10156 | B197: 1200 | C197: 45099 | D197: 45106 | E197: Hyderabad | F197: Karnataka | G197: Website | H197: Credit Card | I197: Books | J197: Comics | K197: BrandC | L197: 6 | M197: 445.71
A198: 10159 | B198: 1929 | C198: 45109 | D198: 45113 | E198: Bengaluru | F198: Delhi | G198: Website | H198: Debit Card | I198: Electronics | J198: Smartphone | K198: BrandC | L198: 6 | M198: 3800.77
A199: 10270 | B199: 1496 | C199: 45080 | D199: 45086 | E199: Pune | F199: West Bengal | G199: Website | H199: Cash on Delivery | I199: Fashion | J199: Jeans | K199: BrandC | L199: 6 | M199: 3197.13
A200: 10273 | B200: 1267 | C200: 45091 | D200: 45100 | E200: Mumbai | F200: Maharashtra | G200: Marketplace | H200: Credit Card | I200: Fashion | J200: Jacket | K200: BrandC | L200: 6 | M200: 384.88
A201: 10376 | B201: 1008 | C201: 45242 | D201: 45251 | E201: Kolkata | F201: Maharashtra | G201: Marketplace | H201: Credit Card | I201: Books | J201: Comics | K201: BrandC | L201: 6 | M201: 681.36
A202: 10496 | B202: 1017 | C202: 45177 | D202: 45178 | E202: Chennai | F202: Tamil Nadu | G202: Mobile App | H202: Net Banking | I202: Beauty | J202: Perfume | K202: BrandC | L202: 6 | M202: 1128.91 | Q202: Order ID | R202: Customer ID | S202: Order Date | T202: Ship Date | U202: City | V202: State | W202: Sales Channel | X202: Payment Method | Y202: Product Category | Z202: Product Name | AA202: Brand | AB202: Units Sold | AC202: Unit Price
A203: 10033 | B203: 1459 | C203: 45129 | D203: 45130 | E203: Pune | F203: Karnataka | G203: Mobile App | H203: UPI | I203: Books | J203: Comics | K203: BrandC | L203: 7 | M203: 3363.18 | Q203: 10403 | R203: 1152 | S203: 45035 | T203: 45037 | U203: Delhi | V203: Karnataka | W203: Website | X203: UPI | Y203: Sports | Z203: Yoga Mat | AA203: BrandA | AB203: 1 | AC203: 2743.75
A204: 10039 | B204: 1560 | C204: 44948 | D204: 44953 | E204: Bengaluru | F204: Telangana | G204: Mobile App | H204: Credit Card | I204: Fashion | J204: T-Shirt | K204: BrandC | L204: 7 | M204: 2369.42 | Q204: 10406 | R204: 1895 | S204: 45195 | T204: 45204 | U204: Delhi | V204: West Bengal | W204: Marketplace | X204: UPI | Y204: Electronics | Z204: Smartwatch | AA204: BrandA | AB204: 1 | AC204: 2044.41
A205: 10061 | B205: 1646 | C205: 44956 | D205: 44957 | E205: Kolkata | F205: Maharashtra | G205: Website | H205: Net Banking | I205: Sports | J205: Yoga Mat | K205: BrandC | L205: 7 | M205: 319.56 | Q205: 10020 | R205: 1130 | S205: 45194 | T205: 45203 | U205: Mumbai | V205: Karnataka | W205: Mobile App | X205: Credit Card | Y205: Electronics | Z205: Smartwatch | AA205: BrandA | AB205: 2 | AC205: 3959.31
A206: 10167 | B206: 1098 | C206: 45177 | D206: 45182 | E206: Hyderabad | F206: Telangana | G206: Marketplace | H206: Net Banking | I206: Fashion | J206: Sneakers | K206: BrandC | L206: 7 | M206: 1767.02 | Q206: 10102 | R206: 1161 | S206: 44996 | T206: 45002 | U206: Kolkata | V206: Maharashtra | W206: Marketplace | X206: Debit Card | Y206: Fashion | Z206: Jacket | AA206: BrandA | AB206: 2 | AC206: 1859.03
A207: 10178 | B207: 1642 | C207: 45124 | D207: 45126 | E207: Hyderabad | F207: West Bengal | G207: Mobile App | H207: Credit Card | I207: Sports | J207: Cricket Bat | K207: BrandC | L207: 7 | M207: 174.09 | Q207: 10004 | R207: 1270 | S207: 45079 | T207: 45087 | U207: Bengaluru | V207: West Bengal | W207: Website | X207: Cash on Delivery | Y207: Sports | Z207: Yoga Mat | AA207: BrandA | AB207: 1 | AC207: 1008.79
A208: 10321 | B208: 1143 | C208: 45270 | D208: 45275 | E208: Kolkata | F208: Delhi | G208: Marketplace | H208: Net Banking | I208: Beauty | J208: Perfume | K208: BrandC | L208: 7 | M208: 3383.31 | Q208: 10073 | R208: 1564 | S208: 45055 | T208: 45063 | U208: Hyderabad | V208: Delhi | W208: Mobile App | X208: Debit Card | Y208: Electronics | Z208: Smartphone | AA208: BrandA | AB208: 1 | AC208: 3037.61
A209: 10325 | B209: 1186 | C209: 45025 | D209: 45030 | E209: Kolkata | F209: Karnataka | G209: Marketplace | H209: Cash on Delivery | I209: Beauty | J209: Face Cream | K209: BrandC | L209: 7 | M209: 730.15 | Q209: 10232 | R209: 1639 | S209: 44962 | T209: 44969 | U209: Pune | V209: West Bengal | W209: Mobile App | X209: Credit Card | Y209: Books | Z209: Comics | AA209: BrandA | AB209: 1 | AC209: 2250.49
A210: 10490 | B210: 1927 | C210: 45259 | D210: 45261 | E210: Chennai | F210: West Bengal | G210: Mobile App | H210: Cash on Delivery | I210: Fashion | J210: Sneakers | K210: BrandC | L210: 7 | M210: 2838.06 | Q210: 10350 | R210: 1640 | S210: 45180 | T210: 45185 | U210: Chennai | V210: Telangana | W210: Mobile App | X210: UPI | Y210: Books | Z210: Textbook | AA210: BrandA | AB210: 1 | AC210: 3708.38
A211: 10046 | B211: 1975 | C211: 45209 | D211: 45211 | E211: Kolkata | F211: Maharashtra | G211: Website | H211: Credit Card | I211: Electronics | J211: Smartwatch | K211: BrandC | L211: 8 | M211: 444.79 | Q211: 10190 | R211: 1857 | S211: 45185 | T211: 45187 | U211: Bengaluru | V211: Maharashtra | W211: Marketplace | X211: Debit Card | Y211: Electronics | Z211: Smartwatch | AA211: BrandA | AB211: 2 | AC211: 1372.59
A212: 10060 | B212: 1818 | C212: 44949 | D212: 44952 | E212: Mumbai | F212: Telangana | G212: Marketplace | H212: Net Banking | I212: Books | J212: Textbook | K212: BrandC | L212: 8 | M212: 3128.25 | Q212: 10305 | R212: 1438 | S212: 44991 | T212: 44993 | U212: Mumbai | V212: Telangana | W212: Mobile App | X212: Cash on Delivery | Y212: Fashion | Z212: T-Shirt | AA212: BrandA | AB212: 2 | AC212: 3256.02
A213: 10066 | B213: 1387 | C213: 45155 | D213: 45158 | E213: Chennai | F213: Tamil Nadu | G213: Mobile App | H213: Cash on Delivery | I213: Books | J213: Biography | K213: BrandC | L213: 8 | M213: 3769.71 | Q213: 10332 | R213: 1954 | S213: 44946 | T213: 44955 | U213: Chennai | V213: Tamil Nadu | W213: Mobile App | X213: Net Banking | Y213: Books | Z213: Biography | AA213: BrandA | AB213: 2 | AC213: 1335.36
A214: 10168 | B214: 1683 | C214: 45229 | D214: 45232 | E214: Kolkata | F214: Delhi | G214: Marketplace | H214: UPI | I214: Beauty | J214: Lipstick | K214: BrandC | L214: 8 | M214: 187.29 | Q214: 10372 | R214: 1651 | S214: 45164 | T214: 45167 | U214: Delhi | V214: Tamil Nadu | W214: Website | X214: Cash on Delivery | Y214: Electronics | Z214: Laptop | AA214: BrandA | AB214: 2 | AC214: 3957.02
... A373: 10486 | B373: 1115 | C373: 45068 | D373: 45077 | E373: Delhi | F373: Telangana | G373: Website | H373: Net Banking | I373: Electronics | J373: Laptop | K373: BrandE | L373: 9 | M373: 775.77 | Q373: 10115 | R373: 1295 | S373: 45156 | T373: 45159 | U373: Pune | V373: Maharashtra | W373: Website | X373: Net Banking | Y373: Books | Z373: Textbook | AA373: BrandD | AB373: 2 | AC373: 3621.09
Q374: 10141 | R374: 1062 | S374: 45085 | T374: 45092 | U374: Kolkata | V374: West Bengal | W374: Mobile App | X374: Debit Card | Y374: Fashion | Z374: Jacket | AA374: BrandD | AB374: 2 | AC374: 1766.42
Q375: 10150 | R375: 1772 | S375: 44956 | T375: 44961 | U375: Pune | V375: Maharashtra | W375: Website | X375: Credit Card | Y375: Electronics | Z375: Smartwatch | AA375: BrandD | AB375: 2 | AC375: 2808.06
Q376: 10386 | R376: 1119 | S376: 45146 | T376: 45154 | U376: Chennai | V376: Tamil Nadu | W376: Website | X376: UPI | Y376: Electronics | Z376: Smartphone | AA376: BrandD | AB376: 2 | AC376: 1984.38
Q377: 10173 | R377: 1960 | S377: 45124 | T377: 45127 | U377: Chennai | V377: Karnataka | W377: Website | X377: Net Banking | Y377: Fashion | Z377: Jeans | AA377: BrandD | AB377: 3 | AC377: 1357.77
Q378: 10174 | R378: 1738 | S378: 45186 | T378: 45195 | U378: Bengaluru | V378: Delhi | W378: Marketplace | X378: Credit Card | Y378: Beauty | Z378: Shampoo | AA378: BrandD | AB378: 3 | AC378: 1104.31
Q379: 10439 | R379: 1669 | S379: 45174 | T379: 45179 | U379: Bengaluru | V379: West Bengal | W379: Website | X379: Cash on Delivery | Y379: Electronics | Z379: Smartwatch | AA379: BrandD | AB379: 3 | AC379: 1448.62
Q380: 10165 | R380: 1727 | S380: 45039 | T380: 45043 | U380: Bengaluru | V380: Karnataka | W380: Website | X380: Cash on Delivery | Y380: Books | Z380: Textbook | AA380: BrandD | AB380: 4 | AC380: 3718.63
Q381: 10217 | R381: 1795 | S381: 45055 | T381: 45057 | U381: Kolkata | V381: Telangana | W381: Website | X381: Net Banking | Y381: Electronics | Z381: Headphones | AA381: BrandD | AB381: 4 | AC381: 3335.32
Q382: 10307 | R382: 1183 | S382: 45267 | T382: 45273 | U382: Chennai | V382: Delhi | W382: Website | X382: Net Banking | Y382: Books | Z382: Fiction Novel | AA382: BrandD | AB382: 4 | AC382: 2008.45
Q383: 10447 | R383: 1026 | S383: 45264 | T383: 45265 | U383: Bengaluru | V383: Karnataka | W383: Mobile App | X383: Cash on Delivery | Y383: Sports | Z383: Dumbbells | AA383: BrandD | AB383: 4 | AC383: 3871.21
Q384: 10009 | R384: 1614 | S384: 45204 | T384: 45213 | U384: Chennai | V384: West Bengal | W384: Website | X384: Debit Card | Y384: Fashion | Z384: T-Shirt | AA384: BrandD | AB384: 5 | AC384: 1098.04
Q385: 10036 | R385: 1252 | S385: 45076 | T385: 45084 | U385: Delhi | V385: Karnataka | W385: Mobile App | X385: Net Banking | Y385: Sports | Z385: Football | AA385: BrandD | AB385: 5 | AC385: 2327.9
... Q481: 10407 | R481: 1877 | S481: 45088 | T481: 45090 | U481: Pune | V481: Tamil Nadu | W481: Website | X481: Debit Card | Y481: Beauty | Z481: Shampoo | AA481: BrandE | AB481: 9 | AC481: 3216.56

Sheet Sheet8
A1: Order ID | B1: Customer ID | C1: Order Date | D1: Ship Date | E1: City | F1: State | G1: Sales Channel | H1: Payment Method | I1: Product Category | J1: Product Name | K1: Brand | L1: Units Sold | M1: Unit Price | O1: Order ID | P1: Customer ID | Q1: Order Date | R1: Ship Date | S1: City | T1: State | U1: Sales Channel | V1: Payment Method | W1: Product Category | X1: Product Name | Y1: Brand | Z1: Units Sold | AA1: Unit Price
A2: 10102 | B2: 1161 | C2: 44996 | D2: 45002 | E2: Kolkata | F2: Maharashtra | G2: Marketplace | H2: Debit Card | I2: Fashion | J2: Jacket | K2: BrandA | L2: 2 | M2: 1859.03 | O2: 10020 | P2: 1130 | Q2: 45194 | R2: 45203 | S2: Mumbai | T2: Karnataka | U2: Mobile App | V2: Credit Card | W2: Electronics | X2: Smartwatch | Y2: BrandA | Z2: 2 | AA2: 3959.31
A3: 10027 | B3: 1805 | C3: 45286 | D3: 45290 | E3: Kolkata | F3: Telangana | G3: Website | H3: Cash on Delivery | I3: Books | J3: Fiction Novel | K3: BrandA | L3: 3 | M3: 3599.15 | O3: 10073 | P3: 1564 | Q3: 45055 | R3: 45063 | S3: Hyderabad | T3: Delhi | U3: Mobile App | V3: Debit Card | W3: Electronics | X3: Smartphone | Y3: BrandA | Z3: 1 | AA3: 3037.61
A4: 10037 | B4: 1747 | C4: 45161 | D4: 45165 | E4: Kolkata | F4: Delhi | G4: Website | H4: Credit Card | I4: Home & Kitchen | J4: Curtains | K4: BrandA | L4: 4 | M4: 853.29 | O4: 10138 | P4: 1128 | Q4: 45088 | R4: 45093 | S4: Pune | T4: West Bengal | U4: Mobile App | V4: Cash on Delivery | W4: Beauty | X4: Shampoo | Y4: BrandA | Z4: 1 | AA4: 912.67
A5: 10112 | B5: 1726 | C5: 45153 | D5: 45154 | E5: Kolkata | F5: Telangana | G5: Marketplace | H5: Credit Card | I5: Sports | J5: Yoga Mat | K5: BrandA | L5: 4 | M5: 1110.59 | O5: 10232 | P5: 1639 | Q5: 44962 | R5: 44969 | S5: Pune | T5: West Bengal | U5: Mobile App | V5: Credit Card | W5: Books | X5: Comics | Y5: BrandA | Z5: 1 | AA5: 2250.49
A6: 10127 | B6: 1379 | C6: 44930 | D6: 44935 | E6: Kolkata | F6: Maharashtra | G6: Website | H6: Credit Card | I6: Fashion | J6: Jacket | K6: BrandA | L6: 6 | M6: 1846.21 | O6: 10350 | P6: 1640 | Q6: 45180 | R6: 45185 | S6: Chennai | T6: Telangana | U6: Mobile App | V6: UPI | W6: Books | X6: Textbook | Y6: BrandA | Z6: 1 | AA6: 3708.38
A7: 10216 | B7: 1085 | C7: 45221 | D7: 45227 | E7: Kolkata | F7: Tamil Nadu | G7: Website | H7: Credit Card | I7: Books | J7: Biography | K7: BrandA | L7: 6 | M7: 809.49 | O7: 10305 | P7: 1438 | Q7: 44991 | R7: 44993 | S7: Mumbai | T7: Telangana | U7: Mobile App | V7: Cash on Delivery | W7: Fashion | X7: T-Shirt | Y7: BrandA | Z7: 2 | AA7: 3256.02
A8: 10303 | B8: 1246 | C8: 45124 | D8: 45125 | E8: Kolkata | F8: West Bengal | G8: Mobile App | H8: Debit Card | I8: Books | J8: Biography | K8: BrandA | L8: 6 | M8: 257.2 | O8: 10332 | P8: 1954 | Q8: 44946 | R8: 44955 | S8: Chennai | T8: Tamil Nadu | U8: Mobile App | V8: Net Banking | W8: Books | X8: Biography | Y8: BrandA | Z8: 2 | AA8: 1335.36
A9: 10005 | B9: 1106 | C9: 45241 | D9: 45244 | E9: Kolkata | F9: Karnataka | G9: Marketplace | H9: Credit Card | I9: Fashion | J9: Jacket | K9: BrandA | L9: 7 | M9: 3511.47 | O9: 10188 | P9: 1206 | Q9: 45064 | R9: 45070 | S9: Hyderabad | T9: Maharashtra | U9: Mobile App | V9: Debit Card | W9: Beauty | X9: Shampoo | Y9: BrandA | Z9: 3 | AA9: 778.85
A10: 10143 | B10: 1498 | C10: 44986 | D10: 44993 | E10: Kolkata | F10: Maharashtra | G10: Marketplace | H10: Debit Card | I10: Books | J10: Fiction Novel | K10: BrandA | L10: 7 | M10: 3680.23 | O10: 10339 | P10: 1147 | Q10: 45005 | R10: 45012 | S10: Chennai | T10: Maharashtra | U10: Mobile App | V10: Debit Card | W10: Fashion | X10: Sneakers | Y10: BrandA | Z10: 4 | AA10: 3708.51
A11: 10289 | B11: 1854 | C11: 45012 | D11: 45014 | E11: Kolkata | F11: Maharashtra | G11: Mobile App | H11: Debit Card | I11: Books | J11: Fiction Novel | K11: BrandA | L11: 7 | M11: 1396.71 | O11: 10053 | P11: 1875 | Q11: 45115 | R11: 45118 | S11: Mumbai | T11: Delhi | U11: Mobile App | V11: Cash on Delivery | W11: Beauty | X11: Face Cream | Y11: BrandA | Z11: 5 | AA11: 2534.07
A12: 10330 | B12: 1659 | C12: 44958 | D12: 44966 | E12: Kolkata | F12: Maharashtra | G12: Mobile App | H12: UPI | I12: Beauty | J12: Face Cream | K12: BrandA | L12: 7 | M12: 3978.5 | O12: 10184 | P12: 1397 | Q12: 45063 | R12: 45072 | S12: Pune | T12: Maharashtra | U12: Mobile App | V12: UPI | W12: Beauty | X12: Face Cream | Y12: BrandA | Z12: 5 | AA12: 2125.75
A13: 10041 | B13: 1058 | C13: 45211 | D13: 45220 | E13: Kolkata | F13: Delhi | G13: Mobile App | H13: Debit Card | I13: Beauty | J13: Face Cream | K13: BrandA | L13: 8 | M13: 3158.8 | O13: 10215 | P13: 1242 | Q13: 45157 | R13: 45162 | S13: Chennai | T13: Delhi | U13: Mobile App | V13: Debit Card | W13: Sports | X13: Football | Y13: BrandA | Z13: 5 | AA13: 633.43
... A63: 10057 | B63: 1504 | C63: 45117 | D63: 45122 | E63: Kolkata | F63: West Bengal | G63: Mobile App | H63: Debit Card | I63: Books | J63: Fiction Novel | K63: BrandE | L63: 9 | M63: 1012.33 | O63: 10254 | P63: 1676 | Q63: 45010 | R63: 45012 | S63: Pune | T63: Delhi | U63: Mobile App | V63: Net Banking | W63: Beauty | X63: Face Cream | Y63: BrandC | Z63: 2 | AA63: 2711.66
O64: 10455 | P64: 1480 | Q64: 45034 | R64: 45036 | S64: Chennai | T64: West Bengal | U64: Mobile App | V64: Credit Card | W64: Beauty | X64: Face Cream | Y64: BrandC | Z64: 2 | AA64: 1374.23
O65: 10485 | P65: 1992 | Q65: 45228 | R65: 45237 | S65: Delhi | T65: Delhi | U65: Mobile App | V65: Net Banking | W65: Home & Kitchen | X65: Bedsheet | Y65: BrandC | Z65: 2 | AA65: 1294.84
O66: 10244 | P66: 1627 | Q66: 45032 | R66: 45038 | S66: Bengaluru | T66: West Bengal | U66: Mobile App | V66: UPI | W66: Beauty | X66: Shampoo | Y66: BrandC | Z66: 3 | AA66: 800.89
O67: 10441 | P67: 1229 | Q67: 45116 | R67: 45119 | S67: Delhi | T67: Tamil Nadu | U67: Mobile App | V67: Net Banking | W67: Fashion | X67: Jeans | Y67: BrandC | Z67: 3 | AA67: 2189.4
O68: 10175 | P68: 1612 | Q68: 45074 | R68: 45081 | S68: Delhi | T68: Telangana | U68: Mobile App | V68: Credit Card | W68: Fashion | X68: Sneakers | Y68: BrandC | Z68: 4 | AA68: 2836.21
O69: 10197 | P69: 1742 | Q69: 45263 | R69: 45266 | S69: Delhi | T69: Karnataka | U69: Mobile App | V69: Cash on Delivery | W69: Electronics | X69: Smartphone | Y69: BrandC | Z69: 4 | AA69: 1256.21
O70: 10007 | P70: 1700 | Q70: 45050 | R70: 45054 | S70: Bengaluru | T70: Telangana | U70: Mobile App | V70: UPI | W70: Fashion | X70: Sneakers | Y70: BrandC | Z70: 5 | AA70: 3030.42
O71: 10107 | P71: 1862 | Q71: 45058 | R71: 45064 | S71: Mumbai | T71: Karnataka | U71: Mobile App | V71: UPI | W71: Beauty | X71: Perfume | Y71: BrandC | Z71: 5 | AA71: 1063.01
O72: 10198 | P72: 1240 | Q72: 45291 | R72: 45292 | S72: Bengaluru | T72: Telangana | U72: Mobile App | V72: Net Banking | W72: Home & Kitchen | X72: Cookware Set | Y72: BrandC | Z72: 5 | AA72: 1227.02
O73: 10226 | P73: 1619 | Q73: 45290 | R73: 45291 | S73: Kolkata | T73: Karnataka | U73: Mobile App | V73: Net Banking | W73: Electronics | X73: Laptop | Y73: BrandC | Z73: 5 | AA73: 620.13
O74: 10494 | P74: 1322 | Q74: 45151 | R74: 45154 | S74: Kolkata | T74: Telangana | U74: Mobile App | V74: UPI | W74: Books | X74: Biography | Y74: BrandC | Z74: 5 | AA74: 529.59
O75: 10056 | P75: 1831 | Q75: 44929 | R75: 44934 | S75: Kolkata | T75: West Bengal | U75: Mobile App | V75: Net Banking | W75: Books | X75: Textbook | Y75: BrandC | Z75: 6 | AA75: 3402.72
... O122: 10093 | P122: 1565 | Q122: 44980 | R122: 44982 | S122: Hyderabad | T122: West Bengal | U122: Mobile App | V122: Net Banking | W122: Beauty | X122: Lipstick | Y122: BrandE | Z122: 9 | AA122: 1938.76

Sheet Sheet9
A1: Batch Code | B1: ILT Hours | C1: ILT %
A2: ANP-D2475 | B2: 118.57 | C2: 0.6854
A3: ANP-D3870 | B3: 26.93 | C3: 0.1557
A4: ANP-D4972 | B4: 33.38 | C4: 0.193
A5: ANP-D2474 | B5: 112.52 | C5: 0.6504
A6: ANP-D4971 | B6: 31.03 | C6: 0.1794
A7: ANP-D3872 | B7: 23.88 | C7: 0.1381

Sheet Sheet16
B13: Name | C13: Sub1 | D13: Sub2 | E13: Sub3
B14: Soham | C14: 65 | D14: 68 | E14: 90
B15: Amiya | C15: 45 | D15: 64 | E15: 98
B16: Ajay | C16: 56 | D16: 89 | E16: 73
B17: Nisha | C17: 83 | D17: 87 | E17: 51
B18: Sahil | C18: 78 | D18: 90 | E18: 68
B19: Riya | C19: 60 | D19: 87 | E19: 93
B20: Nilay | C20: 65 | D20: 98 | E20: 78

Sheet Sheet17
G2: Name | H2: Sub1 | I2: Sub2 | J2: Sub3
G3: Soham | H3: 65 | I3: 68 | J3: 100
G4: Amiya | H4: 45 | I4: 64 | J4: 98
G5: Ajay | H5: 56 | I5: 89 | J5: 73
G6: Nisha | H6: 83 | I6: 87 | J6: 51
G7: Sahil | H7: 78 | I7: 90 | J7: 68
G8: Riya | H8: 60 | I8: 87 | J8: 93
G9: Nilay | H9: 65 | I9: 98 | J9: 78

Sheet Sheet18
E10: Name | F10: Sub1 | G10: Sub2 | H10: Sub3
E11: Soham | F11: 65 | G11: 68 | H11: 90
E12: Amiya | F12: 45 | G12: 64 | H12: 98
E13: Ajay | F13: 56 | G13: 89 | H13: 73
E14: Nisha | F14: 83 | G14: 87 | H14: 51
E15: Sahil | F15: 78 | G15: 90 | H15: 68
E16: Riya | F16: 60 | G16: 87 | H16: 93
E17: Nilay | F17: 65 | G17: 98 | H17: 78

Sheet Sheet19
B2: =SUM(Sheet16:Sheet18!B2) -> 0 | C2: =SUM(Sheet16:Sheet18!C2) -> 0 | D2: =SUM(Sheet16:Sheet18!D2) -> 0
B3: =SUM(Sheet16:Sheet18!B3) -> 0 | C3: =SUM(Sheet16:Sheet18!C3) -> 0 | D3: =SUM(Sheet16:Sheet18!D3) -> 0
B4: =SUM(Sheet16:Sheet18!B4) -> 0 | C4: =SUM(Sheet16:Sheet18!C4) -> 0 | D4: =SUM(Sheet16:Sheet18!D4) -> 0
B5: =SUM(Sheet16:Sheet18!B5) -> 0 | C5: =SUM(Sheet16:Sheet18!C5) -> 0 | D5: =SUM(Sheet16:Sheet18!D5) -> 0
B6: =SUM(Sheet16:Sheet18!B6) -> 0 | C6: =SUM(Sheet16:Sheet18!C6) -> 0 | D6: =SUM(Sheet16:Sheet18!D6) -> 0 | J6: Sub1 | K6: Sub2 | L6: Sub3
I7: Anp-D4972_Class Work | J7: =Sheet16!$C$14 -> 65 | K7: =Sheet16!$D$14 -> 68 | L7: =Sheet16!$E$14 -> 90
I8: Anp-D4972_Class Work | J8: =Sheet17!$H$3 -> 65 | K8: =Sheet17!$I$3 -> 68 | L8: =Sheet17!$J$3 -> 100
I9: Anp-D4972_Class Work | J9: =Sheet18!$F$11 -> 65 | K9: =Sheet18!$G$11 -> 68 | L9: =Sheet18!$H$11 -> 90
B10: =SUM(Sheet16:Sheet18!B7) -> 0 | C10: =SUM(Sheet16:Sheet18!C7) -> 0 | D10: =SUM(Sheet16:Sheet18!D7) -> 0 | H10: Soham | J10: =SUM(J7:J9) -> 195 | K10: =SUM(K7:K9) -> 204 | L10: =SUM(L7:L9) -> 280
I11: Anp-D4972_Class Work | J11: =Sheet16!$C$15 -> 45 | K11: =Sheet16!$D$15 -> 64 | L11: =Sheet16!$E$15 -> 98
I12: Anp-D4972_Class Work | J12: =Sheet17!$H$4 -> 45 | K12: =Sheet17!$I$4 -> 64 | L12: =Sheet17!$J$4 -> 98
I13: Anp-D4972_Class Work | J13: =Sheet18!$F$12 -> 45 | K13: =Sheet18!$G$12 -> 64 | L13: =Sheet18!$H$12 -> 98
H14: Amiya | J14: =SUM(J11:J13) -> 135 | K14: =SUM(K11:K13) -> 192 | L14: =SUM(L11:L13) -> 294
I15: Anp-D4972_Class Work | J15: =Sheet16!$C$16 -> 56 | K15: =Sheet16!$D$16 -> 89 | L15: =Sheet16!$E$16 -> 73
I16: Anp-D4972_Class Work | J16: =Sheet17!$H$5 -> 56 | K16: =Sheet17!$I$5 -> 89 | L16: =Sheet17!$J$5 -> 73
I17: Anp-D4972_Class Work | J17: =Sheet18!$F$13 -> 56 | K17: =Sheet18!$G$13 -> 89 | L17: =Sheet18!$H$13 -> 73
H18: Ajay | J18: =SUM(J15:J17) -> 168 | K18: =SUM(K15:K17) -> 267 | L18: =SUM(L15:L17) -> 219
I19: Anp-D4972_Class Work | J19: =Sheet16!$C$17 -> 83 | K19: =Sheet16!$D$17 -> 87 | L19: =Sheet16!$E$17 -> 51
I20: Anp-D4972_Class Work | J20: =Sheet17!$H$6 -> 83 | K20: =Sheet17!$I$6 -> 87 | L20: =Sheet17!$J$6 -> 51
I21: Anp-D4972_Class Work | J21: =Sheet18!$F$14 -> 83 | K21: =Sheet18!$G$14 -> 87 | L21: =Sheet18!$H$14 -> 51
H22: Nisha | J22: =SUM(J19:J21) -> 249 | K22: =SUM(K19:K21) -> 261 | L22: =SUM(L19:L21) -> 153
I23: Anp-D4972_Class Work | J23: =Sheet16!$C$18 -> 78 | K23: =Sheet16!$D$18 -> 90 | L23: =Sheet16!$E$18 -> 68
I24: Anp-D4972_Class Work | J24: =Sheet17!$H$7 -> 78 | K24: =Sheet17!$I$7 -> 90 | L24: =Sheet17!$J$7 -> 68
I25: Anp-D4972_Class Work | J25: =Sheet18!$F$15 -> 78 | K25: =Sheet18!$G$15 -> 90 | L25: =Sheet18!$H$15 -> 68
H26: Sahil | J26: =SUM(J23:J25) -> 234 | K26: =SUM(K23:K25) -> 270 | L26: =SUM(L23:L25) -> 204
I27: Anp-D4972_Class Work | J27: =Sheet16!$C$19 -> 60 | K27: =Sheet16!$D$19 -> 87 | L27: =Sheet16!$E$19 -> 93
I28: Anp-D4972_Class Work | J28: =Sheet17!$H$8 -> 60 | K28: =Sheet17!$I$8 -> 87 | L28: =Sheet17!$J$8 -> 93
I29: Anp-D4972_Class Work | J29: =Sheet18!$F$16 -> 60 | K29: =Sheet18!$G$16 -> 87 | L29: =Sheet18!$H$16 -> 93
H30: Riya | J30: =SUM(J27:J29) -> 180 | K30: =SUM(K27:K29) -> 261 | L30: =SUM(L27:L29) -> 279
I31: Anp-D4972_Class Work | J31: =Sheet16!$C$20 -> 65 | K31: =Sheet16!$D$20 -> 98 | L31: =Sheet16!$E$20 -> 78
I32: Anp-D4972_Class Work | J32: =Sheet17!$H$9 -> 65 | K32: =Sheet17!$I$9 -> 98 | L32: =Sheet17!$J$9 -> 78
I33: Anp-D4972_Class Work | J33: =Sheet18!$F$17 -> 65 | K33: =Sheet18!$G$17 -> 98 | L33: =Sheet18!$H$17 -> 78
H34: Nilay | J34: =SUM(J31:J33) -> 195 | K34: =SUM(K31:K33) -> 294 | L34: =SUM(L31:L33) -> 234

Sheet Sheet3
C2: Mon | E2: Jan | F2: Mango
C3: Tue | E3: Feb | F3: PineApple
C4: Wed | E4: Mar | F4: Orange | I4: Rose | N4: Mon | P4: Mon
C5: Thu | E5: Apr | F5: Apple | I5: Hibiscus | N5: Tue | P5: Tue
C6: Fri | E6: May | F6: Grape | I6: Mogra | N6: Wed | P6: Wed
C7: Sat | E7: Jun | F7: Mango | I7: Marigold | N7: Thu | P7: Thu
C8: Sun | E8: Jul | F8: PineApple | N8: Fri | P8: Fri
C9: Mon | E9: Aug | F9: Orange | N9: Sat | P9: Mon
C10: Tue | E10: Sep | F10: Apple | K10: Mogra | N10: Sun | P10: Tue
F11: Grape | K11: Marigold | N11: Mon | P11: Wed
K12: Rose | N12: Tue | P12: Thu
K13: Hibiscus | P13: Fri
K14: Mogra
K15: Marigold
K16: Rose
K17: Hibiscus

Sheet Sheet2
A1: Name | B1: Sub1 | C1: Sub2 | D1: Sub3 | E1: Total | F1: Average | G1: Grade
I3: >=90 | J3: A
I4: >=70 | J4: B
I5: >=50 | J5: C
I6: >=40 | J6: Pass
I7: <40 | J7: Fail
I9: Use Nested IF

Sheet Sheet4
A1: Order ID | B1: 10001 | C1: 10002 | D1: 10003 | E1: 10004 | F1: 10005 | G1: 10006 | H1: 10007 | I1: 10008 | J1: 10009 | K1: 10010 | L1: 10011 | M1: 10012 | N1: 10013 | O1: 10014 | P1: 10015 | Q1: 10016 | R1: 10017 | S1: 10018 | T1: 10019 | U1: 10020 | V1: 10021 | W1: 10022 | X1: 10023 | Y1: 10024 | Z1: 10025 | AA1: 10026 | AB1: 10027 | AC1: 10028 | AD1: 10029 | AE1: 10030 | AF1: 10031 | AG1: 10032 | AH1: 10033 | AI1: 10034 | AJ1: 10035 | AK1: 10036 | AL1: 10037 | AM1: 10038 | AN1: 10039 | AO1: 10040 | AP1: 10041 | AQ1: 10042 | AR1: 10043 | AS1: 10044 | AT1: 10045 | AU1: 10046 | AV1: 10047 | AW1: 10048 | AX1: 10049 | AY1: 10050 | AZ1: 10052 | BA1: 10053 | BB1: 10054 | BC1: 10055 | BD1: 10056 | BE1: 10057 | BF1: 10059 | BG1: 10060 | BH1: 10061 | BI1: 10063 | BJ1: 10064 | BK1: 10065 | BL1: 10066 | BM1: 10067 | BN1: 10068 | BO1: 10069 | BP1: 10070 | BQ1: 10071 | BR1: 10072 | BS1: 10073 | BT1: 10074 | BU1: 10075 | BV1: 10076 | BW1: 10077 | BX1: 10079 | BY1: 10080 | BZ1: 10081 | CA1: 10082 | CB1: 10083 | CC1: 10084 | CD1: 10085 | CE1: 10086 | CF1: 10087 | CG1: 10088 | CH1: 10091 | CI1: 10092 | CJ1: 10093 | CK1: 10094 | CL1: 10095 | CM1: 10096 | CN1: 10097 | CO1: 10098 | CP1: 10099 | CQ1: 10100 | CR1: 10101 | CS1: 10102 | CT1: 10103 | CU1: 10105 | CV1: 10106 | CW1: 10107 | CX1: 10108 | CY1: 10110 | CZ1: 10111 | DA1: 10112 | DB1: 10113 | DC1: 10114 | DD1: 10115 | DE1: 10116 | DF1: 10117 | DG1: 10118 | DH1: 10119 | DI1: 10120 | DJ1: 10121 | DK1: 10122 | DL1: 10123 | DM1: 10124 | DN1: 10125 | DO1: 10126 | DP1: 10127 | DQ1: 10128 | DR1: 10129 | DS1: 10130 | DT1: 10131 | DU1: 10132 | DV1: 10133 | DW1: 10135 | DX1: 10136 | DY1: 10138 | DZ1: 10139 | EA1: 10140 | EB1: 10141 | EC1: 10142 | ED1: 10143 | EE1: 10144 | EF1: 10145 | EG1: 10146 | EH1: 10147 | EI1: 10148 | EJ1: 10149 | EK1: 10150 | EL1: 10151 | EM1: 10152 | EN1: 10154 | EO1: 10155 | EP1: 10156 | EQ1: 10157 | ER1: 10158 | ES1: 10159 | ET1: 10160 | EU1: 10161 | EV1: 10162 | EW1: 10163 | EX1: 10164 | EY1: 10165 | EZ1: 10166 | FA1: 10167 | FB1: 10168 | FC1: 10170 | FD1: 10171 | FE1: 10172 | FF1: 10173 | FG1: 10174 | FH1: 10175 | FI1: 10178 | FJ1: 10179 | FK1: 10180 | FL1: 10181 | FM1: 10183 | FN1: 10184 | FO1: 10185 | FP1: 10186 | FQ1: 10187 | FR1: 10188 | FS1: 10190 | FT1: 10191 | FU1: 10192 | FV1: 10193 | FW1: 10194 | FX1: 10195 | FY1: 10196 | FZ1: 10197 | GA1: 10198 | GB1: 10199 | GC1: 10200 | GD1: 10201 | GE1: 10202 | GF1: 10207 | GG1: 10208 | GH1: 10209 | GI1: 10210 | GJ1: 10211 | GK1: 10212 | GL1: 10214 | GM1: 10215 | GN1: 10216 | GO1: 10217 | GP1: 10218 | GQ1: 10220 | GR1: 10222 | GS1: 10223 | GT1: 10226 | GU1: 10229 | GV1: 10232 | GW1: 10233 | GX1: 10234 | GY1: 10235 | GZ1: 10238 | HA1: 10239 | HB1: 10240 | HC1: 10241 | HD1: 10243 | HE1: 10244 | HF1: 10245 | HG1: 10246 | HH1: 10247 | HI1: 10248 | HJ1: 10249 | HK1: 10251 | HL1: 10252 | HM1: 10253 | HN1: 10254 | HO1: 10257 | HP1: 10260 | HQ1: 10261 | HR1: 10262 | HS1: 10263 | HT1: 10264 | HU1: 10266 | HV1: 10267 | HW1: 10268 | HX1: 10269 | HY1: 10270 | HZ1: 10271 | IA1: 10273 | IB1: 10274 | IC1: 10275 | ID1: 10277 | IE1: 10280 | IF1: 10281 | IG1: 10286 | IH1: 10287 | II1: 10289 | IJ1: 10290 | IK1: 10291 | IL1: 10294 | IM1: 10295 | IN1: 10296 | IO1: 10302 | IP1: 10303 | IQ1: 10304 | IR1: 10305 | IS1: 10306 | IT1: 10307 | IU1: 10308 | IV1: 10309 | IW1: 10311 | IX1: 10312 | IY1: 10313 | IZ1: 10314 | JA1: 10315 | JB1: 10316 | JC1: 10317 | JD1: 10318 | JE1: 10320 | JF1: 10321 | JG1: 10322 | JH1: 10324 | JI1: 10325 | JJ1: 10326 | JK1: 10327 | JL1: 10328 | JM1: 10329 | JN1: 10330 | JO1: 10332 | JP1: 10336 | JQ1: 10338 | JR1: 10339 | JS1: 10341 | JT1: 10342 | JU1: 10343 | JV1: 10344 | JW1: 10345 | JX1: 10347 | JY1: 10350 | JZ1: 10351 | KA1: 10352 | KB1: 10355 | KC1: 10356 | KD1: 10357 | KE1: 10358 | KF1: 10359 | KG1: 10360 | KH1: 10361 | KI1: 10365 | KJ1: 10366 | KK1: 10367 | KL1: 10369 | KM1: 10370 | KN1: 10371 | KO1: 10372 | KP1: 10373 | KQ1: 10374 | KR1: 10376 | KS1: 10379 | KT1: 10381 | KU1: 10383 | KV1: 10384 | KW1: 10385 | KX1: 10386 | KY1: 10387 | KZ1: 10388 | LA1: 10390 | LB1: 10392 | LC1: 10393 | LD1: 10394 | LE1: 10395 | LF1: 10396 | LG1: 10398 | LH1: 10399 | LI1: 10403 | LJ1: 10405 | LK1: 10406 | LL1: 10407 | LM1: 10409 | LN1: 10411 | LO1: 10413 | LP1: 10414 | LQ1: 10417 | LR1: 10418 | LS1: 10422 | LT1: 10423 | LU1: 10427 | LV1: 10431 | LW1: 10434 | LX1: 10435 | LY1: 10436 | LZ1: 10438 | MA1: 10439 | MB1: 10440 | MC1: 10441 | MD1: 10442 | ME1: 10444 | MF1: 10447 | MG1: 10448 | MH1: 10452 | MI1: 10454 | MJ1: 10455 | MK1: 10457 | ML1: 10460 | MM1: 10463 | MN1: 10464 | MO1: 10465 | MP1: 10466 | MQ1: 10468 | MR1: 10470 | MS1: 10472 | MT1: 10480 | MU1: 10481 | MV1: 10482 | MW1: 10485 | MX1: 10486 | MY1: 10487 | MZ1: 10489 | NA1: 10490 | NB1: 10491 | NC1: 10493 | ND1: 10494 | NE1: 10495 | NF1: 10496 | NG1: 10497 | NH1: 10498 | NI1: 10500
A2: Customer ID | B2: 1102 | C2: 1435 | D2: 1860 | E2: 1270 | F2: 1106 | G2: 1071 | H2: 1700 | I2: 1020 | J2: 1614 | K2: 1121 | L2: 1466 | M2: 1214 | N2: 1330 | O2: 1458 | P2: 1087 | Q2: 1372 | R2: 1099 | S2: 1871 | T2: 1663 | U2: 1130 | V2: 1661 | W2: 1308 | X2: 1769 | Y2: 1343 | Z2: 1491 | AA2: 1413 | AB2: 1805 | AC2: 1385 | AD2: 1191 | AE2: 1955 | AF2: 1276 | AG2: 1160 | AH2: 1459 | AI2: 1313 | AJ2: 1021 | AK2: 1252 | AL2: 1747 | AM2: 1856 | AN2: 1560 | AO2: 1474 | AP2: 1058 | AQ2: 1510 | AR2: 1681 | AS2: 1475 | AT2: 1699 | AU2: 1975 | AV2: 1782 | AW2: 1189 | AX2: 1957 | AY2: 1686 | AZ2: 1562 | BA2: 1875 | BB2: 1566 | BC2: 1243 | BD2: 1831 | BE2: 1504 | BF2: 1484 | BG2: 1818 | BH2: 1646 | BI2: 1840 | BJ2: 1166 | BK2: 1273 | BL2: 1387 | BM2: 1600 | BN2: 1315 | BO2: 1013 | BP2: 1241 | BQ2: 1776 | BR2: 1345 | BS2: 1564 | BT2: 1897 | BU2: 1339 | BV2: 1091 | BW2: 1366 | BX2: 1454 | BY2: 1427 | BZ2: 1508 | CA2: 1775 | CB2: 1942 | CC2: 1034 | CD2: 1205 | CE2: 1080 | CF2: 1931 | CG2: 1561 | CH2: 1001 | CI2: 1389 | CJ2: 1565 | CK2: 1105 | CL2: 1771 | CM2: 1821 | CN2: 1476 | CO2: 1702 | CP2: 1401 | CQ2: 1729 | CR2: 1555 | CS2: 1161 | CT2: 1201 | CU2: 1995 | CV2: 1269 | CW2: 1862 | CX2: 1815 | CY2: 1455 | CZ2: 1461 | DA2: 1726 | DB2: 1251 | DC2: 1701 | DD2: 1295 | DE2: 1724 | DF2: 1719 | DG2: 1748 | DH2: 1337 | DI2: 1878 | DJ2: 1052 | DK2: 1791 | DL2: 1921 | DM2: 1216 | DN2: 1763 | DO2: 1187 | DP2: 1379 | DQ2: 1492 | DR2: 1040 | DS2: 1156 | DT2: 1014 | DU2: 1812 | DV2: 1064 | DW2: 1838 | DX2: 1520 | DY2: 1128 | DZ2: 1647 | EA2: 1471 | EB2: 1062 | EC2: 1138 | ED2: 1498 | EE2: 1592 | EF2: 1391 | EG2: 1674 | EH2: 1418 | EI2: 1288 | EJ2: 1378 | EK2: 1772 | EL2: 1489 | EM2: 1230 | EN2: 1027 | EO2: 1134 | EP2: 1200 | EQ2: 1839 | ER2: 1779 | ES2: 1929 | ET2: 1032 | EU2: 1047 | EV2: 1502 | EW2: 1406 | EX2: 1573 | EY2: 1727 | EZ2: 1804 | FA2: 1098 | FB2: 1683 | FC2: 1725 | FD2: 1986 | FE2: 1546 | FF2: 1960 | FG2: 1738 | FH2: 1612 | FI2: 1642 | FJ2: 1768 | FK2: 1004 | FL2: 1217 | FM2: 1766 | FN2: 1397 | FO2: 1870 | FP2: 1794 | FQ2: 1392 | FR2: 1206 | FS2: 1857 | FT2: 1553 | FU2: 1891 | FV2: 1460 | FW2: 1690 | FX2: 1574 | FY2: 1863 | FZ2: 1742 | GA2: 1240 | GB2: 1563 | GC2: 1095 | GD2: 1899 | GE2: 1733 | GF2: 1654 | GG2: 1170 | GH2: 1540 | GI2: 1035 | GJ2: 1524 | GK2: 1159 | GL2: 1698 | GM2: 1242 | GN2: 1085 | GO2: 1795 | GP2: 1577 | GQ2: 1556 | GR2: 1952 | GS2: 1645 | GT2: 1619 | GU2: 1797 | GV2: 1639 | GW2: 1505 | GX2: 1347 | GY2: 1472 | GZ2: 1224 | HA2: 1384 | HB2: 1376 | HC2: 1282 | HD2: 1632 | HE2: 1627 | HF2: 1972 | HG2: 1744 | HH2: 1258 | HI2: 1358 | HJ2: 1709 | HK2: 1410 | HL2: 1648 | HM2: 1317 | HN2: 1676 | HO2: 1233 | HP2: 1974 | HQ2: 1826 | HR2: 1373 | HS2: 1671 | HT2: 1607 | HU2: 1232 | HV2: 1691 | HW2: 1112 | HX2: 1829 | HY2: 1496 | HZ2: 1441 | IA2: 1267 | IB2: 1509 | IC2: 1806 | ID2: 1386 | IE2: 1624 | IF2: 1951 | IG2: 1641 | IH2: 1219 | II2: 1854 | IJ2: 1996 | IK2: 1735 | IL2: 1402 | IM2: 1637 | IN2: 1129 | IO2: 1415 | IP2: 1246 | IQ2: 1835 | IR2: 1438 | IS2: 1202 | IT2: 1183 | IU2: 1122 | IV2: 1400 | IW2: 1293 | IX2: 1279 | IY2: 1836 | IZ2: 1883 | JA2: 1609 | JB2: 1197 | JC2: 1981 | JD2: 1906 | JE2: 1751 | JF2: 1143 | JG2: 1608 | JH2: 1123 | JI2: 1186 | JJ2: 1325 | JK2: 1463 | JL2: 1348 | JM2: 1770 | JN2: 1659 | JO2: 1954 | JP2: 1962 | JQ2: 1146 | JR2: 1147 | JS2: 1710 | JT2: 1819 | JU2: 1488 | JV2: 1928 | JW2: 1935 | JX2: 1550 | JY2: 1640 | JZ2: 1778 | KA2: 1987 | KB2: 1945 | KC2: 1150 | KD2: 1414 | KE2: 1989 | KF2: 1297 | KG2: 1610 | KH2: 1262 | KI2: 1623 | KJ2: 1571 | KK2: 1880 | KL2: 1896 | KM2: 1303 | KN2: 1253 | KO2: 1651 | KP2: 1452 | KQ2: 1036 | KR2: 1008 | KS2: 1658 | KT2: 1207 | KU2: 1403 | KV2: 1151 | KW2: 1053 | KX2: 1119 | KY2: 1672 | KZ2: 1919 | LA2: 1586 | LB2: 1967 | LC2: 1419 | LD2: 1421 | LE2: 1103 | LF2: 1851 | LG2: 1226 | LH2: 1111 | LI2: 1152 | LJ2: 1913 | LK2: 1895 | LL2: 1877 | LM2: 1705 | LN2: 1162 | LO2: 1956 | LP2: 1680 | LQ2: 1579 | LR2: 1800 | LS2: 1915 | LT2: 1503 | LU2: 1194 | LV2: 1687 | LW2: 1882 | LX2: 1469 | LY2: 1374 | LZ2: 1749 | MA2: 1669 | MB2: 1037 | MC2: 1229 | MD2: 1364 | ME2: 1437 | MF2: 1026 | MG2: 1225 | MH2: 1283 | MI2: 1959 | MJ2: 1480 | MK2: 1828 | ML2: 1515 | MM2: 1048 | MN2: 1511 | MO2: 1016 | MP2: 1171 | MQ2: 1157 | MR2: 1045 | MS2: 1517 | MT2: 1301 | MU2: 1180 | MV2: 1606 | MW2: 1992 | MX2: 1115 | MY2: 1190 | MZ2: 1980 | NA2: 1927 | NB2: 1982 | NC2: 1255 | ND2: 1322 | NE2: 1127 | NF2: 1017 | NG2: 1792 | NH2: 1734 | NI2: 1569
A3: Order Date | B3: 45197 | C3: 45199 | D3: 45109 | E3: 45079 | F3: 45241 | G3: 45260 | H3: 45050 | I3: 45040 | J3: 45204 | K3: 45139 | L3: 45098 | M3: 45214 | N3: 45100 | O3: 45039 | P3: 45048 | Q3: 44958 | R3: 45148 | S3: 45045 | T3: 44965 | U3: 45194 | V3: 45159 | W3: 44944 | X3: 45075 | Y3: 45075 | Z3: 45052 | AA3: 45228 | AB3: 45286 | AC3: 45164 | AD3: 45061 | AE3: 45077 | AF3: 45162 | AG3: 45150 | AH3: 45129 | AI3: 45182 | AJ3: 45012 | AK3: 45076 | AL3: 45161 | AM3: 45271 | AN3: 44948 | AO3: 45274 | AP3: 45211 | AQ3: 45195 | AR3: 45184 | AS3: 44955 | AT3: 45139 | AU3: 45209 | AV3: 44976 | AW3: 45021 | AX3: 45014 | AY3: 44970 | AZ3: 45097 | BA3: 45115 | BB3: 45279 | BC3: 45110 | BD3: 44929 | BE3: 45117 | BF3: 44945 | BG3: 44949 | BH3: 44956 | BI3: 45034 | BJ3: 45207 | BK3: 45054 | BL3: 45155 | BM3: 45037 | BN3: 45062 | BO3: 45288 | BP3: 45112 | BQ3: 45070 | BR3: 44998 | BS3: 45055 | BT3: 45290 | BU3: 45187 | BV3: 44929 | BW3: 45030 | BX3: 45246 | BY3: 45288 | BZ3: 45280 | CA3: 44936 | CB3: 45228 | CC3: 45157 | CD3: 45145 | CE3: 44992 | CF3: 45038 | CG3: 44939 | CH3: 45016 | CI3: 45240 | CJ3: 44980 | CK3: 44938 | CL3: 45135 | CM3: 44940 | CN3: 45047 | CO3: 44946 | CP3: 45001 | CQ3: 45169 | CR3: 45149 | CS3: 44996 | CT3: 45238 | CU3: 45027 | CV3: 45112 | CW3: 45058 | CX3: 45037 | CY3: 44946 | CZ3: 44950 | DA3: 45153 | DB3: 45080 | DC3: 45219 | DD3: 45156 | DE3: 45236 | DF3: 45285 | DG3: 45128 | DH3: 44964 | DI3: 45186 | DJ3: 45114 | DK3: 44983 | DL3: 44946 | DM3: 45199 | DN3: 45045 | DO3: 44997 | DP3: 44930 | DQ3: 45147 | DR3: 44940 | DS3: 44929 | DT3: 45142 | DU3: 45155 | DV3: 45262 | DW3: 44981 | DX3: 45180 | DY3: 45088 | DZ3: 45084 | EA3: 45008 | EB3: 45085 | EC3: 45114 | ED3: 44986 | EE3: 45231 | EF3: 45245 | EG3: 45137 | EH3: 45078 | EI3: 45035 | EJ3: 45002 | EK3: 44956 | EL3: 45240 | EM3: 45043 | EN3: 45118 | EO3: 44945 | EP3: 45099 | EQ3: 45154 | ER3: 45276 | ES3: 45109 | ET3: 45039 | EU3: 45109 | EV3: 45072 | EW3: 45245 | EX3: 45042 | EY3: 45039 | EZ3: 45177 | FA3: 45177 | FB3: 45229 | FC3: 45044 | FD3: 45227 | FE3: 45087 | FF3: 45124 | FG3: 45186 | FH3: 45074 | FI3: 45124 | FJ3: 44973 | FK3: 45004 | FL3: 45050 | FM3: 45285 | FN3: 45063 | FO3: 45016 | FP3: 45251 | FQ3: 44987 | FR3: 45064 | FS3: 45185 | FT3: 45033 | FU3: 45039 | FV3: 45276 | FW3: 45180 | FX3: 45044 | FY3: 45124 | FZ3: 45263 | GA3: 45291 | GB3: 44977 | GC3: 45171 | GD3: 44961 | GE3: 45228 | GF3: 45000 | GG3: 45118 | GH3: 45187 | GI3: 45282 | GJ3: 44996 | GK3: 45016 | GL3: 45052 | GM3: 45157 | GN3: 45221 | GO3: 45055 | GP3: 45206 | GQ3: 45026 | GR3: 45223 | GS3: 45108 | GT3: 45290 | GU3: 44957 | GV3: 44962 | GW3: 45139 | GX3: 45290 | GY3: 45032 | GZ3: 45089 | HA3: 45146 | HB3: 45196 | HC3: 45046 | HD3: 45108 | HE3: 45032 | HF3: 45143 | HG3: 45131 | HH3: 44996 | HI3: 44970 | HJ3: 45255 | HK3: 45154 | HL3: 45110 | HM3: 45033 | HN3: 45010 | HO3: 45289 | HP3: 45104 | HQ3: 44933 | HR3: 44996 | HS3: 45053 | HT3: 45086 | HU3: 45129 | HV3: 45074 | HW3: 45069 | HX3: 45125 | HY3: 45080 | HZ3: 45068 | IA3: 45091 | IB3: 45240 | IC3: 44947 | ID3: 44995 | IE3: 45144 | IF3: 45231 | IG3: 45043 | IH3: 45122 | II3: 45012 | IJ3: 45215 | IK3: 45007 | IL3: 44987 | IM3: 45280 | IN3: 44954 | IO3: 45024 | IP3: 45124 | IQ3: 45024 | IR3: 44991 | IS3: 45256 | IT3: 45267 | IU3: 44931 | IV3: 44928 | IW3: 45038 | IX3: 44983 | IY3: 44992 | IZ3: 45256 | JA3: 45024 | JB3: 45070 | JC3: 45051 | JD3: 45093 | JE3: 45002 | JF3: 45270 | JG3: 45220 | JH3: 45064 | JI3: 45025 | JJ3: 45118 | JK3: 45169 | JL3: 45245 | JM3: 44975 | JN3: 44958 | JO3: 44946 | JP3: 45069 | JQ3: 45139 | JR3: 45005 | JS3: 45042 | JT3: 45018 | JU3: 45196 | JV3: 45094 | JW3: 44984 | JX3: 44952 | JY3: 45180 | JZ3: 44970 | KA3: 45023 | KB3: 45188 | KC3: 45093 | KD3: 45205 | KE3: 45015 | KF3: 45104 | KG3: 45123 | KH3: 45233 | KI3: 44934 | KJ3: 45223 | KK3: 45090 | KL3: 44998 | KM3: 44981 | KN3: 44973 | KO3: 45164 | KP3: 45030 | KQ3: 45136 | KR3: 45242 | KS3: 45262 | KT3: 45185 | KU3: 45040 | KV3: 45289 | KW3: 44966 | KX3: 45146 | KY3: 45055 | KZ3: 44934 | LA3: 45102 | LB3: 45027 | LC3: 45186 | LD3: 45172 | LE3: 45201 | LF3: 44958 | LG3: 44938 | LH3: 45228 | LI3: 45035 | LJ3: 45084 | LK3: 45195 | LL3: 45088 | LM3: 45028 | LN3: 44985 | LO3: 45054 | LP3: 45209 | LQ3: 45057 | LR3: 45279 | LS3: 45059 | LT3: 45153 | LU3: 45137 | LV3: 45139 | LW3: 45057 | LX3: 45002 | LY3: 45212 | LZ3: 45082 | MA3: 45174 | MB3: 45144 | MC3: 45116 | MD3: 45089 | ME3: 44960 | MF3: 45264 | MG3: 45240 | MH3: 45076 | MI3: 45251 | MJ3: 45034 | MK3: 45276 | ML3: 45215 | MM3: 44992 | MN3: 45174 | MO3: 45082 | MP3: 44973 | MQ3: 45074 | MR3: 44927 | MS3: 45269 | MT3: 45117 | MU3: 44947 | MV3: 45153 | MW3: 45228 | MX3: 45068 | MY3: 44965 | MZ3: 45178 | NA3: 45259 | NB3: 45133 | NC3: 45041 | ND3: 45151 | NE3: 45060 | NF3: 45177 | NG3: 45145 | NH3: 45017 | NI3: 44972
A4: Ship Date | B4: 45203 | C4: 45203 | D4: 45114 | E4: 45087 | F4: 45244 | G4: 45263 | H4: 45054 | I4: 45041 | J4: 45213 | K4: 45147 | L4: 45106 | M4: 45220 | N4: 45107 | O4: 45045 | P4: 45057 | Q4: 44961 | R4: 45151 | S4: 45048 | T4: 44968 | U4: 45203 | V4: 45163 | W4: 44951 | X4: 45084 | Y4: 45082 | Z4: 45061 | AA4: 45231 | AB4: 45290 | AC4: 45172 | AD4: 45067 | AE4: 45082 | AF4: 45166 | AG4: 45158 | AH4: 45130 | AI4: 45191 | AJ4: 45013 | AK4: 45084 | AL4: 45165 | AM4: 45280 | AN4: 44953 | AO4: 45277 | AP4: 45220 | AQ4: 45204 | AR4: 45188 | AS4: 44959 | AT4: 45147 | AU4: 45211 | AV4: 44985 | AW4: 45027 | AX4: 45023 | AY4: 44978 | AZ4: 45098 | BA4: 45118 | BB4: 45281 | BC4: 45115 | BD4: 44934 | BE4: 45122 | BF4: 44950 | BG4: 44952 | BH4: 44957 | BI4: 45043 | BJ4: 45216 | BK4: 45058 | BL4: 45158 | BM4: 45038 | BN4: 45064 | BO4: 45296 | BP4: 45113 | BQ4: 45078 | BR4: 45005 | BS4: 45063 | BT4: 45296 | BU4: 45196 | BV4: 44932 | BW4: 45034 | BX4: 45254 | BY4: 45293 | BZ4: 45283 | CA4: 44942 | CB4: 45232 | CC4: 45166 | CD4: 45148 | CE4: 44996 | CF4: 45045 | CG4: 44946 | CH4: 45019 | CI4: 45246 | CJ4: 44982 | CK4: 44946 | CL4: 45137 | CM4: 44947 | CN4: 45056 | CO4: 44947 | CP4: 45009 | CQ4: 45176 | CR4: 45155 | CS4: 45002 | CT4: 45244 | CU4: 45029 | CV4: 45113 | CW4: 45064 | CX4: 45045 | CY4: 44947 | CZ4: 44959 | DA4: 45154 | DB4: 45083 | DC4: 45227 | DD4: 45159 | DE4: 45240 | DF4: 45293 | DG4: 45129 | DH4: 44970 | DI4: 45187 | DJ4: 45115 | DK4: 44991 | DL4: 44950 | DM4: 45200 | DN4: 45052 | DO4: 45002 | DP4: 44935 | DQ4: 45148 | DR4: 44946 | DS4: 44938 | DT4: 45151 | DU4: 45163 | DV4: 45267 | DW4: 44990 | DX4: 45181 | DY4: 45093 | DZ4: 45087 | EA4: 45015 | EB4: 45092 | EC4: 45123 | ED4: 44993 | EE4: 45234 | EF4: 45246 | EG4: 45145 | EH4: 45081 | EI4: 45043 | EJ4: 45010 | EK4: 44961 | EL4: 45241 | EM4: 45050 | EN4: 45126 | EO4: 44954 | EP4: 45106 | EQ4: 45161 | ER4: 45277 | ES4: 45113 | ET4: 45041 | EU4: 45111 | EV4: 45074 | EW4: 45249 | EX4: 45043 | EY4: 45043 | EZ4: 45179 | FA4: 45182 | FB4: 45232 | FC4: 45048 | FD4: 45228 | FE4: 45088 | FF4: 45127 | FG4: 45195 | FH4: 45081 | FI4: 45126 | FJ4: 44976 | FK4: 45006 | FL4: 45053 | FM4: 45294 | FN4: 45072 | FO4: 45023 | FP4: 45254 | FQ4: 44991 | FR4: 45070 | FS4: 45187 | FT4: 45039 | FU4: 45042 | FV4: 45284 | FW4: 45182 | FX4: 45045 | FY4: 45133 | FZ4: 45266 | GA4: 45292 | GB4: 44984 | GC4: 45176 | GD4: 44966 | GE4: 45229 | GF4: 45006 | GG4: 45123 | GH4: 45193 | GI4: 45284 | GJ4: 45000 | GK4: 45019 | GL4: 45061 | GM4: 45162 | GN4: 45227 | GO4: 45057 | GP4: 45209 | GQ4: 45035 | GR4: 45231 | GS4: 45117 | GT4: 45291 | GU4: 44959 | GV4: 44969 | GW4: 45143 | GX4: 45295 | GY4: 45040 | GZ4: 45093 | HA4: 45149 | HB4: 45198 | HC4: 45049 | HD4: 45109 | HE4: 45038 | HF4: 45148 | HG4: 45139 | HH4: 44998 | HI4: 44974 | HJ4: 45263 | HK4: 45155 | HL4: 45114 | HM4: 45034 | HN4: 45012 | HO4: 45297 | HP4: 45110 | HQ4: 44936 | HR4: 44998 | HS4: 45059 | HT4: 45091 | HU4: 45134 | HV4: 45079 | HW4: 45072 | HX4: 45132 | HY4: 45086 | HZ4: 45072 | IA4: 45100 | IB4: 45241 | IC4: 44951 | ID4: 45001 | IE4: 45149 | IF4: 45240 | IG4: 45050 | IH4: 45125 | II4: 45014 | IJ4: 45218 | IK4: 45008 | IL4: 44994 | IM4: 45284 | IN4: 44957 | IO4: 45027 | IP4: 45125 | IQ4: 45027 | IR4: 44993 | IS4: 45264 | IT4: 45273 | IU4: 44940 | IV4: 44936 | IW4: 45043 | IX4: 44990 | IY4: 44997 | IZ4: 45264 | JA4: 45029 | JB4: 45071 | JC4: 45056 | JD4: 45097 | JE4: 45005 | JF4: 45275 | JG4: 45222 | JH4: 45070 | JI4: 45030 | JJ4: 45124 | JK4: 45176 | JL4: 45250 | JM4: 44976 | JN4: 44966 | JO4: 44955 | JP4: 45072 | JQ4: 45145 | JR4: 45012 | JS4: 45048 | JT4: 45019 | JU4: 45204 | JV4: 45101 | JW4: 44993 | JX4: 44954 | JY4: 45185 | JZ4: 44972 | KA4: 45026 | KB4: 45191 | KC4: 45102 | KD4: 45213 | KE4: 45019 | KF4: 45105 | KG4: 45124 | KH4: 45234 | KI4: 44940 | KJ4: 45226 | KK4: 45095 | KL4: 45000 | KM4: 44987 | KN4: 44979 | KO4: 45167 | KP4: 45036 | KQ4: 45141 | KR4: 45251 | KS4: 45270 | KT4: 45188 | KU4: 45042 | KV4: 45297 | KW4: 44967 | KX4: 45154 | KY4: 45062 | KZ4: 44941 | LA4: 45103 | LB4: 45036 | LC4: 45191 | LD4: 45173 | LE4: 45206 | LF4: 44966 | LG4: 44943 | LH4: 45237 | LI4: 45037 | LJ4: 45091 | LK4: 45204 | LL4: 45090 | LM4: 45034 | LN4: 44993 | LO4: 45056 | LP4: 45212 | LQ4: 45065 | LR4: 45280 | LS4: 45061 | LT4: 45155 | LU4: 45140 | LV4: 45146 | LW4: 45062 | LX4: 45009 | LY4: 45213 | LZ4: 45091 | MA4: 45179 | MB4: 45149 | MC4: 45119 | MD4: 45094 | ME4: 44969 | MF4: 45265 | MG4: 45247 | MH4: 45082 | MI4: 45255 | MJ4: 45036 | MK4: 45280 | ML4: 45221 | MM4: 45000 | MN4: 45176 | MO4: 45089 | MP4: 44975 | MQ4: 45082 | MR4: 44936 | MS4: 45278 | MT4: 45119 | MU4: 44955 | MV4: 45162 | MW4: 45237 | MX4: 45077 | MY4: 44966 | MZ4: 45187 | NA4: 45261 | NB4: 45137 | NC4: 45043 | ND4: 45154 | NE4: 45063 | NF4: 45178 | NG4: 45151 | NH4: 45025 | NI4: 44977
A5: City | B5: Chennai | C5: Pune | D5: Chennai | E5: Bengaluru | F5: Kolkata | G5: Hyderabad | H5: Bengaluru | I5: Mumbai | J5: Chennai | K5: Bengaluru | L5: Bengaluru | M5: Mumbai | N5: Delhi | O5: Kolkata | P5: Hyderabad | Q5: Pune | R5: Delhi | S5: Chennai | T5: Bengaluru | U5: Mumbai | V5: Mumbai | W5: Kolkata | X5: Delhi | Y5: Pune | Z5: Kolkata | AA5: Bengaluru | AB5: Kolkata | AC5: Hyderabad | AD5: Mumbai | AE5: Mumbai | AF5: Chennai | AG5: Chennai | AH5: Pune | AI5: Bengaluru | AJ5: Hyderabad | AK5: Delhi | AL5: Kolkata | AM5: Pune | AN5: Bengaluru | AO5: Chennai | AP5: Kolkata | AQ5: Chennai | AR5: Kolkata | AS5: Delhi | AT5: Bengaluru | AU5: Kolkata | AV5: Hyderabad | AW5: Pune | AX5: Mumbai | AY5: Hyderabad | AZ5: Pune | BA5: Mumbai | BB5: Hyderabad | BC5: Kolkata | BD5: Kolkata | BE5: Kolkata | BF5: Hyderabad | BG5: Mumbai | BH5: Kolkata | BI5: Hyderabad | BJ5: Hyderabad | BK5: Chennai | BL5: Chennai | BM5: Delhi | BN5: Bengaluru | BO5: Chennai | BP5: Mumbai | BQ5: Chennai | BR5: Delhi | BS5: Hyderabad | BT5: Delhi | BU5: Hyderabad | BV5: Pune | BW5: Pune | BX5: Bengaluru | BY5: Chennai | BZ5: Mumbai | CA5: Mumbai | CB5: Kolkata | CC5: Hyderabad | CD5: Mumbai | CE5: Bengaluru | CF5: Hyderabad | CG5: Bengaluru | CH5: Kolkata | CI5: Mumbai | CJ5: Hyderabad | CK5: Pune | CL5: Hyderabad | CM5: Hyderabad | CN5: Kolkata | CO5: Kolkata | CP5: Mumbai | CQ5: Delhi | CR5: Delhi | CS5: Kolkata | CT5: Mumbai | CU5: Mumbai | CV5: Mumbai | CW5: Mumbai | CX5: Chennai | CY5: Mumbai | CZ5: Chennai | DA5: Kolkata | DB5: Delhi | DC5: Hyderabad | DD5: Pune | DE5: Delhi | DF5: Hyderabad | DG5: Pune | DH5: Delhi | DI5: Hyderabad | DJ5: Delhi | DK5: Delhi | DL5: Pune | DM5: Delhi | DN5: Delhi | DO5: Pune | DP5: Kolkata | DQ5: Mumbai | DR5: Bengaluru | DS5: Chennai | DT5: Bengaluru | DU5: Bengaluru | DV5: Hyderabad | DW5: Hyderabad | DX5: Mumbai | DY5: Pune | DZ5: Mumbai | EA5: Delhi | EB5: Kolkata | EC5: Delhi | ED5: Kolkata | EE5: Hyderabad | EF5: Kolkata | EG5: Hyderabad | EH5: Pune | EI5: Bengaluru | EJ5: Pune | EK5: Pune | EL5: Bengaluru | EM5: Kolkata | EN5: Hyderabad | EO5: Delhi | EP5: Hyderabad | EQ5: Delhi | ER5: Pune | ES5: Bengaluru | ET5: Pune | EU5: Mumbai | EV5: Kolkata | EW5: Delhi | EX5: Hyderabad | EY5: Bengaluru | EZ5: Delhi | FA5: Hyderabad | FB5: Kolkata | FC5: Kolkata | FD5: Chennai | FE5: Mumbai | FF5: Chennai | FG5: Bengaluru | FH5: Delhi | FI5: Hyderabad | FJ5: Kolkata | FK5: Chennai | FL5: Chennai | FM5: Chennai | FN5: Pune | FO5: Bengaluru | FP5: Kolkata | FQ5: Delhi | FR5: Hyderabad | FS5: Bengaluru | FT5: Hyderabad | FU5: Chennai | FV5: Mumbai | FW5: Bengaluru | FX5: Bengaluru | FY5: Kolkata | FZ5: Delhi | GA5: Bengaluru | GB5: Bengaluru | GC5: Chennai | GD5: Chennai | GE5: Hyderabad | GF5: Kolkata | GG5: Mumbai | GH5: Hyderabad | GI5: Chennai | GJ5: Pune | GK5: Delhi | GL5: Kolkata | GM5: Chennai | GN5: Kolkata | GO5: Kolkata | GP5: Kolkata | GQ5: Kolkata | GR5: Delhi | GS5: Mumbai | GT5: Kolkata | GU5: Delhi | GV5: Pune | GW5: Delhi | GX5: Kolkata | GY5: Hyderabad | GZ5: Bengaluru | HA5: Bengaluru | HB5: Delhi | HC5: Hyderabad | HD5: Kolkata | HE5: Bengaluru | HF5: Chennai | HG5: Delhi | HH5: Chennai | HI5: Pune | HJ5: Mumbai | HK5: Delhi | HL5: Kolkata | HM5: Hyderabad | HN5: Pune | HO5: Hyderabad | HP5: Pune | HQ5: Chennai | HR5: Chennai | HS5: Hyderabad | HT5: Chennai | HU5: Hyderabad | HV5: Hyderabad | HW5: Kolkata | HX5: Chennai | HY5: Pune | HZ5: Hyderabad | IA5: Mumbai | IB5: Kolkata | IC5: Delhi | ID5: Hyderabad | IE5: Mumbai | IF5: Mumbai | IG5: Chennai | IH5: Pune | II5: Kolkata | IJ5: Kolkata | IK5: Chennai | IL5: Pune | IM5: Bengaluru | IN5: Delhi | IO5: Delhi | IP5: Kolkata | IQ5: Hyderabad | IR5: Mumbai | IS5: Mumbai | IT5: Chennai | IU5: Kolkata | IV5: Bengaluru | IW5: Mumbai | IX5: Mumbai | IY5: Hyderabad | IZ5: Kolkata | JA5: Kolkata | JB5: Mumbai | JC5: Bengaluru | JD5: Chennai | JE5: Chennai | JF5: Kolkata | JG5: Chennai | JH5: Mumbai | JI5: Kolkata | JJ5: Kolkata | JK5: Pune | JL5: Pune | JM5: Hyderabad | JN5: Kolkata | JO5: Chennai | JP5: Delhi | JQ5: Pune | JR5: Chennai | JS5: Delhi | JT5: Chennai | JU5: Mumbai | JV5: Pune | JW5: Bengaluru | JX5: Chennai | JY5: Chennai | JZ5: Mumbai | KA5: Mumbai | KB5: Kolkata | KC5: Delhi | KD5: Kolkata | KE5: Chennai | KF5: Delhi | KG5: Bengaluru | KH5: Bengaluru | KI5: Delhi | KJ5: Chennai | KK5: Mumbai | KL5: Pune | KM5: Pune | KN5: Bengaluru | KO5: Delhi | KP5: Pune | KQ5: Kolkata | KR5: Kolkata | KS5: Chennai | KT5: Delhi | KU5: Kolkata | KV5: Pune | KW5: Delhi | KX5: Chennai | KY5: Mumbai | KZ5: Pune | LA5: Hyderabad | LB5: Pune | LC5: Hyderabad | LD5: Pune | LE5: Delhi | LF5: Mumbai | LG5: Pune | LH5: Delhi | LI5: Delhi | LJ5: Mumbai | LK5: Delhi | LL5: Pune | LM5: Kolkata | LN5: Mumbai | LO5: Kolkata | LP5: Mumbai | LQ5: Pune | LR5: Hyderabad | LS5: Delhi | LT5: Hyderabad | LU5: Hyderabad | LV5: Mumbai | LW5: Mumbai | LX5: Chennai | LY5: Chennai | LZ5: Mumbai | MA5: Bengaluru | MB5: Kolkata | MC5: Delhi | MD5: Chennai | ME5: Hyderabad | MF5: Bengaluru | MG5: Hyderabad | MH5: Mumbai | MI5: Bengaluru | MJ5: Chennai | MK5: Mumbai | ML5: Pune | MM5: Pune | MN5: Mumbai | MO5: Kolkata | MP5: Delhi | MQ5: Pune | MR5: Bengaluru | MS5: Chennai | MT5: Delhi | MU5: Bengaluru | MV5: Bengaluru | MW5: Delhi | MX5: Delhi | MY5: Hyderabad | MZ5: Bengaluru | NA5: Chennai | NB5: Delhi | NC5: Hyderabad | ND5: Kolkata | NE5: Chennai | NF5: Chennai | NG5: Delhi | NH5: Mumbai | NI5: Chennai
A6: State | B6: Delhi | C6: Tamil Nadu | D6: West Bengal | E6: West Bengal | F6: Karnataka | G6: Telangana | H6: Telangana | I6: Delhi | J6: West Bengal | K6: Karnataka | L6: Karnataka | M6: Tamil Nadu | N6: Tamil Nadu | O6: Karnataka | P6: Tamil Nadu | Q6: West Bengal | R6: Maharashtra | S6: West Bengal | T6: Karnataka | U6: Karnataka | V6: West Bengal | W6: Tamil Nadu | X6: Tamil Nadu | Y6: Telangana | Z6: Karnataka | AA6: Delhi | AB6: Telangana | AC6: Tamil Nadu | AD6: West Bengal | AE6: Tamil Nadu | AF6: West Bengal | AG6: Telangana | AH6: Karnataka | AI6: Tamil Nadu | AJ6: West Bengal | AK6: Karnataka | AL6: Delhi | AM6: West Bengal | AN6: Telangana | AO6: Delhi | AP6: Delhi | AQ6: Maharashtra | AR6: Tamil Nadu | AS6: West Bengal | AT6: Delhi | AU6: Maharashtra | AV6: Telangana | AW6: Karnataka | AX6: West Bengal | AY6: Delhi | AZ6: Maharashtra | BA6: Delhi | BB6: Tamil Nadu | BC6: Delhi | BD6: West Bengal | BE6: West Bengal | BF6: Telangana | BG6: Telangana | BH6: Maharashtra | BI6: Tamil Nadu | BJ6: Delhi | BK6: Karnataka | BL6: Tamil Nadu | BM6: Telangana | BN6: Telangana | BO6: Tamil Nadu | BP6: Telangana | BQ6: West Bengal | BR6: Maharashtra | BS6: Delhi | BT6: Maharashtra | BU6: Delhi | BV6: Delhi | BW6: Maharashtra | BX6: Delhi | BY6: Maharashtra | BZ6: Delhi | CA6: Karnataka | CB6: Tamil Nadu | CC6: West Bengal | CD6: Delhi | CE6: Karnataka | CF6: West Bengal | CG6: West Bengal | CH6: Delhi | CI6: Karnataka | CJ6: West Bengal | CK6: Delhi | CL6: Maharashtra | CM6: Delhi | CN6: Tamil Nadu | CO6: Maharashtra | CP6: Karnataka | CQ6: West Bengal | CR6: Delhi | CS6: Maharashtra | CT6: Tamil Nadu | CU6: Telangana | CV6: Tamil Nadu | CW6: Karnataka | CX6: West Bengal | CY6: Delhi | CZ6: Maharashtra | DA6: Telangana | DB6: Tamil Nadu | DC6: Tamil Nadu | DD6: Maharashtra | DE6: Telangana | DF6: Maharashtra | DG6: Delhi | DH6: Karnataka | DI6: Tamil Nadu | DJ6: Delhi | DK6: Karnataka | DL6: Delhi | DM6: Telangana | DN6: Tamil Nadu | DO6: Maharashtra | DP6: Maharashtra | DQ6: Karnataka | DR6: West Bengal | DS6: Telangana | DT6: Karnataka | DU6: West Bengal | DV6: Delhi | DW6: Delhi | DX6: Tamil Nadu | DY6: West Bengal | DZ6: Tamil Nadu | EA6: Maharashtra | EB6: West Bengal | EC6: Karnataka | ED6: Maharashtra | EE6: Maharashtra | EF6: Karnataka | EG6: Telangana | EH6: Maharashtra | EI6: West Bengal | EJ6: Tamil Nadu | EK6: Maharashtra | EL6: West Bengal | EM6: Delhi | EN6: Tamil Nadu | EO6: West Bengal | EP6: Karnataka | EQ6: Tamil Nadu | ER6: Telangana | ES6: Delhi | ET6: Karnataka | EU6: Telangana | EV6: West Bengal | EW6: Tamil Nadu | EX6: Delhi | EY6: Karnataka | EZ6: Telangana | FA6: Telangana | FB6: Delhi | FC6: Delhi | FD6: Telangana | FE6: Maharashtra | FF6: Karnataka | FG6: Delhi | FH6: Telangana | FI6: West Bengal | FJ6: Delhi | FK6: West Bengal | FL6: Tamil Nadu | FM6: Tamil Nadu | FN6: Maharashtra | FO6: Delhi | FP6: Telangana | FQ6: Telangana | FR6: Maharashtra | FS6: Maharashtra | FT6: West Bengal | FU6: West Bengal | FV6: Karnataka | FW6: Telangana | FX6: Tamil Nadu | FY6: West Bengal | FZ6: Karnataka | GA6: Telangana | GB6: Tamil Nadu | GC6: West Bengal | GD6: West Bengal | GE6: Maharashtra | GF6: Telangana | GG6: Telangana | GH6: Delhi | GI6: Maharashtra | GJ6: Tamil Nadu | GK6: West Bengal | GL6: West Bengal | GM6: Delhi | GN6: Tamil Nadu | GO6: Telangana | GP6: West Bengal | GQ6: Delhi | GR6: Delhi | GS6: Maharashtra | GT6: Karnataka | GU6: Maharashtra | GV6: West Bengal | GW6: Telangana | GX6: Delhi | GY6: West Bengal | GZ6: Karnataka | HA6: Telangana | HB6: Karnataka | HC6: Telangana | HD6: Tamil Nadu | HE6: West Bengal | HF6: Delhi | HG6: West Bengal | HH6: Maharashtra | HI6: Delhi | HJ6: Telangana | HK6: Tamil Nadu | HL6: Karnataka | HM6: Telangana | HN6: Delhi | HO6: Telangana | HP6: Telangana | HQ6: Maharashtra | HR6: Tamil Nadu | HS6: Karnataka | HT6: Delhi | HU6: Delhi | HV6: Karnataka | HW6: Delhi | HX6: Telangana | HY6: West Bengal | HZ6: Delhi | IA6: Maharashtra | IB6: Delhi | IC6: Maharashtra | ID6: Telangana | IE6: Telangana | IF6: Maharashtra | IG6: West Bengal | IH6: Karnataka | II6: Maharashtra | IJ6: Telangana | IK6: Maharashtra | IL6: Delhi | IM6: Tamil Nadu | IN6: Delhi | IO6: West Bengal | IP6: West Bengal | IQ6: Tamil Nadu | IR6: Telangana | IS6: West Bengal | IT6: Delhi | IU6: Tamil Nadu | IV6: West Bengal | IW6: Tamil Nadu | IX6: Karnataka | IY6: Telangana | IZ6: Delhi | JA6: West Bengal | JB6: Karnataka | JC6: Karnataka | JD6: Tamil Nadu | JE6: Delhi | JF6: Delhi | JG6: Maharashtra | JH6: Telangana | JI6: Karnataka | JJ6: Delhi | JK6: Tamil Nadu | JL6: Maharashtra | JM6: Karnataka | JN6: Maharashtra | JO6: Tamil Nadu | JP6: Telangana | JQ6: West Bengal | JR6: Maharashtra | JS6: West Bengal | JT6: Maharashtra | JU6: Tamil Nadu | JV6: West Bengal | JW6: West Bengal | JX6: West Bengal | JY6: Telangana | JZ6: Delhi | KA6: Tamil Nadu | KB6: Tamil Nadu | KC6: Karnataka | KD6: Karnataka | KE6: West Bengal | KF6: Telangana | KG6: Telangana | KH6: Tamil Nadu | KI6: Telangana | KJ6: Delhi | KK6: Telangana | KL6: Tamil Nadu | KM6: Telangana | KN6: Telangana | KO6: Tamil Nadu | KP6: Delhi | KQ6: Delhi | KR6: Maharashtra | KS6: Delhi | KT6: Tamil Nadu | KU6: Tamil Nadu | KV6: Delhi | KW6: Tamil Nadu | KX6: Tamil Nadu | KY6: West Bengal | KZ6: Maharashtra | LA6: Maharashtra | LB6: Karnataka | LC6: Tamil Nadu | LD6: West Bengal | LE6: Tamil Nadu | LF6: Delhi | LG6: West Bengal | LH6: Delhi | LI6: Karnataka | LJ6: Tamil Nadu | LK6: West Bengal | LL6: Tamil Nadu | LM6: Delhi | LN6: Delhi | LO6: Maharashtra | LP6: Maharashtra | LQ6: Maharashtra | LR6: Maharashtra | LS6: Maharashtra | LT6: Delhi | LU6: Tamil Nadu | LV6: Karnataka | LW6: Maharashtra | LX6: West Bengal | LY6: Tamil Nadu | LZ6: Tamil Nadu | MA6: West Bengal | MB6: Maharashtra | MC6: Tamil Nadu | MD6: Tamil Nadu | ME6: Karnataka | MF6: Karnataka | MG6: Karnataka | MH6: Tamil Nadu | MI6: Telangana | MJ6: West Bengal | MK6: West Bengal | ML6: West Bengal | MM6: Delhi | MN6: Tamil Nadu | MO6: Tamil Nadu | MP6: Telangana | MQ6: Delhi | MR6: West Bengal | MS6: Maharashtra | MT6: West Bengal | MU6: Telangana | MV6: Maharashtra | MW6: Delhi | MX6: Telangana | MY6: Delhi | MZ6: Tamil Nadu | NA6: West Bengal | NB6: West Bengal | NC6: Delhi | ND6: Telangana | NE6: Tamil Nadu | NF6: Tamil Nadu | NG6: West Bengal | NH6: Delhi | NI6: Delhi
A7: Sales Channel | B7: Mobile App | C7: Website | D7: Marketplace | E7: Website | F7: Marketplace | G7: Website | H7: Mobile App | I7: Website | J7: Website | K7: Website | L7: Mobile App | M7: Website | N7: Mobile App | O7: Marketplace | P7: Website | Q7: Mobile App | R7: Mobile App | S7: Website | T7: Marketplace | U7: Mobile App | V7: Website | W7: Marketplace | X7: Mobile App | Y7: Mobile App | Z7: Marketplace | AA7: Marketplace | AB7: Website | AC7: Website | AD7: Mobile App | AE7: Marketplace | AF7: Marketplace | AG7: Marketplace | AH7: Mobile App | AI7: Marketplace | AJ7: Marketplace | AK7: Mobile App | AL7: Website | AM7: Website | AN7: Mobile App | AO7: Marketplace | AP7: Mobile App | AQ7: Website | AR7: Website | AS7: Mobile App | AT7: Mobile App | AU7: Website | AV7: Mobile App | AW7: Website | AX7: Mobile App | AY7: Mobile App | AZ7: Website | BA7: Mobile App | BB7: Website | BC7: Website | BD7: Mobile App | BE7: Mobile App | BF7: Website | BG7: Marketplace | BH7: Website | BI7: Marketplace | BJ7: Marketplace | BK7: Mobile App | BL7: Mobile App | BM7: Website | BN7: Marketplace | BO7: Mobile App | BP7: Mobile App | BQ7: Mobile App | BR7: Mobile App | BS7: Mobile App | BT7: Marketplace | BU7: Marketplace | BV7: Marketplace | BW7: Marketplace | BX7: Marketplace | BY7: Mobile App | BZ7: Marketplace | CA7: Website | CB7: Mobile App | CC7: Marketplace | CD7: Marketplace | CE7: Marketplace | CF7: Mobile App | CG7: Mobile App | CH7: Mobile App | CI7: Marketplace | CJ7: Mobile App | CK7: Marketplace | CL7: Marketplace | CM7: Mobile App | CN7: Website | CO7: Website | CP7: Mobile App | CQ7: Website | CR7: Marketplace | CS7: Marketplace | CT7: Mobile App | CU7: Website | CV7: Marketplace | CW7: Mobile App | CX7: Website | CY7: Website | CZ7: Marketplace | DA7: Marketplace | DB7: Mobile App | DC7: Marketplace | DD7: Website | DE7: Marketplace | DF7: Mobile App | DG7: Mobile App | DH7: Mobile App | DI7: Website | DJ7: Website | DK7: Website | DL7: Website | DM7: Website | DN7: Marketplace | DO7: Website | DP7: Website | DQ7: Marketplace | DR7: Website | DS7: Mobile App | DT7: Website | DU7: Website | DV7: Mobile App | DW7: Mobile App | DX7: Mobile App | DY7: Mobile App | DZ7: Mobile App | EA7: Marketplace | EB7: Mobile App | EC7: Mobile App | ED7: Marketplace | EE7: Marketplace | EF7: Website | EG7: Marketplace | EH7: Website | EI7: Marketplace | EJ7: Marketplace | EK7: Website | EL7: Marketplace | EM7: Website | EN7: Mobile App | EO7: Marketplace | EP7: Website | EQ7: Marketplace | ER7: Website | ES7: Website | ET7: Mobile App | EU7: Mobile App | EV7: Website | EW7: Marketplace | EX7: Website | EY7: Website | EZ7: Marketplace | FA7: Marketplace | FB7: Marketplace | FC7: Website | FD7: Website | FE7: Mobile App | FF7: Website | FG7: Marketplace | FH7: Mobile App | FI7: Mobile App | FJ7: Marketplace | FK7: Mobile App | FL7: Mobile App | FM7: Marketplace | FN7: Mobile App | FO7: Mobile App | FP7: Marketplace | FQ7: Mobile App | FR7: Mobile App | FS7: Marketplace | FT7: Marketplace | FU7: Marketplace | FV7: Marketplace | FW7: Website | FX7: Mobile App | FY7: Marketplace | FZ7: Mobile App | GA7: Mobile App | GB7: Website | GC7: Marketplace | GD7: Marketplace | GE7: Mobile App | GF7: Website | GG7: Website | GH7: Mobile App | GI7: Marketplace | GJ7: Website | GK7: Marketplace | GL7: Website | GM7: Mobile App | GN7: Website | GO7: Website | GP7: Mobile App | GQ7: Website | GR7: Website | GS7: Mobile App | GT7: Mobile App | GU7: Marketplace | GV7: Mobile App | GW7: Mobile App | GX7: Marketplace | GY7: Mobile App | GZ7: Website | HA7: Website | HB7: Mobile App | HC7: Marketplace | HD7: Marketplace | HE7: Mobile App | HF7: Marketplace | HG7: Website | HH7: Marketplace | HI7: Marketplace | HJ7: Mobile App | HK7: Mobile App | HL7: Website | HM7: Website | HN7: Mobile App | HO7: Website | HP7: Mobile App | HQ7: Website | HR7: Mobile App | HS7: Marketplace | HT7: Marketplace | HU7: Marketplace | HV7: Marketplace | HW7: Marketplace | HX7: Website | HY7: Website | HZ7: Marketplace | IA7: Marketplace | IB7: Website | IC7: Website | ID7: Marketplace | IE7: Website | IF7: Marketplace | IG7: Mobile App | IH7: Website | II7: Mobile App | IJ7: Marketplace | IK7: Website | IL7: Website | IM7: Website | IN7: Mobile App | IO7: Website | IP7: Mobile App | IQ7: Website | IR7: Mobile App | IS7: Marketplace | IT7: Website | IU7: Marketplace | IV7: Marketplace | IW7: Website | IX7: Marketplace | IY7: Mobile App | IZ7: Website | JA7: Website | JB7: Marketplace | JC7: Website | JD7: Marketplace | JE7: Mobile App | JF7: Marketplace | JG7: Marketplace | JH7: Website | JI7: Marketplace | JJ7: Website | JK7: Mobile App | JL7: Website | JM7: Mobile App | JN7: Mobile App | JO7: Mobile App | JP7: Website | JQ7: Marketplace | JR7: Mobile App | JS7: Mobile App | JT7: Mobile App | JU7: Mobile App | JV7: Marketplace | JW7: Marketplace | JX7: Website | JY7: Mobile App | JZ7: Marketplace | KA7: Marketplace | KB7: Marketplace | KC7: Marketplace | KD7: Mobile App | KE7: Marketplace | KF7: Mobile App | KG7: Marketplace | KH7: Website | KI7: Mobile App | KJ7: Website | KK7: Marketplace | KL7: Mobile App | KM7: Marketplace | KN7: Mobile App | KO7: Website | KP7: Website | KQ7: Mobile App | KR7: Marketplace | KS7: Website | KT7: Website | KU7: Website | KV7: Website | KW7: Website | KX7: Website | KY7: Website | KZ7: Marketplace | LA7: Website | LB7: Website | LC7: Website | LD7: Mobile App | LE7: Website | LF7: Marketplace | LG7: Mobile App | LH7: Website | LI7: Website | LJ7: Website | LK7: Marketplace | LL7: Website | LM7: Website | LN7: Marketplace | LO7: Website | LP7: Marketplace | LQ7: Mobile App | LR7: Website | LS7: Mobile App | LT7: Website | LU7: Website | LV7: Marketplace | LW7: Website | LX7: Website | LY7: Marketplace | LZ7: Marketplace | MA7: Website | MB7: Mobile App | MC7: Mobile App | MD7: Website | ME7: Marketplace | MF7: Mobile App | MG7: Marketplace | MH7: Website | MI7: Mobile App | MJ7: Mobile App | MK7: Website | ML7: Website | MM7: Website | MN7: Marketplace | MO7: Marketplace | MP7: Marketplace | MQ7: Mobile App | MR7: Marketplace | MS7: Marketplace | MT7: Mobile App | MU7: Mobile App | MV7: Website | MW7: Mobile App | MX7: Website | MY7: Marketplace | MZ7: Website | NA7: Mobile App | NB7: Mobile App | NC7: Website | ND7: Mobile App | NE7: Marketplace | NF7: Mobile App | NG7: Website | NH7: Marketplace | NI7: Marketplace
A8: Payment Method | B8: Credit Card | C8: Debit Card | D8: Debit Card | E8: Cash on Delivery | F8: Credit Card | G8: Net Banking | H8: UPI | I8: Credit Card | J8: Debit Card | K8: Cash on Delivery | L8: Cash on Delivery | M8: UPI | N8: Cash on Delivery | O8: Cash on Delivery | P8: Credit Card | Q8: Net Banking | R8: UPI | S8: Credit Card | T8: Net Banking | U8: Credit Card | V8: Credit Card | W8: Cash on Delivery | X8: Net Banking | Y8: UPI | Z8: UPI | AA8: Net Banking | AB8: Cash on Delivery | AC8: Debit Card | AD8: Credit Card | AE8: Cash on Delivery | AF8: Net Banking | AG8: Credit Card | AH8: UPI | AI8: Debit Card | AJ8: UPI | AK8: Net Banking | AL8: Credit Card | AM8: Net Banking | AN8: Credit Card | AO8: Cash on Delivery | AP8: Debit Card | AQ8: Cash on Delivery | AR8: Cash on Delivery | AS8: Net Banking | AT8: Debit Card | AU8: Credit Card | AV8: Credit Card | AW8: UPI | AX8: Credit Card | AY8: Net Banking | AZ8: Cash on Delivery | BA8: Cash on Delivery | BB8: Debit Card | BC8: Credit Card | BD8: Net Banking | BE8: Debit Card | BF8: Net Banking | BG8: Net Banking | BH8: Net Banking | BI8: Net Banking | BJ8: Credit Card | BK8: Net Banking | BL8: Cash on Delivery | BM8: Net Banking | BN8: UPI | BO8: UPI | BP8: Cash on Delivery | BQ8: Credit Card | BR8: Credit Card | BS8: Debit Card | BT8: Cash on Delivery | BU8: Net Banking | BV8: Cash on Delivery | BW8: Debit Card | BX8: Cash on Delivery | BY8: Debit Card | BZ8: Credit Card | CA8: Net Banking | CB8: Debit Card | CC8: UPI | CD8: Credit Card | CE8: UPI | CF8: Credit Card | CG8: Net Banking | CH8: UPI | CI8: Credit Card | CJ8: Net Banking | CK8: Debit Card | CL8: Net Banking | CM8: Debit Card | CN8: Credit Card | CO8: Net Banking | CP8: Net Banking | CQ8: Credit Card | CR8: Net Banking | CS8: Debit Card | CT8: Net Banking | CU8: Cash on Delivery | CV8: Debit Card | CW8: UPI | CX8: Credit Card | CY8: Cash on Delivery | CZ8: Cash on Delivery | DA8: Credit Card | DB8: Credit Card | DC8: Debit Card | DD8: Net Banking | DE8: Credit Card | DF8: Net Banking | DG8: UPI | DH8: Cash on Delivery | DI8: Net Banking | DJ8: Cash on Delivery | DK8: Net Banking | DL8: UPI | DM8: Credit Card | DN8: UPI | DO8: Credit Card | DP8: Credit Card | DQ8: Cash on Delivery | DR8: UPI | DS8: Net Banking | DT8: UPI | DU8: Cash on Delivery | DV8: Credit Card | DW8: Debit Card | DX8: Debit Card | DY8: Cash on Delivery | DZ8: Net Banking | EA8: Net Banking | EB8: Debit Card | EC8: Net Banking | ED8: Debit Card | EE8: Credit Card | EF8: Cash on Delivery | EG8: Net Banking | EH8: Debit Card | EI8: UPI | EJ8: Net Banking | EK8: Credit Card | EL8: Credit Card | EM8: UPI | EN8: Net Banking | EO8: Debit Card | EP8: Credit Card | EQ8: Debit Card | ER8: Credit Card | ES8: Debit Card | ET8: UPI | EU8: Cash on Delivery | EV8: UPI | EW8: UPI | EX8: Cash on Delivery | EY8: Cash on Delivery | EZ8: Net Banking | FA8: Net Banking | FB8: UPI | FC8: Credit Card | FD8: Credit Card | FE8: Net Banking | FF8: Net Banking | FG8: Credit Card | FH8: Credit Card | FI8: Credit Card | FJ8: Debit Card | FK8: Cash on Delivery | FL8: Net Banking | FM8: Credit Card | FN8: UPI | FO8: Credit Card | FP8: Debit Card | FQ8: UPI | FR8: Debit Card | FS8: Debit Card | FT8: Cash on Delivery | FU8: Cash on Delivery | FV8: Debit Card | FW8: Debit Card | FX8: Cash on Delivery | FY8: UPI | FZ8: Cash on Delivery | GA8: Net Banking | GB8: Cash on Delivery | GC8: UPI | GD8: Net Banking | GE8: Credit Card | GF8: UPI | GG8: Net Banking | GH8: Net Banking | GI8: Credit Card | GJ8: Net Banking | GK8: UPI | GL8: UPI | GM8: Debit Card | GN8: Credit Card | GO8: Net Banking | GP8: UPI | GQ8: Credit Card | GR8: UPI | GS8: Debit Card | GT8: Net Banking | GU8: UPI | GV8: Credit Card | GW8: UPI | GX8: UPI | GY8: Cash on Delivery | GZ8: Cash on Delivery | HA8: Debit Card | HB8: Net Banking | HC8: Credit Card | HD8: Credit Card | HE8: UPI | HF8: Net Banking | HG8: Debit Card | HH8: Cash on Delivery | HI8: Net Banking | HJ8: Credit Card | HK8: Debit Card | HL8: Net Banking | HM8: Cash on Delivery | HN8: Net Banking | HO8: UPI | HP8: Net Banking | HQ8: Debit Card | HR8: UPI | HS8: Cash on Delivery | HT8: UPI | HU8: Cash on Delivery | HV8: UPI | HW8: Net Banking | HX8: Cash on Delivery | HY8: Cash on Delivery | HZ8: Debit Card | IA8: Credit Card | IB8: UPI | IC8: Debit Card | ID8: Credit Card | IE8: Credit Card | IF8: UPI | IG8: UPI | IH8: Credit Card | II8: Debit Card | IJ8: Credit Card | IK8: Debit Card | IL8: Cash on Delivery | IM8: Net Banking | IN8: Cash on Delivery | IO8: Credit Card | IP8: Debit Card | IQ8: Debit Card | IR8: Cash on Delivery | IS8: Net Banking | IT8: Net Banking | IU8: Debit Card | IV8: UPI | IW8: Credit Card | IX8: Credit Card | IY8: Cash on Delivery | IZ8: Debit Card | JA8: Credit Card | JB8: Credit Card | JC8: Debit Card | JD8: Cash on Delivery | JE8: Cash on Delivery | JF8: Net Banking | JG8: Cash on Delivery | JH8: UPI | JI8: Cash on Delivery | JJ8: UPI | JK8: Net Banking | JL8: Debit Card | JM8: UPI | JN8: UPI | JO8: Net Banking | JP8: Net Banking | JQ8: Net Banking | JR8: Debit Card | JS8: Cash on Delivery | JT8: Cash on Delivery | JU8: Credit Card | JV8: UPI | JW8: Net Banking | JX8: UPI | JY8: UPI | JZ8: Cash on Delivery | KA8: Credit Card | KB8: Cash on Delivery | KC8: Net Banking | KD8: Debit Card | KE8: Cash on Delivery | KF8: Debit Card | KG8: Net Banking | KH8: UPI | KI8: Cash on Delivery | KJ8: Net Banking | KK8: Cash on Delivery | KL8: Cash on Delivery | KM8: Credit Card | KN8: Credit Card | KO8: Cash on Delivery | KP8: Credit Card | KQ8: Net Banking | KR8: Credit Card | KS8: Cash on Delivery | KT8: UPI | KU8: Net Banking | KV8: Net Banking | KW8: Net Banking | KX8: UPI | KY8: Net Banking | KZ8: Credit Card | LA8: Cash on Delivery | LB8: Debit Card | LC8: Cash on Delivery | LD8: Credit Card | LE8: UPI | LF8: UPI | LG8: UPI | LH8: Net Banking | LI8: UPI | LJ8: Debit Card | LK8: UPI | LL8: Debit Card | LM8: Credit Card | LN8: Debit Card | LO8: Credit Card | LP8: Net Banking | LQ8: UPI | LR8: Cash on Delivery | LS8: Credit Card | LT8: UPI | LU8: Debit Card | LV8: Cash on Delivery | LW8: Debit Card | LX8: UPI | LY8: Credit Card | LZ8: Credit Card | MA8: Cash on Delivery | MB8: Net Banking | MC8: Net Banking | MD8: Cash on Delivery | ME8: Credit Card | MF8: Cash on Delivery | MG8: Credit Card | MH8: Net Banking | MI8: Debit Card | MJ8: Credit Card | MK8: UPI | ML8: Debit Card | MM8: Cash on Delivery | MN8: Net Banking | MO8: UPI | MP8: Cash on Delivery | MQ8: Credit Card | MR8: Credit Card | MS8: Cash on Delivery | MT8: UPI | MU8: UPI | MV8: Debit Card | MW8: Net Banking | MX8: Net Banking | MY8: Debit Card | MZ8: Credit Card | NA8: Cash on Delivery | NB8: UPI | NC8: UPI | ND8: UPI | NE8: Debit Card | NF8: Net Banking | NG8: Net Banking | NH8: Credit Card | NI8: Net Banking
A9: Product Category | B9: Home & Kitchen | C9: Sports | D9: Fashion | E9: Sports | F9: Fashion | G9: Home & Kitchen | H9: Fashion | I9: Fashion | J9: Fashion | K9: Electronics | L9: Electronics | M9: Electronics | N9: Home & Kitchen | O9: Sports | P9: Beauty | Q9: Fashion | R9: Fashion | S9: Home & Kitchen | T9: Fashion | U9: Electronics | V9: Beauty | W9: Books | X9: Fashion | Y9: Electronics | Z9: Books | AA9: Beauty | AB9: Books | AC9: Electronics | AD9: Sports | AE9: Sports | AF9: Books | AG9: Home & Kitchen | AH9: Books | AI9: Fashion | AJ9: Fashion | AK9: Sports | AL9: Home & Kitchen | AM9: Electronics | AN9: Fashion | AO9: Sports | AP9: Beauty | AQ9: Sports | AR9: Fashion | AS9: Fashion | AT9: Sports | AU9: Electronics | AV9: Books | AW9: Fashion | AX9: Sports | AY9: Sports | AZ9: Books | BA9: Beauty | BB9: Electronics | BC9: Beauty | BD9: Books | BE9: Books | BF9: Beauty | BG9: Books | BH9: Sports | BI9: Books | BJ9: Sports | BK9: Home & Kitchen | BL9: Books | BM9: Beauty | BN9: Fashion | BO9: Books | BP9: Fashion | BQ9: Sports | BR9: Home & Kitchen | BS9: Electronics | BT9: Home & Kitchen | BU9: Books | BV9: Fashion | BW9: Fashion | BX9: Fashion | BY9: Beauty | BZ9: Sports | CA9: Electronics | CB9: Books | CC9: Beauty | CD9: Electronics | CE9: Fashion | CF9: Fashion | CG9: Electronics | CH9: Sports | CI9: Electronics | CJ9: Beauty | CK9: Beauty | CL9: Electronics | CM9: Beauty | CN9: Beauty | CO9: Sports | CP9: Beauty | CQ9: Home & Kitchen | CR9: Books | CS9: Fashion | CT9: Home & Kitchen | CU9: Sports | CV9: Electronics | CW9: Beauty | CX9: Sports | CY9: Beauty | CZ9: Electronics | DA9: Sports | DB9: Sports | DC9: Sports | DD9: Books | DE9: Beauty | DF9: Books | DG9: Fashion | DH9: Fashion | DI9: Beauty | DJ9: Books | DK9: Electronics | DL9: Sports | DM9: Sports | DN9: Beauty | DO9: Fashion | DP9: Fashion | DQ9: Sports | DR9: Beauty | DS9: Books | DT9: Fashion | DU9: Books | DV9: Fashion | DW9: Home & Kitchen | DX9: Fashion | DY9: Beauty | DZ9: Beauty | EA9: Books | EB9: Fashion | EC9: Electronics | ED9: Books | EE9: Home & Kitchen | EF9: Books | EG9: Books | EH9: Fashion | EI9: Home & Kitchen | EJ9: Books | EK9: Electronics | EL9: Electronics | EM9: Beauty | EN9: Home & Kitchen | EO9: Beauty | EP9: Books | EQ9: Home & Kitchen | ER9: Electronics | ES9: Electronics | ET9: Fashion | EU9: Home & Kitchen | EV9: Books | EW9: Beauty | EX9: Beauty | EY9: Books | EZ9: Sports | FA9: Fashion | FB9: Beauty | FC9: Fashion | FD9: Home & Kitchen | FE9: Electronics | FF9: Fashion | FG9: Beauty | FH9: Fashion | FI9: Sports | FJ9: Fashion | FK9: Home & Kitchen | FL9: Electronics | FM9: Fashion | FN9: Beauty | FO9: Fashion | FP9: Beauty | FQ9: Home & Kitchen | FR9: Beauty | FS9: Electronics | FT9: Beauty | FU9: Beauty | FV9: Electronics | FW9: Books | FX9: Fashion | FY9: Beauty | FZ9: Electronics | GA9: Home & Kitchen | GB9: Electronics | GC9: Home & Kitchen | GD9: Books | GE9: Fashion | GF9: Electronics | GG9: Beauty | GH9: Electronics | GI9: Home & Kitchen | GJ9: Electronics | GK9: Sports | GL9: Electronics | GM9: Sports | GN9: Books | GO9: Electronics | GP9: Sports | GQ9: Home & Kitchen | GR9: Electronics | GS9: Books | GT9: Electronics | GU9: Electronics | GV9: Books | GW9: Home & Kitchen | GX9: Fashion | GY9: Beauty | GZ9: Books | HA9: Electronics | HB9: Books | HC9: Home & Kitchen | HD9: Books | HE9: Beauty | HF9: Electronics | HG9: Beauty | HH9: Beauty | HI9: Fashion | HJ9: Fashion | HK9: Fashion | HL9: Beauty | HM9: Home & Kitchen | HN9: Beauty | HO9: Fashion | HP9: Fashion | HQ9: Fashion | HR9: Books | HS9: Electronics | HT9: Beauty | HU9: Sports | HV9: Beauty | HW9: Fashion | HX9: Electronics | HY9: Fashion | HZ9: Home & Kitchen | IA9: Fashion | IB9: Beauty | IC9: Beauty | ID9: Sports | IE9: Electronics | IF9: Sports | IG9: Books | IH9: Books | II9: Books | IJ9: Home & Kitchen | IK9: Beauty | IL9: Home & Kitchen | IM9: Fashion | IN9: Fashion | IO9: Fashion | IP9: Books | IQ9: Sports | IR9: Fashion | IS9: Books | IT9: Books | IU9: Beauty | IV9: Electronics | IW9: Home & Kitchen | IX9: Beauty | IY9: Books | IZ9: Sports | JA9: Electronics | JB9: Books | JC9: Electronics | JD9: Electronics | JE9: Sports | JF9: Beauty | JG9: Sports | JH9: Books | JI9: Beauty | JJ9: Beauty | JK9: Beauty | JL9: Beauty | JM9: Sports | JN9: Beauty | JO9: Books | JP9: Home & Kitchen | JQ9: Electronics | JR9: Fashion | JS9: Electronics | JT9: Sports | JU9: Electronics | JV9: Beauty | JW9: Sports | JX9: Home & Kitchen | JY9: Books | JZ9: Fashion | KA9: Sports | KB9: Beauty | KC9: Fashion | KD9: Books | KE9: Books | KF9: Fashion | KG9: Fashion | KH9: Books | KI9: Beauty | KJ9: Electronics | KK9: Books | KL9: Sports | KM9: Electronics | KN9: Electronics | KO9: Electronics | KP9: Beauty | KQ9: Books | KR9: Books | KS9: Sports | KT9: Beauty | KU9: Fashion | KV9: Home & Kitchen | KW9: Beauty | KX9: Electronics | KY9: Fashion | KZ9: Fashion | LA9: Fashion | LB9: Beauty | LC9: Beauty | LD9: Electronics | LE9: Sports | LF9: Electronics | LG9: Electronics | LH9: Home & Kitchen | LI9: Sports | LJ9: Home & Kitchen | LK9: Electronics | LL9: Beauty | LM9: Fashion | LN9: Home & Kitchen | LO9: Beauty | LP9: Sports | LQ9: Beauty | LR9: Beauty | LS9: Beauty | LT9: Beauty | LU9: Home & Kitchen | LV9: Electronics | LW9: Home & Kitchen | LX9: Beauty | LY9: Beauty | LZ9: Sports | MA9: Electronics | MB9: Electronics | MC9: Fashion | MD9: Books | ME9: Fashion | MF9: Sports | MG9: Home & Kitchen | MH9: Electronics | MI9: Books | MJ9: Beauty | MK9: Sports | ML9: Electronics | MM9: Sports | MN9: Fashion | MO9: Home & Kitchen | MP9: Home & Kitchen | MQ9: Books | MR9: Sports | MS9: Fashion | MT9: Sports | MU9: Electronics | MV9: Books | MW9: Home & Kitchen | MX9: Electronics | MY9: Beauty | MZ9: Books | NA9: Fashion | NB9: Electronics | NC9: Electronics | ND9: Books | NE9: Books | NF9: Beauty | NG9: Fashion | NH9: Sports | NI9: Fashion
A10: Product Name | B10: Mixer Grinder | C10: Football | D10: Sneakers | E10: Yoga Mat | F10: Jacket | G10: Bedsheet | H10: Sneakers | I10: Sneakers | J10: T-Shirt | K10: Headphones | L10: Headphones | M10: Smartwatch | N10: Bedsheet | O10: Yoga Mat | P10: Shampoo | Q10: Jacket | R10: Jacket | S10: Curtains | T10: Jacket | U10: Smartwatch | V10: Lipstick | W10: Fiction Novel | X10: Sneakers | Y10: Smartwatch | Z10: Comics | AA10: Perfume | AB10: Fiction Novel | AC10: Smartwatch | AD10: Football | AE10: Cricket Bat | AF10: Textbook | AG10: Bedsheet | AH10: Comics | AI10: T-Shirt | AJ10: T-Shirt | AK10: Football | AL10: Curtains | AM10: Laptop | AN10: T-Shirt | AO10: Football | AP10: Face Cream | AQ10: Football | AR10: T-Shirt | AS10: T-Shirt | AT10: Cricket Bat | AU10: Smartwatch | AV10: Textbook | AW10: Jeans | AX10: Football | AY10: Cricket Bat | AZ10: Textbook | BA10: Face Cream | BB10: Headphones | BC10: Face Cream | BD10: Textbook | BE10: Fiction Novel | BF10: Face Cream | BG10: Textbook | BH10: Yoga Mat | BI10: Textbook | BJ10: Yoga Mat | BK10: Bedsheet | BL10: Biography | BM10: Face Cream | BN10: T-Shirt | BO10: Textbook | BP10: Jacket | BQ10: Cricket Bat | BR10: Curtains | BS10: Smartphone | BT10: Bedsheet | BU10: Fiction Novel | BV10: Jacket | BW10: Sneakers | BX10: Sneakers | BY10: Lipstick | BZ10: Football | CA10: Laptop | CB10: Textbook | CC10: Lipstick | CD10: Headphones | CE10: Jeans | CF10: Jacket | CG10: Laptop | CH10: Football | CI10: Headphones | CJ10: Lipstick | CK10: Perfume | CL10: Headphones | CM10: Perfume | CN10: Perfume | CO10: Yoga Mat | CP10: Shampoo | CQ10: Bedsheet | CR10: Comics | CS10: Jacket | CT10: Mixer Grinder | CU10: Football | CV10: Laptop | CW10: Perfume | CX10: Yoga Mat | CY10: Lipstick | CZ10: Smartphone | DA10: Yoga Mat | DB10: Cricket Bat | DC10: Dumbbells | DD10: Textbook | DE10: Perfume | DF10: Fiction Novel | DG10: T-Shirt | DH10: Sneakers | DI10: Shampoo | DJ10: Textbook | DK10: Laptop | DL10: Dumbbells | DM10: Cricket Bat | DN10: Face Cream | DO10: T-Shirt | DP10: Jacket | DQ10: Cricket Bat | DR10: Lipstick | DS10: Textbook | DT10: Sneakers | DU10: Fiction Novel | DV10: T-Shirt | DW10: Bedsheet | DX10: Jacket | DY10: Shampoo | DZ10: Shampoo | EA10: Comics | EB10: Jacket | EC10: Smartwatch | ED10: Fiction Novel | EE10: Curtains | EF10: Comics | EG10: Textbook | EH10: T-Shirt | EI10: Mixer Grinder | EJ10: Textbook | EK10: Smartwatch | EL10: Laptop | EM10: Lipstick | EN10: Bedsheet | EO10: Lipstick | EP10: Comics | EQ10: Mixer Grinder | ER10: Laptop | ES10: Smartphone | ET10: T-Shirt | EU10: Mixer Grinder | EV10: Fiction Novel | EW10: Shampoo | EX10: Face Cream | EY10: Textbook | EZ10: Football | FA10: Sneakers | FB10: Lipstick | FC10: Jeans | FD10: Bedsheet | FE10: Laptop | FF10: Jeans | FG10: Shampoo | FH10: Sneakers | FI10: Cricket Bat | FJ10: Sneakers | FK10: Bedsheet | FL10: Headphones | FM10: Jacket | FN10: Face Cream | FO10: Jacket | FP10: Lipstick | FQ10: Bedsheet | FR10: Shampoo | FS10: Smartwatch | FT10: Lipstick | FU10: Perfume | FV10: Smartwatch | FW10: Comics | FX10: Jeans | FY10: Shampoo | FZ10: Smartphone | GA10: Cookware Set | GB10: Smartwatch | GC10: Cookware Set | GD10: Comics | GE10: Jeans | GF10: Smartwatch | GG10: Shampoo | GH10: Headphones | GI10: Mixer Grinder | GJ10: Smartwatch | GK10: Cricket Bat | GL10: Laptop | GM10: Football | GN10: Biography | GO10: Headphones | GP10: Dumbbells | GQ10: Curtains | GR10: Smartwatch | GS10: Comics | GT10: Laptop | GU10: Smartphone | GV10: Comics | GW10: Curtains | GX10: T-Shirt | GY10: Perfume | GZ10: Textbook | HA10: Laptop | HB10: Biography | HC10: Cookware Set | HD10: Comics | HE10: Shampoo | HF10: Smartwatch | HG10: Shampoo | HH10: Face Cream | HI10: Jacket | HJ10: Jeans | HK10: T-Shirt | HL10: Perfume | HM10: Mixer Grinder | HN10: Face Cream | HO10: Sneakers | HP10: Jeans | HQ10: Sneakers | HR10: Comics | HS10: Laptop | HT10: Perfume | HU10: Cricket Bat | HV10: Shampoo | HW10: Jacket | HX10: Smartwatch | HY10: Jeans | HZ10: Cookware Set | IA10: Jacket | IB10: Perfume | IC10: Face Cream | ID10: Dumbbells | IE10: Smartphone | IF10: Dumbbells | IG10: Fiction Novel | IH10: Biography | II10: Fiction Novel | IJ10: Mixer Grinder | IK10: Shampoo | IL10: Bedsheet | IM10: T-Shirt | IN10: T-Shirt | IO10: Jeans | IP10: Biography | IQ10: Cricket Bat | IR10: T-Shirt | IS10: Textbook | IT10: Fiction Novel | IU10: Shampoo | IV10: Smartwatch | IW10: Bedsheet | IX10: Lipstick | IY10: Textbook | IZ10: Dumbbells | JA10: Headphones | JB10: Fiction Novel | JC10: Laptop | JD10: Smartphone | JE10: Yoga Mat | JF10: Perfume | JG10: Cricket Bat | JH10: Fiction Novel | JI10: Face Cream | JJ10: Perfume | JK10: Perfume | JL10: Shampoo | JM10: Football | JN10: Face Cream | JO10: Biography | JP10: Cookware Set | JQ10: Headphones | JR10: Sneakers | JS10: Smartwatch | JT10: Football | JU10: Smartwatch | JV10: Lipstick | JW10: Yoga Mat | JX10: Mixer Grinder | JY10: Textbook | JZ10: Sneakers | KA10: Yoga Mat | KB10: Shampoo | KC10: T-Shirt | KD10: Fiction Novel | KE10: Fiction Novel | KF10: T-Shirt | KG10: Sneakers | KH10: Comics | KI10: Shampoo | KJ10: Laptop | KK10: Textbook | KL10: Yoga Mat | KM10: Laptop | KN10: Smartphone | KO10: Laptop | KP10: Shampoo | KQ10: Fiction Novel | KR10: Comics | KS10: Dumbbells | KT10: Lipstick | KU10: T-Shirt | KV10: Curtains | KW10: Face Cream | KX10: Smartphone | KY10: Sneakers | KZ10: Jacket | LA10: T-Shirt | LB10: Perfume | LC10: Perfume | LD10: Headphones | LE10: Yoga Mat | LF10: Smartwatch | LG10: Laptop | LH10: Bedsheet | LI10: Yoga Mat | LJ10: Cookware Set | LK10: Smartwatch | LL10: Shampoo | LM10: Jacket | LN10: Bedsheet | LO10: Shampoo | LP10: Yoga Mat | LQ10: Face Cream | LR10: Lipstick | LS10: Face Cream | LT10: Perfume | LU10: Curtains | LV10: Smartwatch | LW10: Mixer Grinder | LX10: Lipstick | LY10: Perfume | LZ10: Cricket Bat | MA10: Smartwatch | MB10: Headphones | MC10: Jeans | MD10: Fiction Novel | ME10: Sneakers | MF10: Dumbbells | MG10: Mixer Grinder | MH10: Smartphone | MI10: Fiction Novel | MJ10: Face Cream | MK10: Football | ML10: Headphones | MM10: Yoga Mat | MN10: Jeans | MO10: Bedsheet | MP10: Bedsheet | MQ10: Comics | MR10: Yoga Mat | MS10: T-Shirt | MT10: Yoga Mat | MU10: Headphones | MV10: Biography | MW10: Bedsheet | MX10: Laptop | MY10: Shampoo | MZ10: Textbook | NA10: Sneakers | NB10: Laptop | NC10: Smartphone | ND10: Biography | NE10: Comics | NF10: Perfume | NG10: Jacket | NH10: Yoga Mat | NI10: Jeans
A11: Brand | B11: BrandA | C11: BrandD | D11: BrandE | E11: BrandA | F11: BrandA | G11: BrandE | H11: BrandC | I11: BrandB | J11: BrandD | K11: BrandB | L11: BrandE | M11: BrandA | N11: BrandA | O11: BrandD | P11: BrandA | Q11: BrandA | R11: BrandD | S11: BrandD | T11: BrandE | U11: BrandA | V11: BrandA | W11: BrandE | X11: BrandC | Y11: BrandC | Z11: BrandC | AA11: BrandE | AB11: BrandA | AC11: BrandE | AD11: BrandE | AE11: BrandC | AF11: BrandB | AG11: BrandA | AH11: BrandC | AI11: BrandB | AJ11: BrandB | AK11: BrandD | AL11: BrandA | AM11: BrandB | AN11: BrandC | AO11: BrandD | AP11: BrandA | AQ11: BrandE | AR11: BrandC | AS11: BrandB | AT11: BrandB | AU11: BrandC | AV11: BrandB | AW11: BrandD | AX11: BrandA | AY11: BrandD | AZ11: BrandE | BA11: BrandA | BB11: BrandA | BC11: BrandC | BD11: BrandC | BE11: BrandE | BF11: BrandE | BG11: BrandC | BH11: BrandC | BI11: BrandD | BJ11: BrandB | BK11: BrandC | BL11: BrandC | BM11: BrandD | BN11: BrandD | BO11: BrandE | BP11: BrandE | BQ11: BrandB | BR11: BrandB | BS11: BrandA | BT11: BrandE | BU11: BrandC | BV11: BrandE | BW11: BrandC | BX11: BrandE | BY11: BrandD | BZ11: BrandB | CA11: BrandB | CB11: BrandA | CC11: BrandE | CD11: BrandD | CE11: BrandC | CF11: BrandB | CG11: BrandB | CH11: BrandD | CI11: BrandE | CJ11: BrandE | CK11: BrandA | CL11: BrandB | CM11: BrandE | CN11: BrandD | CO11: BrandC | CP11: BrandD | CQ11: BrandB | CR11: BrandD | CS11: BrandA | CT11: BrandB | CU11: BrandA | CV11: BrandB | CW11: BrandC | CX11: BrandA | CY11: BrandB | CZ11: BrandE | DA11: BrandA | DB11: BrandA | DC11: BrandC | DD11: BrandD | DE11: BrandB | DF11: BrandB | DG11: BrandE | DH11: BrandE | DI11: BrandB | DJ11: BrandE | DK11: BrandC | DL11: BrandB | DM11: BrandE | DN11: BrandB | DO11: BrandD | DP11: BrandA | DQ11: BrandB | DR11: BrandA | DS11: BrandE | DT11: BrandA | DU11: BrandB | DV11: BrandD | DW11: BrandB | DX11: BrandE | DY11: BrandA | DZ11: BrandC | EA11: BrandB | EB11: BrandD | EC11: BrandE | ED11: BrandA | EE11: BrandE | EF11: BrandB | EG11: BrandE | EH11: BrandA | EI11: BrandB | EJ11: BrandE | EK11: BrandD | EL11: BrandB | EM11: BrandB | EN11: BrandC | EO11: BrandA | EP11: BrandC | EQ11: BrandE | ER11: BrandD | ES11: BrandC | ET11: BrandB | EU11: BrandE | EV11: BrandE | EW11: BrandC | EX11: BrandC | EY11: BrandD | EZ11: BrandA | FA11: BrandC | FB11: BrandC | FC11: BrandE | FD11: BrandA | FE11: BrandB | FF11: BrandD | FG11: BrandD | FH11: BrandC | FI11: BrandC | FJ11: BrandA | FK11: BrandC | FL11: BrandE | FM11: BrandB | FN11: BrandA | FO11: BrandB | FP11: BrandB | FQ11: BrandE | FR11: BrandA | FS11: BrandA | FT11: BrandA | FU11: BrandA | FV11: BrandE | FW11: BrandC | FX11: BrandB | FY11: BrandA | FZ11: BrandC | GA11: BrandC | GB11: BrandB | GC11: BrandE | GD11: BrandD | GE11: BrandD | GF11: BrandE | GG11: BrandD | GH11: BrandC | GI11: BrandC | GJ11: BrandA | GK11: BrandE | GL11: BrandB | GM11: BrandA | GN11: BrandA | GO11: BrandD | GP11: BrandC | GQ11: BrandA | GR11: BrandA | GS11: BrandB | GT11: BrandC | GU11: BrandE | GV11: BrandA | GW11: BrandB | GX11: BrandE | GY11: BrandB | GZ11: BrandC | HA11: BrandB | HB11: BrandC | HC11: BrandE | HD11: BrandD | HE11: BrandC | HF11: BrandB | HG11: BrandC | HH11: BrandB | HI11: BrandA | HJ11: BrandC | HK11: BrandD | HL11: BrandE | HM11: BrandB | HN11: BrandC | HO11: BrandB | HP11: BrandD | HQ11: BrandE | HR11: BrandA | HS11: BrandE | HT11: BrandB | HU11: BrandE | HV11: BrandB | HW11: BrandD | HX11: BrandB | HY11: BrandC | HZ11: BrandB | IA11: BrandC | IB11: BrandE | IC11: BrandE | ID11: BrandC | IE11: BrandE | IF11: BrandA | IG11: BrandD | IH11: BrandA | II11: BrandA | IJ11: BrandD | IK11: BrandE | IL11: BrandC | IM11: BrandE | IN11: BrandB | IO11: BrandE | IP11: BrandA | IQ11: BrandA | IR11: BrandA | IS11: BrandD | IT11: BrandD | IU11: BrandC | IV11: BrandB | IW11: BrandE | IX11: BrandE | IY11: BrandC | IZ11: BrandD | JA11: BrandC | JB11: BrandE | JC11: BrandB | JD11: BrandA | JE11: BrandD | JF11: BrandC | JG11: BrandD | JH11: BrandE | JI11: BrandC | JJ11: BrandE | JK11: BrandB | JL11: BrandC | JM11: BrandB | JN11: BrandA | JO11: BrandA | JP11: BrandE | JQ11: BrandA | JR11: BrandA | JS11: BrandD | JT11: BrandB | JU11: BrandA | JV11: BrandE | JW11: BrandC | JX11: BrandC | JY11: BrandA | JZ11: BrandC | KA11: BrandC | KB11: BrandA | KC11: BrandA | KD11: BrandD | KE11: BrandE | KF11: BrandB | KG11: BrandC | KH11: BrandA | KI11: BrandE | KJ11: BrandA | KK11: BrandC | KL11: BrandB | KM11: BrandD | KN11: BrandB | KO11: BrandA | KP11: BrandA | KQ11: BrandE | KR11: BrandC | KS11: BrandC | KT11: BrandB | KU11: BrandE | KV11: BrandD | KW11: BrandE | KX11: BrandD | KY11: BrandE | KZ11: BrandE | LA11: BrandB | LB11: BrandE | LC11: BrandC | LD11: BrandB | LE11: BrandC | LF11: BrandB | LG11: BrandE | LH11: BrandE | LI11: BrandA | LJ11: BrandC | LK11: BrandA | LL11: BrandE | LM11: BrandE | LN11: BrandE | LO11: BrandD | LP11: BrandC | LQ11: BrandC | LR11: BrandE | LS11: BrandB | LT11: BrandB | LU11: BrandD | LV11: BrandD | LW11: BrandC | LX11: BrandA | LY11: BrandA | LZ11: BrandB | MA11: BrandD | MB11: BrandE | MC11: BrandC | MD11: BrandC | ME11: BrandA | MF11: BrandD | MG11: BrandE | MH11: BrandD | MI11: BrandD | MJ11: BrandC | MK11: BrandD | ML11: BrandA | MM11: BrandB | MN11: BrandB | MO11: BrandE | MP11: BrandD | MQ11: BrandC | MR11: BrandD | MS11: BrandD | MT11: BrandB | MU11: BrandB | MV11: BrandE | MW11: BrandC | MX11: BrandE | MY11: BrandA | MZ11: BrandE | NA11: BrandC | NB11: BrandD | NC11: BrandD | ND11: BrandC | NE11: BrandC | NF11: BrandC | NG11: BrandA | NH11: BrandD | NI11: BrandE
A12: Units Sold | B12: 7 | C12: 9 | D12: 6 | E12: 1 | F12: 7 | G12: 3 | H12: 5 | I12: 4 | J12: 5 | K12: 5 | L12: 6 | M12: 6 | N12: 8 | O12: 8 | P12: 9 | Q12: 8 | R12: 2 | S12: 1 | T12: 2 | U12: 2 | V12: 3 | W12: 7 | X12: 2 | Y12: 1 | Z12: 6 | AA12: 9 | AB12: 3 | AC12: 6 | AD12: 3 | AE12: 1 | AF12: 5 | AG12: 4 | AH12: 7 | AI12: 6 | AJ12: 7 | AK12: 5 | AL12: 4 | AM12: 7 | AN12: 7 | AO12: 6 | AP12: 8 | AQ12: 4 | AR12: 5 | AS12: 4 | AT12: 1 | AU12: 8 | AV12: 1 | AW12: 5 | AX12: 6 | AY12: 6 | AZ12: 3 | BA12: 5 | BB12: 8 | BC12: 2 | BD12: 6 | BE12: 9 | BF12: 8 | BG12: 8 | BH12: 7 | BI12: 6 | BJ12: 2 | BK12: 2 | BL12: 8 | BM12: 1 | BN12: 6 | BO12: 6 | BP12: 4 | BQ12: 3 | BR12: 3 | BS12: 1 | BT12: 3 | BU12: 4 | BV12: 5 | BW12: 3 | BX12: 5 | BY12: 3 | BZ12: 6 | CA12: 6 | CB12: 8 | CC12: 2 | CD12: 1 | CE12: 4 | CF12: 7 | CG12: 3 | CH12: 5 | CI12: 3 | CJ12: 9 | CK12: 4 | CL12: 3 | CM12: 2 | CN12: 9 | CO12: 4 | CP12: 3 | CQ12: 7 | CR12: 8 | CS12: 2 | CT12: 7 | CU12: 5 | CV12: 3 | CW12: 5 | CX12: 2 | CY12: 6 | CZ12: 1 | DA12: 4 | DB12: 6 | DC12: 9 | DD12: 2 | DE12: 7 | DF12: 6 | DG12: 2 | DH12: 8 | DI12: 7 | DJ12: 5 | DK12: 5 | DL12: 7 | DM12: 9 | DN12: 9 | DO12: 9 | DP12: 6 | DQ12: 6 | DR12: 3 | DS12: 1 | DT12: 7 | DU12: 4 | DV12: 1 | DW12: 6 | DX12: 6 | DY12: 1 | DZ12: 2 | EA12: 4 | EB12: 2 | EC12: 1 | ED12: 7 | EE12: 8 | EF12: 6 | EG12: 4 | EH12: 6 | EI12: 3 | EJ12: 8 | EK12: 2 | EL12: 5 | EM12: 1 | EN12: 2 | EO12: 4 | EP12: 6 | EQ12: 8 | ER12: 8 | ES12: 6 | ET12: 4 | EU12: 8 | EV12: 8 | EW12: 1 | EX12: 4 | EY12: 4 | EZ12: 7 | FA12: 7 | FB12: 8 | FC12: 7 | FD12: 8 | FE12: 9 | FF12: 3 | FG12: 3 | FH12: 4 | FI12: 7 | FJ12: 9 | FK12: 8 | FL12: 5 | FM12: 7 | FN12: 5 | FO12: 7 | FP12: 1 | FQ12: 1 | FR12: 3 | FS12: 2 | FT12: 7 | FU12: 2 | FV12: 4 | FW12: 2 | FX12: 6 | FY12: 8 | FZ12: 4 | GA12: 5 | GB12: 4 | GC12: 3 | GD12: 5 | GE12: 9 | GF12: 7 | GG12: 8 | GH12: 8 | GI12: 8 | GJ12: 7 | GK12: 1 | GL12: 4 | GM12: 5 | GN12: 6 | GO12: 4 | GP12: 2 | GQ12: 8 | GR12: 7 | GS12: 6 | GT12: 5 | GU12: 8 | GV12: 1 | GW12: 1 | GX12: 7 | GY12: 9 | GZ12: 8 | HA12: 2 | HB12: 9 | HC12: 6 | HD12: 2 | HE12: 3 | HF12: 8 | HG12: 1 | HH12: 7 | HI12: 7 | HJ12: 1 | HK12: 8 | HL12: 4 | HM12: 5 | HN12: 2 | HO12: 3 | HP12: 3 | HQ12: 2 | HR12: 7 | HS12: 7 | HT12: 4 | HU12: 8 | HV12: 1 | HW12: 1 | HX12: 5 | HY12: 6 | HZ12: 3 | IA12: 6 | IB12: 4 | IC12: 7 | ID12: 9 | IE12: 8 | IF12: 5 | IG12: 6 | IH12: 6 | II12: 7 | IJ12: 8 | IK12: 9 | IL12: 3 | IM12: 1 | IN12: 5 | IO12: 7 | IP12: 6 | IQ12: 4 | IR12: 2 | IS12: 1 | IT12: 4 | IU12: 4 | IV12: 1 | IW12: 4 | IX12: 1 | IY12: 1 | IZ12: 1 | JA12: 8 | JB12: 8 | JC12: 2 | JD12: 7 | JE12: 8 | JF12: 7 | JG12: 5 | JH12: 9 | JI12: 7 | JJ12: 2 | JK12: 6 | JL12: 2 | JM12: 1 | JN12: 7 | JO12: 2 | JP12: 1 | JQ12: 3 | JR12: 4 | JS12: 4 | JT12: 5 | JU12: 7 | JV12: 4 | JW12: 1 | JX12: 4 | JY12: 1 | JZ12: 3 | KA12: 2 | KB12: 9 | KC12: 9 | KD12: 8 | KE12: 8 | KF12: 1 | KG12: 8 | KH12: 3 | KI12: 5 | KJ12: 5 | KK12: 8 | KL12: 8 | KM12: 6 | KN12: 6 | KO12: 2 | KP12: 6 | KQ12: 5 | KR12: 6 | KS12: 1 | KT12: 3 | KU12: 1 | KV12: 5 | KW12: 3 | KX12: 2 | KY12: 8 | KZ12: 3 | LA12: 1 | LB12: 3 | LC12: 8 | LD12: 6 | LE12: 2 | LF12: 6 | LG12: 5 | LH12: 3 | LI12: 1 | LJ12: 4 | LK12: 1 | LL12: 9 | LM12: 7 | LN12: 3 | LO12: 8 | LP12: 1 | LQ12: 1 | LR12: 8 | LS12: 6 | LT12: 9 | LU12: 9 | LV12: 6 | LW12: 8 | LX12: 3 | LY12: 3 | LZ12: 5 | MA12: 3 | MB12: 1 | MC12: 3 | MD12: 9 | ME12: 2 | MF12: 4 | MG12: 7 | MH12: 1 | MI12: 9 | MJ12: 2 | MK12: 5 | ML12: 1 | MM12: 5 | MN12: 1 | MO12: 4 | MP12: 6 | MQ12: 9 | MR12: 8 | MS12: 5 | MT12: 6 | MU12: 8 | MV12: 7 | MW12: 2 | MX12: 9 | MY12: 4 | MZ12: 8 | NA12: 7 | NB12: 5 | NC12: 7 | ND12: 5 | NE12: 8 | NF12: 6 | NG12: 5 | NH12: 9 | NI12: 1
A13: Unit Price | B13: 2843.87 | C13: 2525.23 | D13: 3474.34 | E13: 1008.79 | F13: 3511.47 | G13: 3189.55 | H13: 3030.42 | I13: 2310.83 | J13: 1098.04 | K13: 1780.66 | L13: 3205.25 | M13: 272.35 | N13: 3160.9 | O13: 1074.27 | P13: 705.59 | Q13: 595.45 | R13: 254.91 | S13: 2165.81 | T13: 990.3 | U13: 3959.31 | V13: 2361.58 | W13: 680.86 | X13: 2801.74 | Y13: 3606.31 | Z13: 3018.94 | AA13: 444.29 | AB13: 3599.15 | AC13: 3206.63 | AD13: 759.47 | AE13: 349.38 | AF13: 2295.65 | AG13: 750.74 | AH13: 3363.18 | AI13: 1529.59 | AJ13: 3664.64 | AK13: 2327.9 | AL13: 853.29 | AM13: 687.46 | AN13: 2369.42 | AO13: 3083.25 | AP13: 3158.8 | AQ13: 1211.67 | AR13: 936.35 | AS13: 214.51 | AT13: 2764.92 | AU13: 444.79 | AV13: 1769.93 | AW13: 2466.48 | AX13: 3757.87 | AY13: 1350.44 | AZ13: 2668.52 | BA13: 2534.07 | BB13: 1428.62 | BC13: 3723.19 | BD13: 3402.72 | BE13: 1012.33 | BF13: 2122.36 | BG13: 3128.25 | BH13: 319.56 | BI13: 2645.71 | BJ13: 1041.2 | BK13: 2773.21 | BL13: 3769.71 | BM13: 330.13 | BN13: 1380.66 | BO13: 1836.98 | BP13: 3612.15 | BQ13: 3854.71 | BR13: 1859.84 | BS13: 3037.61 | BT13: 2196.89 | BU13: 2220.46 | BV13: 1220.68 | BW13: 985.28 | BX13: 2291.86 | BY13: 262.25 | BZ13: 3642.91 | CA13: 751.69 | CB13: 997.34 | CC13: 2145.36 | CD13: 2883.94 | CE13: 518.56 | CF13: 1373.12 | CG13: 3879.4 | CH13: 3370.52 | CI13: 343.33 | CJ13: 1938.76 | CK13: 1611.52 | CL13: 1368.86 | CM13: 1249.94 | CN13: 501.79 | CO13: 1362.08 | CP13: 315.75 | CQ13: 3156.71 | CR13: 1683.18 | CS13: 1859.03 | CT13: 3590.34 | CU13: 181.03 | CV13: 3781.22 | CW13: 1063.01 | CX13: 564.31 | CY13: 2076.84 | CZ13: 1820.02 | DA13: 1110.59 | DB13: 2257.77 | DC13: 1206.38 | DD13: 3621.09 | DE13: 978.54 | DF13: 3554.77 | DG13: 2303.71 | DH13: 3339.68 | DI13: 2894.46 | DJ13: 2832.28 | DK13: 1398.73 | DL13: 1050.5 | DM13: 961.91 | DN13: 3450.19 | DO13: 3308.64 | DP13: 1846.21 | DQ13: 659.76 | DR13: 1621.67 | DS13: 2534.47 | DT13: 1899.45 | DU13: 3153.73 | DV13: 3990.85 | DW13: 1919.66 | DX13: 1809.29 | DY13: 912.67 | DZ13: 402.91 | EA13: 3565.41 | EB13: 1766.42 | EC13: 2063.05 | ED13: 3680.23 | EE13: 3138.72 | EF13: 652.43 | EG13: 2326.87 | EH13: 1852.67 | EI13: 3219.26 | EJ13: 2938.3 | EK13: 2808.06 | EL13: 1461.1 | EM13: 3249.11 | EN13: 764.56 | EO13: 1442.15 | EP13: 445.71 | EQ13: 1054.73 | ER13: 3346.08 | ES13: 3800.77 | ET13: 1322.72 | EU13: 1168.39 | EV13: 1227.59 | EW13: 1219.22 | EX13: 288.33 | EY13: 3718.63 | EZ13: 972.74 | FA13: 1767.02 | FB13: 187.29 | FC13: 2964.96 | FD13: 3795.01 | FE13: 3159.22 | FF13: 1357.77 | FG13: 1104.31 | FH13: 2836.21 | FI13: 174.09 | FJ13: 388.26 | FK13: 2211.17 | FL13: 2329.38 | FM13: 658.07 | FN13: 2125.75 | FO13: 898.62 | FP13: 508.81 | FQ13: 1730.41 | FR13: 778.85 | FS13: 1372.59 | FT13: 1148.65 | FU13: 487.23 | FV13: 496.18 | FW13: 894.01 | FX13: 344.65 | FY13: 2561.86 | FZ13: 1256.21 | GA13: 1227.02 | GB13: 1428.19 | GC13: 2701.77 | GD13: 3501.94 | GE13: 3072.48 | GF13: 982.56 | GG13: 953.07 | GH13: 1291.11 | GI13: 3656.59 | GJ13: 2257.55 | GK13: 2975.54 | GL13: 1719.71 | GM13: 633.43 | GN13: 809.49 | GO13: 3335.32 | GP13: 2401.63 | GQ13: 3240.98 | GR13: 3907.73 | GS13: 1477.55 | GT13: 620.13 | GU13: 3519.2 | GV13: 2250.49 | GW13: 556.53 | GX13: 324.38 | GY13: 2677.09 | GZ13: 284.52 | HA13: 3960.56 | HB13: 265.58 | HC13: 1861.43 | HD13: 601.53 | HE13: 800.89 | HF13: 1504.45 | HG13: 3082.45 | HH13: 2102.27 | HI13: 2605.92 | HJ13: 3942.92 | HK13: 1822.29 | HL13: 1868.8 | HM13: 2532.27 | HN13: 2711.66 | HO13: 240.6 | HP13: 647.32 | HQ13: 533.25 | HR13: 2472.29 | HS13: 2165.86 | HT13: 1126.3 | HU13: 2045.09 | HV13: 900.78 | HW13: 2660.56 | HX13: 3156.54 | HY13: 3197.13 | HZ13: 2469.51 | IA13: 384.88 | IB13: 1258.15 | IC13: 509.1 | ID13: 670.06 | IE13: 3784.12 | IF13: 3098.44 | IG13: 220.79 | IH13: 1936.66 | II13: 1396.71 | IJ13: 2695.39 | IK13: 2661.11 | IL13: 967.49 | IM13: 619.73 | IN13: 2850.33 | IO13: 636.59 | IP13: 257.2 | IQ13: 2547.52 | IR13: 3256.02 | IS13: 3391.76 | IT13: 2008.45 | IU13: 3143.2 | IV13: 2740.46 | IW13: 2046.51 | IX13: 2588.64 | IY13: 3251.27 | IZ13: 1681.85 | JA13: 3253.02 | JB13: 2429.26 | JC13: 788.72 | JD13: 245.03 | JE13: 2254.78 | JF13: 3383.31 | JG13: 640.82 | JH13: 3472.58 | JI13: 730.15 | JJ13: 3428.64 | JK13: 3967.1 | JL13: 2948.33 | JM13: 3171.36 | JN13: 3978.5 | JO13: 1335.36 | JP13: 1126.5 | JQ13: 464.42 | JR13: 3708.51 | JS13: 641.93 | JT13: 1853.11 | JU13: 313.51 | JV13: 2785.81 | JW13: 3625.42 | JX13: 640.37 | JY13: 3708.38 | JZ13: 1923.58 | KA13: 2071.04 | KB13: 2632.88 | KC13: 1259.77 | KD13: 1300.31 | KE13: 3581.12 | KF13: 202.49 | KG13: 1392.5 | KH13: 2284.27 | KI13: 3593.46 | KJ13: 3320.88 | KK13: 3610.33 | KL13: 3277.19 | KM13: 1628.56 | KN13: 2715.13 | KO13: 3957.02 | KP13: 1019.05 | KQ13: 1651.11 | KR13: 681.36 | KS13: 3910.66 | KT13: 487.45 | KU13: 3581.58 | KV13: 1935.68 | KW13: 1382.11 | KX13: 1984.38 | KY13: 1375.47 | KZ13: 2032.79 | LA13: 2430.36 | LB13: 1553.98 | LC13: 2993.25 | LD13: 2716.48 | LE13: 610.31 | LF13: 2354.67 | LG13: 3245.77 | LH13: 1789.86 | LI13: 2743.75 | LJ13: 1333.99 | LK13: 2044.41 | LL13: 3216.56 | LM13: 1020.23 | LN13: 2165.72 | LO13: 1297.59 | LP13: 1219.7 | LQ13: 3354.81 | LR13: 3905.57 | LS13: 1288.31 | LT13: 3740.3 | LU13: 2454.59 | LV13: 2247.37 | LW13: 437.36 | LX13: 3644.78 | LY13: 3986.78 | LZ13: 3116.22 | MA13: 1448.62 | MB13: 3775.07 | MC13: 2189.4 | MD13: 2969.7 | ME13: 3904.44 | MF13: 3871.21 | MG13: 2568.26 | MH13: 1574.59 | MI13: 3191.56 | MJ13: 1374.23 | MK13: 1480.66 | ML13: 445.38 | MM13: 2072.32 | MN13: 559.4 | MO13: 589.44 | MP13: 3773.04 | MQ13: 1890.53 | MR13: 150.72 | MS13: 2523.25 | MT13: 845 | MU13: 1160.51 | MV13: 2172.24 | MW13: 1294.84 | MX13: 775.77 | MY13: 2751.14 | MZ13: 2536.88 | NA13: 2838.06 | NB13: 977.43 | NC13: 1550.03 | ND13: 529.59 | NE13: 598.44 | NF13: 1128.91 | NG13: 1287.55 | NH13: 2190.39 | NI13: 2432.17
A14: Total Price | B14: =B12*B13 -> 19907.09 | C14: =C12*C13 -> 22727.07 | D14: =D12*D13 -> 20846.04 | E14: =E12*E13 -> 1008.79 | F14: =F12*F13 -> 24580.29 | G14: =G12*G13 -> 9568.65 | H14: =H12*H13 -> 15152.1 | I14: =I12*I13 -> 9243.32 | ... NI14: =NI12*NI13 -> 2432.17
A15: Discount % | B15: 0 | C15: 5 | D15: 15 | E15: 15 | F15: 20 | G15: 10 | H15: 10 | I15: 10 | J15: 15 | K15: 20 | L15: 0 | M15: 5 | N15: 0 | O15: 15 | P15: 10 | Q15: 5 | R15: 15 | S15: 15 | T15: 15 | U15: 5 | V15: 5 | W15: 20 | X15: 20 | Y15: 0 | Z15: 5 | AA15: 5 | AB15: 5 | AC15: 20 | AD15: 15 | AE15: 10 | AF15: 20 | AG15: 5 | AH15: 20 | AI15: 0 | AJ15: 5 | AK15: 0 | AL15: 5 | AM15: 20 | AN15: 15 | AO15: 10 | AP15: 0 | AQ15: 20 | AR15: 15 | AS15: 20 | AT15: 0 | AU15: 10 | AV15: 20 | AW15: 5 | AX15: 15 | AY15: 20 | AZ15: 5 | BA15: 10 | BB15: 10 | BC15: 5 | BD15: 15 | BE15: 20 | BF15: 0 | BG15: 15 | BH15: 10 | BI15: 10 | BJ15: 15 | BK15: 10 | BL15: 5 | BM15: 15 | BN15: 0 | BO15: 5 | BP15: 20 | BQ15: 5 | BR15: 15 | BS15: 5 | BT15: 0 | BU15: 0 | BV15: 20 | BW15: 10 | BX15: 15 | BY15: 10 | BZ15: 0 | CA15: 0 | CB15: 5 | CC15: 20 | CD15: 20 | CE15: 20 | CF15: 5 | CG15: 20 | CH15: 10 | CI15: 5 | CJ15: 20 | CK15: 10 | CL15: 10 | CM15: 10 | CN15: 5 | CO15: 15 | CP15: 20 | CQ15: 10 | CR15: 15 | CS15: 20 | CT15: 20 | CU15: 10 | CV15: 5 | CW15: 15 | CX15: 15 | CY15: 20 | CZ15: 10 | DA15: 20 | DB15: 20 | DC15: 10 | DD15: 0 | DE15: 15 | DF15: 20 | DG15: 20 | DH15: 0 | DI15: 5 | DJ15: 0 | DK15: 0 | DL15: 20 | DM15: 15 | DN15: 0 | DO15: 5 | DP15: 10 | DQ15: 0 | DR15: 0 | DS15: 5 | DT15: 15 | DU15: 0 | DV15: 0 | DW15: 5 | DX15: 0 | DY15: 0 | DZ15: 10 | EA15: 20 | EB15: 10 | EC15: 0 | ED15: 5 | EE15: 20 | EF15: 10 | EG15: 15 | EH15: 5 | EI15: 10 | EJ15: 15 | EK15: 0 | EL15: 15 | EM15: 10 | EN15: 0 | EO15: 15 | EP15: 15 | EQ15: 0 | ER15: 15 | ES15: 0 | ET15: 5 | EU15: 10 | EV15: 5 | EW15: 20 | EX15: 20 | EY15: 20 | EZ15: 0 | FA15: 15 | FB15: 5 | FC15: 5 | FD15: 5 | FE15: 20 | FF15: 5 | FG15: 15 | FH15: 20 | FI15: 10 | FJ15: 10 | FK15: 10 | FL15: 20 | FM15: 20 | FN15: 15 | FO15: 0 | FP15: 0 | FQ15: 10 | FR15: 10 | FS15: 5 | FT15: 15 | FU15: 15 | FV15: 15 | FW15: 15 | FX15: 10 | FY15: 0 | FZ15: 10 | GA15: 15 | GB15: 10 | GC15: 15 | GD15: 20 | GE15: 0 | GF15: 10 | GG15: 20 | GH15: 15 | GI15: 15 | GJ15: 10 | GK15: 15 | GL15: 15 | GM15: 20 | GN15: 5 | GO15: 20 | GP15: 0 | GQ15: 0 | GR15: 10 | GS15: 10 | GT15: 5 | GU15: 0 | GV15: 15 | GW15: 5 | GX15: 10 | GY15: 10 | GZ15: 15 | HA15: 10 | HB15: 10 | HC15: 0 | HD15: 20 | HE15: 0 | HF15: 20 | HG15: 5 | HH15: 20 | HI15: 20 | HJ15: 0 | HK15: 20 | HL15: 20 | HM15: 15 | HN15: 0 | HO15: 5 | HP15: 5 | HQ15: 0 | HR15: 10 | HS15: 0 | HT15: 20 | HU15: 10 | HV15: 5 | HW15: 10 | HX15: 20 | HY15: 10 | HZ15: 0 | IA15: 5 | IB15: 0 | IC15: 15 | ID15: 20 | IE15: 15 | IF15: 0 | IG15: 5 | IH15: 0 | II15: 20 | IJ15: 10 | IK15: 10 | IL15: 0 | IM15: 0 | IN15: 5 | IO15: 5 | IP15: 0 | IQ15: 20 | IR15: 20 | IS15: 20 | IT15: 5 | IU15: 0 | IV15: 10 | IW15: 5 | IX15: 0 | IY15: 15 | IZ15: 5 | JA15: 15 | JB15: 15 | JC15: 20 | JD15: 0 | JE15: 0 | JF15: 20 | JG15: 0 | JH15: 15 | JI15: 0 | JJ15: 10 | JK15: 0 | JL15: 15 | JM15: 20 | JN15: 20 | JO15: 5 | JP15: 15 | JQ15: 20 | JR15: 5 | JS15: 0 | JT15: 10 | JU15: 0 | JV15: 20 | JW15: 10 | JX15: 20 | JY15: 20 | JZ15: 15 | KA15: 20 | KB15: 5 | KC15: 15 | KD15: 0 | KE15: 15 | KF15: 5 | KG15: 15 | KH15: 20 | KI15: 20 | KJ15: 0 | KK15: 5 | KL15: 15 | KM15: 0 | KN15: 20 | KO15: 5 | KP15: 0 | KQ15: 20 | KR15: 15 | KS15: 5 | KT15: 5 | KU15: 15 | KV15: 20 | KW15: 10 | KX15: 10 | KY15: 15 | KZ15: 10 | LA15: 15 | LB15: 15 | LC15: 10 | LD15: 0 | LE15: 10 | LF15: 15 | LG15: 0 | LH15: 0 | LI15: 15 | LJ15: 5 | LK15: 0 | LL15: 20 | LM15: 10 | LN15: 5 | LO15: 0 | LP15: 5 | LQ15: 0 | LR15: 10 | LS15: 15 | LT15: 10 | LU15: 5 | LV15: 15 | LW15: 20 | LX15: 0 | LY15: 20 | LZ15: 10 | MA15: 10 | MB15: 10 | MC15: 20 | MD15: 10 | ME15: 10 | MF15: 10 | MG15: 10 | MH15: 5 | MI15: 20 | MJ15: 0 | MK15: 0 | ML15: 10 | MM15: 15 | MN15: 20 | MO15: 20 | MP15: 0 | MQ15: 15 | MR15: 5 | MS15: 10 | MT15: 15 | MU15: 0 | MV15: 20 | MW15: 15 | MX15: 0 | MY15: 20 | MZ15: 5 | NA15: 20 | NB15: 20 | NC15: 10 | ND15: 5 | NE15: 0 | NF15: 20 | NG15: 0 | NH15: 20 | NI15: 20
A16: Discount amount | B16: =B14*B15/100 -> 0 | C16: =C14*C15/100 -> 1136.3535 | D16: =D14*D15/100 -> 3126.906 | E16: =E14*E15/100 -> 151.3185 | F16: =F14*F15/100 -> 4916.058 | G16: =G14*G15/100 -> 956.865 | H16: =H14*H15/100 -> 1515.21 | I16: =I14*I15/100 -> 924.332 | ... NI16: =NI14*NI15/100 -> 486.434
A17: Price after discount | B17: =B14-B16 -> 19907.09 | C17: =C14-C16 -> 21590.716 | D17: =D14-D16 -> 17719.134 | E17: =E14-E16 -> 857.4715 | F17: =F14-F16 -> 19664.232 | G17: =G14-G16 -> 8611.785 | H17: =H14-H16 -> 13636.89 | I17: =I14-I16 -> 8318.988 | ... NI17: =NI14-NI16 -> 1945.736
A18: Price Category | B18: =IF(B17>=10000,"High","Low") -> High | C18: =IF(C17>=10000,"High","Low") -> High | D18: =IF(D17>=10000,"High","Low") -> High | E18: =IF(E17>=10000,"High","Low") -> Low | F18: =IF(F17>=10000,"High","Low") -> High | G18: =IF(G17>=10000,"High","Low") -> Low | H18: =IF(H17>=10000,"High","Low") -> High | I18: =IF(I17>=10000,"High","Low") -> Low | ... NI18: =IF(NI17>=10000,"High","Low") -> Low
A19: Unit Category | B19: {=_xlfn.IFS(B12>=8,"High",B12>=5,"Medium",B12<5,"Low")} -> Medium | C19: {=_xlfn.IFS(C12>=8,"High",C12>=5,"Medium",C12<5,"Low")} -> High | D19: {=_xlfn.IFS(D12>=8,"High",D12>=5,"Medium",D12<5,"Low")} -> Medium | E19: {=_xlfn.IFS(E12>=8,"High",E12>=5,"Medium",E12<5,"Low")} -> Low | F19: {=_xlfn.IFS(F12>=8,"High",F12>=5,"Medium",F12<5,"Low")} -> Medium | G19: {=_xlfn.IFS(G12>=8,"High",G12>=5,"Medium",G12<5,"Low")} -> Low | H19: {=_xlfn.IFS(H12>=8,"High",H12>=5,"Medium",H12<5,"Low")} -> Medium | I19: {=_xlfn.IFS(I12>=8,"High",I12>=5,"Medium",I12<5,"Low")} -> Low | ... NI19: {=_xlfn.IFS(NI12>=8,"High",NI12>=5,"Medium",NI12<5,"Low")} -> Low
A20: Discount Category | B20: =IF(B16>=3000,"High",IF(B16>=1500,"Medium","Low")) -> Low | C20: =IF(C16>=3000,"High",IF(C16>=1500,"Medium","Low")) -> Low | D20: =IF(D16>=3000,"High",IF(D16>=1500,"Medium","Low")) -> High | E20: =IF(E16>=3000,"High",IF(E16>=1500,"Medium","Low")) -> Low | F20: =IF(F16>=3000,"High",IF(F16>=1500,"Medium","Low")) -> High | G20: =IF(G16>=3000,"High",IF(G16>=1500,"Medium","Low")) -> Low | H20: =IF(H16>=3000,"High",IF(H16>=1500,"Medium","Low")) -> Medium | I20: =IF(I16>=3000,"High",IF(I16>=1500,"Medium","Low")) -> Low | ... NI20: =IF(NI16>=3000,"High",IF(NI16>=1500,"Medium","Low")) -> Low

Sheet Sheet5
A1: Order ID | B1: Customer ID | C1: Order Date | D1: Ship Date | E1: City | F1: State | G1: Sales Channel | H1: Payment Method | I1: Product Category | J1: Product Name | K1: Brand | L1: Units Sold | M1: Unit Price
A2: 10001 | B2: 1102 | C2: 45197 | D2: 45203 | E2: Chennai | F2: Delhi | G2: Mobile App | H2: Credit Card | I2: Home & Kitchen | J2: Mixer Grinder | K2: BrandA | L2: 7 | M2: 2843.87 | O2: Unit Price | P2: 1000
A3: 10002 | B3: 1435 | C3: 45199 | D3: 45203 | E3: Pune | F3: Tamil Nadu | G3: Website | H3: Debit Card | I3: Sports | J3: Football | K3: BrandD | L3: 9 | M3: 2525.23
A4: 10003 | B4: 1860 | C4: 45109 | D4: 45114 | E4: Chennai | F4: West Bengal | G4: Marketplace | H4: Debit Card | I4: Fashion | J4: Sneakers | K4: BrandE | L4: 6 | M4: 3474.34
A5: 10004 | B5: 1270 | C5: 45079 | D5: 45087 | E5: Bengaluru | F5: West Bengal | G5: Website | H5: Cash on Delivery | I5: Sports | J5: Yoga Mat | K5: BrandA | L5: 1 | M5: 1008.79 | O5: State | P5: West Bengal
A6: 10005 | B6: 1106 | C6: 45241 | D6: 45244 | E6: Kolkata | F6: Karnataka | G6: Marketplace | H6: Credit Card | I6: Fashion | J6: Jacket | K6: BrandA | L6: 7 | M6: 3511.47
A7: 10006 | B7: 1071 | C7: 45260 | D7: 45263 | E7: Hyderabad | F7: Telangana | G7: Website | H7: Net Banking | I7: Home & Kitchen | J7: Bedsheet | K7: BrandE | L7: 3 | M7: 3189.55
A8: 10007 | B8: 1700 | C8: 45050 | D8: 45054 | E8: Bengaluru | F8: Telangana | G8: Mobile App | H8: UPI | I8: Fashion | J8: Sneakers | K8: BrandC | L8: 5 | M8: 3030.42 | O8: Chennai | Q8: State
A9: 10008 | B9: 1020 | C9: 45040 | D9: 45041 | E9: Mumbai | F9: Delhi | G9: Website | H9: Credit Card | I9: Fashion | J9: Sneakers | K9: BrandB | L9: 4 | M9: 2310.83 | O9: Pune | Q9: Karnataka
A10: 10009 | B10: 1614 | C10: 45204 | D10: 45213 | E10: Chennai | F10: West Bengal | G10: Website | H10: Debit Card | I10: Fashion | J10: T-Shirt | K10: BrandD | L10: 5 | M10: 1098.04 | O10: Chennai
A11: 10010 | B11: 1121 | C11: 45139 | D11: 45147 | E11: Bengaluru | F11: Karnataka | G11: Website | H11: Cash on Delivery | I11: Electronics | J11: Headphones | K11: BrandB | L11: 5 | M11: 1780.66 | O11: Bengaluru
A12: 10011 | B12: 1466 | C12: 45098 | D12: 45106 | E12: Bengaluru | F12: Karnataka | G12: Mobile App | H12: Cash on Delivery | I12: Electronics | J12: Headphones | K12: BrandE | L12: 6 | M12: 3205.25 | O12: Kolkata
A13: 10012 | B13: 1214 | C13: 45214 | D13: 45220 | E13: Mumbai | F13: Tamil Nadu | G13: Website | H13: UPI | I13: Electronics | J13: Smartwatch | K13: BrandA | L13: 6 | M13: 272.35 | O13: Hyderabad
A14: 10013 | B14: 1330 | C14: 45100 | D14: 45107 | E14: Delhi | F14: Tamil Nadu | G14: Mobile App | H14: Cash on Delivery | I14: Home & Kitchen | J14: Bedsheet | K14: BrandA | L14: 8 | M14: 3160.9 | O14: Bengaluru
A15: 10014 | B15: 1458 | C15: 45039 | D15: 45045 | E15: Kolkata | F15: Karnataka | G15: Marketplace | H15: Cash on Delivery | I15: Sports | J15: Yoga Mat | K15: BrandD | L15: 8 | M15: 1074.27
A16: 10015 | B16: 1087 | C16: 45048 | D16: 45057 | E16: Hyderabad | F16: Tamil Nadu | G16: Website | H16: Credit Card | I16: Beauty | J16: Shampoo | K16: BrandA | L16: 9 | M16: 705.59
A17: 10016 | B17: 1372 | C17: 44958 | D17: 44961 | E17: Pune | F17: West Bengal | G17: Mobile App | H17: Net Banking | I17: Fashion | J17: Jacket | K17: BrandA | L17: 8 | M17: 595.45
A18: 10017 | B18: 1099 | C18: 45148 | D18: 45151 | E18: Delhi | F18: Maharashtra | G18: Mobile App | H18: UPI | I18: Fashion | J18: Jacket | K18: BrandD | L18: 2 | M18: 254.91
A19: 10018 | B19: 1871 | C19: 45045 | D19: 45048 | E19: Chennai | F19: West Bengal | G19: Website | H19: Credit Card | I19: Home & Kitchen | J19: Curtains | K19: BrandD | L19: 1 | M19: 2165.81
A20: 10019 | B20: 1663 | C20: 44965 | D20: 44968 | E20: Bengaluru | F20: Karnataka | G20: Marketplace | H20: Net Banking | I20: Fashion | J20: Jacket | K20: BrandE | L20: 2 | M20: 990.3
A21: 10020 | B21: 1130 | C21: 45194 | D21: 45203 | E21: Mumbai | F21: Karnataka | G21: Mobile App | H21: Credit Card | I21: Electronics | J21: Smartwatch | K21: BrandA | L21: 2 | M21: 3959.31
A22: 10021 | B22: 1661 | C22: 45159 | D22: 45163 | E22: Mumbai | F22: West Bengal | G22: Website | H22: Credit Card | I22: Beauty | J22: Lipstick | K22: BrandA | L22: 3 | M22: 2361.58
A23: 10022 | B23: 1308 | C23: 44944 | D23: 44951 | E23: Kolkata | F23: Tamil Nadu | G23: Marketplace | H23: Cash on Delivery | I23: Books | J23: Fiction Novel | K23: BrandE | L23: 7 | M23: 680.86
A24: 10023 | B24: 1769 | C24: 45075 | D24: 45084 | E24: Delhi | F24: Tamil Nadu | G24: Mobile App | H24: Net Banking | I24: Fashion | J24: Sneakers | K24: BrandC | L24: 2 | M24: 2801.74
A25: 10024 | B25: 1343 | C25: 45075 | D25: 45082 | E25: Pune | F25: Telangana | G25: Mobile App | H25: UPI | I25: Electronics | J25: Smartwatch | K25: BrandC | L25: 1 | M25: 3606.31
A26: 10025 | B26: 1491 | C26: 45052 | D26: 45061 | E26: Kolkata | F26: Karnataka | G26: Marketplace | H26: UPI | I26: Books | J26: Comics | K26: BrandC | L26: 6 | M26: 3018.94
... A373: 10500 | B373: 1569 | C373: 44972 | D373: 44977 | E373: Chennai | F373: Delhi | G373: Marketplace | H373: Net Banking | I373: Fashion | J373: Jeans | K373: BrandE | L373: 1 | M373: 2432.17

Sheet Sheet6
A1: Product | B1: Region | C1: Date | D1: Sales
A2: Product A | B2: North | C2: 45292 | D2: 120 | F2: Sales | G2: 200
A3: Product B | B3: South | C3: 45324 | D3: 150
A4: Product A | B4: East | C4: 45294 | D4: 200 | F4: Product | G4: Product A | I4: AND($A2="Product B",$B2="North")
A5: Product C | B5: West | C5: 45295 | D5: 90
A6: Product B | B6: North | C6: 45296 | D6: 220
A7: Product A | B7: South | C7: 45388 | D7: 130
A8: Product C | B8: North | C8: 45298 | D8: 300
A9: Product B | B9: East | C9: 45299 | D9: 80

Sheet VLOOKUP
A1: Order ID | B1: Customer ID | C1: Order Date | D1: Ship Date | E1: City | F1: State | G1: Sales Channel | H1: Payment Method | I1: Product Category | J1: Product Name | K1: Brand | L1: Units Sold | M1: Unit Price
A2: 10403 | B2: 1152 | C2: 45035 | D2: 45037 | E2: Delhi | F2: Karnataka | G2: Website | H2: UPI | I2: Sports | J2: Yoga Mat | K2: BrandA | L2: 1 | M2: 2743.75 | O2: Order ID | P2: Unit Price
A3: 10406 | B3: 1895 | C3: 45195 | D3: 45204 | E3: Delhi | F3: West Bengal | G3: Marketplace | H3: UPI | I3: Electronics | J3: Smartwatch | K3: BrandA | L3: 1 | M3: 2044.41 | O3: 10102 | P3: =VLOOKUP(O3,A1:M373,13,0) -> 1859.03
A4: 10460 | B4: 1515 | C4: 45215 | D4: 45221 | E4: Pune | F4: West Bengal | G4: Website | H4: Debit Card | I4: Electronics | J4: Headphones | K4: BrandA | L4: 1 | M4: 445.38
A5: 10020 | B5: 1130 | C5: 45194 | D5: 45203 | E5: Mumbai | F5: Karnataka | G5: Mobile App | H5: Credit Card | I5: Electronics | J5: Smartwatch | K5: BrandA | L5: 2 | M5: 3959.31 | O5: Order ID | P5: Product Name
A6: 10102 | B6: 1161 | C6: 44996 | D6: 45002 | E6: Kolkata | F6: Maharashtra | G6: Marketplace | H6: Debit Card | I6: Fashion | J6: Jacket | K6: BrandA | L6: 2 | M6: 1859.03 | O6: 10350 | P6: =VLOOKUP(O6,A1:J373,10,0) -> Textbook
A7: 10108 | B7: 1815 | C7: 45037 | D7: 45045 | E7: Chennai | F7: West Bengal | G7: Website | H7: Credit Card | I7: Sports | J7: Yoga Mat | K7: BrandA | L7: 2 | M7: 564.31
A8: 10004 | B8: 1270 | C8: 45079 | D8: 45087 | E8: Bengaluru | F8: West Bengal | G8: Website | H8: Cash on Delivery | I8: Sports | J8: Yoga Mat | K8: BrandA | L8: 1 | M8: 1008.79
A9: 10073 | B9: 1564 | C9: 45055 | D9: 45063 | E9: Hyderabad | F9: Delhi | G9: Mobile App | H9: Debit Card | I9: Electronics | J9: Smartphone | K9: BrandA | L9: 1 | M9: 3037.61
A10: 10138 | B10: 1128 | C10: 45088 | D10: 45093 | E10: Pune | F10: West Bengal | G10: Mobile App | H10: Cash on Delivery | I10: Beauty | J10: Shampoo | K10: BrandA | L10: 1 | M10: 912.67
A11: 10232 | B11: 1639 | C11: 44962 | D11: 44969 | E11: Pune | F11: West Bengal | G11: Mobile App | H11: Credit Card | I11: Books | J11: Comics | K11: BrandA | L11: 1 | M11: 2250.49
A12: 10350 | B12: 1640 | C12: 45180 | D12: 45185 | E12: Chennai | F12: Telangana | G12: Mobile App | H12: UPI | I12: Books | J12: Textbook | K12: BrandA | L12: 1 | M12: 3708.38
A13: 10190 | B13: 1857 | C13: 45185 | D13: 45187 | E13: Bengaluru | F13: Maharashtra | G13: Marketplace | H13: Debit Card | I13: Electronics | J13: Smartwatch | K13: BrandA | L13: 2 | M13: 1372.59
A14: 10192 | B14: 1891 | C14: 45039 | D14: 45042 | E14: Chennai | F14: West Bengal | G14: Marketplace | H14: Cash on Delivery | I14: Beauty | J14: Perfume | K14: BrandA | L14: 2 | M14: 487.23
A15: 10305 | B15: 1438 | C15: 44991 | D15: 44993 | E15: Mumbai | F15: Telangana | G15: Mobile App | H15: Cash on Delivery | I15: Fashion | J15: T-Shirt | K15: BrandA | L15: 2 | M15: 3256.02
A16: 10332 | B16: 1954 | C16: 44946 | D16: 44955 | E16: Chennai | F16: Tamil Nadu | G16: Mobile App | H16: Net Banking | I16: Books | J16: Biography | K16: BrandA | L16: 2 | M16: 1335.36
A17: 10372 | B17: 1651 | C17: 45164 | D17: 45167 | E17: Delhi | F17: Tamil Nadu | G17: Website | H17: Cash on Delivery | I17: Electronics | J17: Laptop | K17: BrandA | L17: 2 | M17: 3957.02
A18: 10444 | B18: 1437 | C18: 44960 | D18: 44969 | E18: Hyderabad | F18: Karnataka | G18: Marketplace | H18: Credit Card | I18: Fashion | J18: Sneakers | K18: BrandA | L18: 2 | M18: 3904.44
... A373: 10486 | B373: 1115 | C373: 45068 | D373: 45077 | E373: Delhi | F373: Telangana | G373: Website | H373: Net Banking | I373: Electronics | J373: Laptop | K373: BrandE | L373: 9 | M373: 775.77
